Workbook

Sheet F-375
B2: UNIDAD DE FINANZAS DAEM
B3: LEY SEP
B4: ESCUELA: F-375 JORGE GONZALEZ BASTIAS - C.C. 2 - 2002
B5: DIRECTOR: FLOR BRAVO JARA
B6: SECTOR: | C6: NIRIVILO
B7: RBD 3489-4
B8: FECHA | C8: SOL | D8: OC | E8: DP | F8: CATEGORIA | G8: DETALLE | H8: INGRESOS | I8: GASTOS | J8: SALDO
G9: SALDO SEP 2025 | H9: ='[1]F-375'!$J$112 -> 17978.8 | J9: =+H9-I9 -> 17978.8
B10: ENERO
F11: SUBVENCION | G11: SUBVENCION | H11: =SUBVENCION!C8+SUBVENCION!D8 -> 6709442 | J11: =+J9+H11-I11 -> 6727420.8
F12: REMUNERACIONES | G12: REMUNERACIONES | I12: 5401335 | J12: =+J11+H12-I12 -> 1326085.8 | K12: ENERO | L12: INGRESOS | M12: 10% ADM | N12: RR.HH. | O12: BNS Y SERV | P12: SALDO
J13: =+J12+H13-I13 -> 1326085.8 | L13: =+H11 -> 6709442 | M13: =+L13*10% -> 670944.2 | N13: =+I12 -> 5401335 | O13: =SUM(I13:I14) -> 0 | P13: =+L13-M13-N13-O13 -> 637162.8
J14: =+J13+H14-I14 -> 1326085.8
B15: FEBRERO
F16: SUBVENCION | G16: SUBVENCION | H16: =SUBVENCION!E8+SUBVENCION!F8 -> 7112717 | J16: =J14+H16-I16 -> 8438802.8 | K16: FEBRERO | L16: INGRESOS | M16: 10% ADM | N16: RR.HH. | O16: BNS Y SERV | P16: SALDO
F17: REMUNERACIONES | G17: REMUNERACIONES | I17: 5863538 | J17: =J16+H17-I17 -> 2575264.8 | L17: =+H16 -> 7112717 | M17: =+L17*10% -> 711271.7 | N17: =+I17 -> 5863538 | O17: 0 | P17: =+L17-M17-N17-O17 -> 537907.3
B18: MARZO
F19: SUBVENCION | G19: SUBVENCION | H19: =SUBVENCION!G8+SUBVENCION!H8 -> 6843635 | J19: =J17+H19-I19 -> 9418899.8 | K19: MARZO | L19: INGRESOS | M19: 10% ADM | N19: RR.HH. | O19: BNS Y SERV | P19: SALDO
F20: REMUNERACIONES | G20: REMUNERACIONES | I20: 3700552 | J20: =J19+H20-I20 -> 5718347.8 | L20: =+H19 -> 6843635 | M20: =+L20*10% -> 684363.5 | N20: =+I20 -> 3700552 | O20: =SUM(I21:I28) -> 1982873 | P20: =+L20-M20-N20-O20 -> 475846.5
B21: 46090 | C21: 3 | D21: 74 | E21: 257 | F21: MATERIALES ENSEÑANZA | G21: LIBRERÍA | I21: 208500 | J21: =J20+H21-I21 -> 5509847.8
B22: 46090 | C22: 4 | D22: 75 | E22: 267 | F22: MATERIALES ENSEÑANZA | G22: LIBRERÍA | I22: 209649 | J22: =J21+H22-I22 -> 5300198.8
B23: 46090 | C23: 5 | D23: 76 | E23: 271 | F23: INSUMO COMPUTACIONALES | G23: TINTAS | I23: 191120 | J23: =J22+H23-I23 -> 5109078.8
B24: 46100 | C24: 6 | D24: 145 | E24: 410 | F24: MATERIALES ENSEÑANZA | G24: LIBRERÍA | I24: 209400 | J24: =J23+H24-I24 -> 4899678.8
B25: 46100 | C25: 7 | D25: 146 | E25: 382 | F25: MATERIALES ENSEÑANZA | G25: LIBRERÍA | I25: 209901 | J25: =J24+H25-I25 -> 4689777.8
B26: 46101 | C26: 8 | D26: 147 | E26: 599 | F26: COLACIONES | G26: COLACIONES | I26: 103360 | J26: =J25+H26-I26 -> 4586417.8
B27: 46111 | C27: 10 | D27: ABASTECIMIENTO | E27: NULA | F27: TRANSPORTE | G27: TRANSPORTE | J27: =J26+H27-I27 -> 4586417.8
B28: 46101 | C28: 9 | D28: 2321-145-AG26 | E28: 1035 | F28: MATERIALES ENSEÑANZA | G28: INSTRUMENTOS MUSICALES | I28: 850943 | J28: =J27+H28-I28 -> 3735474.8
B29: ABRIL
F30: SUBVENCION | G30: SUBVENCION | H30: =SUBVENCION!I8+SUBVENCION!J8 -> 6180358 | J30: =J28+H30-I30 -> 9915832.8 | K30: ABRIL | L30: INGRESOS | M30: 10% ADM | N30: RR.HH. | O30: BNS Y SERV | P30: SALDO
F31: REMUNERACIONES | G31: REMUNERACIONES | I31: 4257476 | J31: =J30+H31-I31 -> 5658356.8 | L31: =+H30 -> 6180358 | M31: =+L31*10% -> 618035.8 | N31: =+I31 -> 4257476 | O31: =SUM(I32:I35) -> 538661 | P31: =+L31-M31-N31-O31 -> 766185.2
B32: 45768 | C32: 13 | D32: 326 | E32: 744 | F32: EQUIPO DE OFICINA | G32: IMPRESORA | I32: 187000 | J32: =J31+H32-I32 -> 5471356.8
B33: 46147 | C33: 16 | D33: 389 | E33: 599 | F33: COLACIONES | G33: COLACIONES | I33: 144660 | J33: =J32+H33-I33 -> 5326696.8
B34: 46133 | C34: 14 | D34: 483 | E34: 745 | F34: MATERIALES ENSEÑANZA | G34: LIBRERÍA | I34: 207001 | J34: =J33+H34-I34 -> 5119695.8
J35: =J34+H35-I35 -> 5119695.8
J36: =J35+H36-I36 -> 5119695.8
B37: MAYO
F38: SUBVENCION | G38: SUBVENCION | H38: =SUBVENCION!K8+SUBVENCION!L8 -> 6212352 | J38: =J36+H38-I38 -> 11332048 | K38: MAYO | L38: INGRESOS | M38: 10% ADM | N38: RR.HH. | O38: BNS Y SERV | P38: SALDO
F39: REMUNERACIONES | G39: REMUNERACIONES | I39: 4243795 | J39: =J38+H39-I39 -> 7088252.8 | L39: =+H38 -> 6212352 | M39: =+L39*10% -> 621235.2 | N39: =+I39 -> 4243795 | O39: =+I40+I41+I42+I43 -> 624429 | P39: =+L39-M39-N39-O39 -> 722892.8
B40: 46156 | C40: 19 | D40: 451 | E40: 747 | F40: COLACIONES | G40: COLACIONES | I40: 178040 | J40: =J39+H40-I40 -> 6910212.8
B41: 46160 | C41: 17 | D41: 484 | F41: INSUMO COMPUTACIONALES | G41: INSUMO COMPUTACIONALES | I41: 179980 | J41: =J40+H41-I41 -> 6730232.8
B42: 29-05--26 | C42: 21 | D42: 515 | E42: 1021 | F42: MATERIALES ENSEÑANZA | G42: LIBRERÍA | I42: =174668+36811 -> 211479 | J42: =J41+H42-I42 -> 6518753.8
B43: 46169 | C43: 20 | D43: 491 | E43: 1076 | F43: MATERIALES ENSEÑANZA | G43: LIENZO | I43: 54930 | J43: =J42+H43-I43 -> 6463823.8
J44: =J43+H44-I44 -> 6463823.8
J45: =J44+H45-I45 -> 6463823.8
B46: JUNIO
F47: SUBVENCION | G47: SUBVENCION | H47: =SUBVENCION!M8+SUBVENCION!N8 -> 5427751 | J47: =J45+H47-I47 -> 11891575 | K47: JUNIO | L47: INGRESOS | M47: 10% ADM | N47: RR.HH. | O47: BNS Y SERV | P47: SALDO
F48: REMUNERACIONES | G48: REMUNERACIONES | I48: 4316590 | J48: =J47+H48-I48 -> 7574984.8 | L48: =+H47 -> 5427751 | M48: =+L48*10% -> 542775.1 | N48: =+I48 -> 4316590 | O48: =+I49+I50+I51 -> 261450 | P48: =+L48-M48-N48-O48 -> 306935.9
B49: 46182 | C49: 22 | D49: 559 | E49: 982 | F49: TEXTILES | G49: GENEROS | I49: 81000 | J49: =J48+H49-I49 -> 7493984.8
B50: 46184 | C50: 24 | D50: 577 | E50: 958 | F50: INSUMO COMPUTACIONALES | G50: TINTAS | I50: 180450 | J50: =J49+H50-I50 -> 7313534.8
J51: =J50+H51-I51 -> 7313534.8
J52: =J51+H52-I52 -> 7313534.8
B53: JULIO
F54: SUBVENCION | G54: SUBVENCION | H54: =+SUBVENCION!O8+SUBVENCION!P8 -> 6141394 | J54: =J52+H54-I54 -> 13454929 | K54: JULIO | L54: INGRESOS | M54: 10% ADM | N54: RR.HH. | O54: BNS Y SERV | P54: SALDO
F55: REMUNERACIONES | G55: REMUNERACIONES | I55: 4130617 | J55: =J54+H55-I55 -> 9324311.8 | L55: =+H54 -> 6141394 | M55: =+L55*10% -> 614139.4 | N55: =+I55 -> 4130617 | O55: =I56+I57 -> 210900 | P55: =+L55-M55-N55-O55 -> 1185737.6
B56: 46210 | C56: 25 | D56: 628 | F56: MATERIAL DE OFICINA | G56: RESMAS | I56: 210900 | J56: =J55+H56-I56 -> 9113411.8
J57: =J56+H57-I57 -> 9113411.8
B58: AGOSTO
F59: SUBVENCION | G59: SUBVENCION | H59: =+SUBVENCION!Q8+SUBVENCION!R8 -> 6160631 | J59: =J57+H59-I59 -> 15274043 | K59: AGOSTO | L59: INGRESOS | M59: 10% ADM | N59: RR.HH. | O59: BNS Y SERV | P59: SALDO
F60: REMUNERACIONES | G60: REMUNERACIONES | I60: 5248731 | J60: =J59+H60-I60 -> 10025312 | L60: =+H59 -> 6160631 | M60: =+L60*10% -> 616063.1 | N60: =+I60 -> 5248731 | O60: =SUM(I61:I63) -> 634842 | P60: =+L60-M60-N60-O60 -> -339005.1
B61: 46252 | C61: 28 | D61: 822 | E61: 1354 | F61: MATERIAL ENSEÑANZA | G61: INSUMO OFICINA | I61: 207177 | J61: =J60+H61-I61 -> 9818134.8
B62: 46252 | C62: 30 | D62: 823 | E62: 1355 | F62: COLACIONES | G62: INSUMOS CONVIVENCIA | I62: 213666 | J62: =J61+H62-I62 -> 9604468.8
B63: 46258 | C63: 34 | D63: 856 | E63: PP | F63: INSUMO COMPUTACIONALES | G63: MATERIAL TECNOLOGICO | I63: 213999 | J63: =J62+H63-I63 -> 9390469.8
B64: SEPTIEMRBE
F65: SUBVENCION | G65: SUBVENCION | H65: =+SUBVENCION!S8+SUBVENCION!T8 -> 6178841 | J65: =J63+H65-I65 -> 15569311 | K65: SEPTIEMBRE | L65: INGRESOS | M65: 10% ADM | N65: RR.HH. | O65: BNS Y SERV | P65: SALDO
F66: REMUNERACIONES | G66: REMUNERACIONES | I66: 5700250 | J66: =J65+H66-I66 -> 9869060.8 | L66: =+H65 -> 6178841 | M66: =+L66*10% -> 617884.1 | N66: =+I66 -> 5700250 | O66: =+I67+I68 -> 214010 | P66: =+L66-M66-N66-O66 -> -353303.1
B67: 46275 | C67: 36 | D67: 962 | F67: MATERIAL ENSEÑANZA | G67: INSUMOS LIBRERÍA | I67: 214010 | J67: =J66+H67-I67 -> 9655050.8
J68: =J67+H68-I68 -> 9655050.8
B70: OCTUBRE
F71: SUBVENCION | G71: SUBVENCION | H71: =+SUBVENCION!U8+SUBVENCION!V8 -> 0 | J71: =+J68+H71-I71 -> 9655050.8 | K71: OCTUBRE | L71: INGRESOS | M71: 10% ADM | N71: RR.HH. | O71: BNS Y SERV | P71: SALDO
F72: REMUNERACIONES | G72: REMUNERACIONES | J72: =+J71+H72-I72 -> 9655050.8 | L72: =+H71 -> 0 | M72: =+L72*10% -> 0 | N72: =+I72 -> 0 | O72: =+I73+I74+I75+I76+I77+I82 -> 21400 | P72: =+L72-M72-N72-O72 -> -21400
B73: 46296 | C73: 37 | D73: 999 | F73: COLACIONES | G73: COLACIONES | I73: 21400 | J73: =+J72+H73-I73 -> 9633650.8
J74: =+J73+H74-I74 -> 9633650.8
J75: =+J74+H75-I75 -> 9633650.8
J76: =+J75+H76-I76 -> 9633650.8
J77: =+J76+H77-I77 -> 9633650.8
J78: =+J77+H78-I78 -> 9633650.8
J79: =+J78+H79-I79 -> 9633650.8
J80: =+J79+H80-I80 -> 9633650.8
J81: =+J80+H81-I81 -> 9633650.8
J82: =+J81+H82-I82 -> 9633650.8
B83: NOVIEMBRE
F84: SUBVENCION | G84: SUBVENCION | H84: =+SUBVENCION!W8+SUBVENCION!X8 -> 0 | J84: =+J82+H84-I84 -> 9633650.8 | K84: NOVIEMBRE | L84: INGRESOS | M84: 10% ADM | N84: RR.HH. | O84: BNS Y SERV | P84: SALDO
F85: REMUNERACIONES | G85: REMUNERACIONES | J85: =+J84+H85-I85 -> 9633650.8 | L85: =+H84 -> 0 | M85: =+L85*10% -> 0 | N85: =+I85 -> 0 | O85: =I86+I87+I88+I89++I90+I91 -> 0 | P85: =+L85-M85-N85-O85 -> 0
J86: =+J85+H86-I86 -> 9633650.8
J87: =+J86+H87-I87 -> 9633650.8
J88: =+J87+H88-I88 -> 9633650.8
J89: =+J88+H89-I89 -> 9633650.8
J90: =+J89+H90-I90 -> 9633650.8
J91: =+J90+H91-I91 -> 9633650.8
B92: DICIEMBRE
F93: SUBVENCION | G93: SUBVENCION | H93: =+SUBVENCION!Y8+SUBVENCION!Z8 -> 0 | J93: =+J91+H93-I93 -> 9633650.8 | K93: DICIEMBRE | L93: INGRESOS | M93: 10% ADM | N93: RR.HH. | O93: BNS Y SERV | P93: SALDO
F94: REMUNERACIONES | G94: REMUNERACIONES | J94: =+J93+H94-I94 -> 9633650.8 | L94: =+H93 -> 0 | M94: =+L94*10% -> 0 | N94: =+I94 -> 0 | O94: =+I95+I96+I97+I98 -> 0 | P94: =+L94-M94-N94-O94 -> 0
J95: =+J94+H95-I95 -> 9633650.8
J96: =+J95+H96-I96 -> 9633650.8
J97: =+J96+H97-I97 -> 9633650.8
J98: =+J97+H98-I98 -> 9633650.8
F99: AC 10% | G99: AC 10% | H99: =(H11+H16+H19+H30+H38+H47+H54+H59+H65+H71+H84+H93)*-10% -> -5696712.1 | J99: =+J98+H99-I99 -> 3936938.7 | K99: ANUAL | L99: INGRESOS | M99: 10% ADM | N99: RR.HH. | O99: BNS Y SERV | P99: SALDO
B100: x | C100: x | G100: TOTAL | H100: =SUM(H9:H99) -> 51288388 | I100: =SUM(I11:I99) -> 47351449 | J100: =+H100-I100 -> 3936938.7 | L100: =+H11+H16+H19+H30+H38+H47+H54+H59+H65+H71+H84+H93 -> 56967121 | M100: =L100*10% -> 5696712.1 | N100: =+I12+I17+I20+I31+I39+I48+I55+I60+I66+I72+I85+I94 -> 42862884 | O100: =+I21+I22+I23+I24+I25+I26+I28+I32+I33+I34+I40+I41+I42+I43+I49+I50+I56+I61+I62+I63+I67 -> 4467165 | P100: =+L100-M100-N100-O100 -> 3940359.9
L102: =SUM(L12:L94) -> 56967121 | M102: =SUM(M12:M94) -> 5696712.1 | N102: =SUM(N12:N94) -> 42862884 | O102: =SUM(O12:O94) -> 4488565 | P102: =+P13+P17+P20+P31+P39+P48+P55+P60+P66+P72+P85+P94 -> 3918959.9
G104: EJECUCION | H104: INGRESOS | I104: GASTOS | J104: %
...

Sheet G-389
B2: UNIDAD DE FINANZAS DAEM
B3: LEY SEP
B4: ESCUELA: G-389 ADELAIDA RIQUELME MEZA C.C.
B5: DIRECTOR: CLAUDIO SOTO BELTRAN
B6: SECTOR: LA PITIGUA
B7: RBD: 3502
B8: FECHA | C8: SOL | D8: OC | E8: DP | F8: CATEGORIA | G8: DETALLE | H8: INGRESOS | I8: GASTOS | J8: SALDO
G9: SALDO SEP 2025 | H9: ='[1]G-389'!$J$89 -> -60562.8 | J9: =+H9-I9 -> -60562.8
B10: ENERO
F11: SUBVENCION | G11: SUBVENCION | H11: =SUBVENCION!C15+SUBVENCION!D15 -> 951328 | J11: =H11-I11 -> 951328 | K11: ENERO | L11: INGRESOS | M11: 10% ADM | N11: RR.HH. | O11: BNS Y SERV | P11: SALDO
F12: REMUNERACIONES | G12: REMUNERACIONES | I12: 724618 | J12: =+J11+H12-I12 -> 226710 | L12: =+H11 -> 951328 | M12: =+L12*10% -> 95132.8 | N12: =+I12 -> 724618 | O12: 0 | P12: =+L12-M12-N12-O12 -> 131577.2
B13: FEBRERO
F14: SUBVENCION | G14: SUBVENCION | H14: =SUBVENCION!E15+SUBVENCION!F15 -> 1008141 | J14: =+J12+H14-I14 -> 1234851 | K14: FEBRERO | L14: INGRESOS | M14: 10% ADM | N14: RR.HH. | O14: BNS Y SERV | P14: SALDO
F15: REMUNERACIONES | G15: REMUNERACIONES | I15: 813283 | J15: =+J14+H15-I15 -> 421568 | L15: =+H14 -> 1008141 | M15: =+L15*10% -> 100814.1 | N15: =+I15 -> 813283 | O15: 0 | P15: =+L15-M15-N15-O15 -> 94043.9
B16: MARZO
F17: SUBVENCION | G17: SUBVENCION | H17: =SUBVENCION!G15+SUBVENCION!H15 -> 970357 | J17: =+J15+H17-I17 -> 1391925 | K17: MARZO | L17: INGRESOS | M17: 10% ADM | N17: RR.HH. | O17: BNS Y SERV | P17: SALDO
F18: REMUNERACIONES | G18: REMUNERACIONES | I18: 773497 | J18: =+J17+H18-I18 -> 618428 | L18: =+H17 -> 970357 | M18: =+L18*10% -> 97035.7 | N18: =+I18 -> 773497 | O18: =+I19+I20+I21+I22 -> 396199 | P18: =+L18-M18-N18-O18 -> -296374.7
B19: 46090 | C19: 1 | D19: 90 | E19: 421 | F19: INSUMOS COMPUTACIONES | G19: TINTAS | I19: 206600 | J19: =+J18+H19-I19 -> 411828
B20: 45727 | C20: 3 | D20: 99 | E20: 383 | F20: MATERIALES ENSEÑANZA | G20: LIBRERÍA | I20: 189599 | J20: =+J19+H20-I20 -> 222229
J21: =+J20+H21-I21 -> 222229
J22: =+J21+H22-I22 -> 222229
B23: ABRIL
F24: SUBVENCION | G24: SUBVENCION | H24: =SUBVENCION!I15+SUBVENCION!J15 -> 996498 | J24: =+J22+H24-I24 -> 1218727 | K24: ABRIL | L24: INGRESOS | M24: 10% ADM | N24: RR.HH. | O24: BNS Y SERV | P24: SALDO
F25: REMUNERACIONES | G25: REMUNERACIONES | I25: 718759 | J25: =+J24+H25-I25 -> 499968 | L25: =+H24 -> 996498 | M25: =+L25*10% -> 99649.8 | N25: =+I25 -> 718759 | O25: =I26+I27+I28+I29+I30 -> 0 | P25: =+L25-M25-N25-O25 -> 178089.2
J26: =+J25+H26-I26 -> 499968
J27: =+J26+H27-I27 -> 499968
J28: =+J27+H28-I28 -> 499968
J29: =+J28+H29-I29 -> 499968
J30: =+J29+H30-I30 -> 499968
B31: MAYO
F32: SUBVENCION | G32: SUBVENCION | H32: =SUBVENCION!K15+SUBVENCION!L15 -> 977415 | J32: =+J30+H32-I32 -> 1477383 | K32: MAYO | L32: INGRESOS | M32: 10% ADM | N32: RR.HH. | O32: BNS Y SERV | P32: SALDO
F33: REMUNERACIONES | G33: REMUNERACIONES | I33: 361693 | J33: =+J32+H33-I33 -> 1115690 | L33: =+H32 -> 977415 | M33: =+L33*10% -> 97741.5 | N33: =+I33 -> 361693 | O33: =+I34+I35+I36+I37 -> 412291 | P33: =+L33-M33-N33-O33 -> 105689.5
B34: 46169 | C34: 15 | D34: 503 | E34: 845 | F34: VESTUARIO | G34: BUZOS | I34: 201001 | J34: =+J33+H34-I34 -> 914689
B35: 46169 | C35: 17 | D35: 502 | E35: 843 | F35: MATERIAL ENSEÑANZA | G35: MANUALIDADES ARTES | I35: =127350+83940 -> 211290 | J35: =+J34+H35-I35 -> 703399
J36: =+J35+H36-I36 -> 703399
J37: =+J36+H37-I37 -> 703399
J38: =+J37+H38-I38 -> 703399
B39: JUNIO
F40: SUBVENCION | G40: SUBVENCION | H40: =SUBVENCION!M15+SUBVENCION!N15 -> 963081 | J40: =+J38+H40-I40 -> 1666480 | K40: JUNIO | L40: INGRESOS | M40: 10% ADM | N40: RR.HH. | O40: BNS Y SERV | P40: SALDO
F41: REMUNERACIONES | G41: REMUNERACIONES | I41: 368769 | J41: =+J40+H41-I41 -> 1297711 | L41: =+H40 -> 963081 | M41: =+L41*10% -> 96308.1 | N41: =+I41 -> 368769 | O41: =I42+I43+I44 -> 0 | P41: =+L41-M41-N41-O41 -> 498003.9
J42: =+J41+H42-I42 -> 1297711
J43: =+J42+H43-I43 -> 1297711
J44: =+J43+H44-I44 -> 1297711
J45: =+J44+H45-I45 -> 1297711
B46: JULIO
F47: SUBVENCION | G47: SUBVENCION | H47: =+SUBVENCION!O15+SUBVENCION!P15 -> 980609 | J47: =+J45+H47-I47 -> 2278320 | K47: JULIO | L47: INGRESOS | M47: 10% ADM | N47: RR.HH. | O47: BNS Y SERV | P47: SALDO
F48: REMUNERACIONES | G48: REMUNERACIONES | I48: 358921 | J48: =+J47+H48-I48 -> 1919399 | L48: =+H47 -> 980609 | M48: =+L48*10% -> 98060.9 | N48: =+I48 -> 358921 | O48: =I49+I50+I51 -> 182070 | P48: =+L48-M48-N48-O48 -> 341557.1
B49: 46212 | C49: 22 | D49: 641 | E49: 1077 | F49: VESTUARIO | G49: BUZOS | I49: 182070 | J49: =+J48+H49-I49 -> 1737329
J50: =+J49+H50-I50 -> 1737329
J51: =+J50+H51-I51 -> 1737329
J52: =+J51+H52-I52 -> 1737329
B53: AGOSTO
F54: SUBVENCION | G54: SUBVENCION | H54: =+SUBVENCION!Q15+SUBVENCION!R15 -> 987062 | J54: =+J52+H54-I54 -> 2724391 | K54: AGOSTO | L54: INGRESOS | M54: 10% ADM | N54: RR.HH. | O54: BNS Y SERV | P54: SALDO
F55: REMUNERACIONES | G55: REMUNERACIONES | I55: 361289 | J55: =+J54+H55-I55 -> 2363102 | L55: =+H54 -> 987062 | M55: =+L55*10% -> 98706.2 | N55: =+I55 -> 361289 | O55: =SUM(I56:I58) -> 328920 | P55: =+L55-M55-N55-O55 -> 198146.8
B56: 46238 | C56: 28 | D56: 762 | E56: 1300 | F56: COLACIONES | G56: COLACIONES | I56: 114420 | J56: =+J55+H56-I56 -> 2248682
B57: 46184 | C57: 30 | D57: 790 | E57: 1302 | F57: ARRIENDO | G57: ARRIENDO | I57: 214500 | J57: =+J56+H57-I57 -> 2034182
J58: =+J57+H58-I58 -> 2034182
J59: =+J58+H59-I59 -> 2034182
B60: SEPTIEMBRE
F61: SUBVENCION | G61: SUBVENCION | H61: =+SUBVENCION!S15+SUBVENCION!T15 -> 991084 | J61: =J59+H61-I61 -> 3025266 | K61: SEPTIEMBRE | L61: INGRESOS | M61: 10% ADM | N61: RR.HH. | O61: BNS Y SERV | P61: SALDO
F62: REMUNERACIONES | G62: REMUNERACIONES | I62: 361973 | J62: =+J61+H62-I62 -> 2663293 | L62: =+H61 -> 991084 | M62: =+L62*10% -> 99108.4 | N62: =+I62 -> 361973 | O62: =SUM(I63:I66) -> 751710 | P62: =+L62-M62-N62-O62 -> -221707.4
B63: 46266 | C63: 32 | D63: 915 | F63: COLACIONES | G63: COLACIONES | I63: 210760 | J63: =+J62+H63-I63 -> 2452533
B64: 46268 | C64: 33 | D64: 932 | F64: MATERIALES ENSEÑANZA | G64: MATERIAL LIBRERÍA | I64: 214800 | J64: =+J63+H64-I64 -> 2237733
B65: 46268 | C65: 35 | D65: 933 | F65: VESTUARIO | G65: POLAR | I65: 208250 | J65: =+J64+H65-I65 -> 2029483
B66: 46294 | C66: 37 | D66: 1043 | F66: COLACIONES | G66: COLACIONES | I66: 117900 | J66: =+J65+H66-I66 -> 1911583
J67: =+J66+H67-I67 -> 1911583
J68: =+J67+H68-I68 -> 1911583
B69: OCTUBRE
F70: SUBVENCION | G70: SUBVENCION | H70: =+SUBVENCION!U15+SUBVENCION!V15 -> 0 | J70: =+J68+H70-I70 -> 1911583 | K70: OCTUBRE | L70: INGRESOS | M70: 10% ADM | N70: RR.HH. | O70: BNS Y SERV | P70: SALDO
F71: REMUNERACIONES | G71: REMUNERACIONES | J71: =+J70+H71-I71 -> 1911583 | L71: =+H70 -> 0 | M71: =+L71*10% -> 0 | N71: =+I71 -> 0 | O71: =+I72+I73+I74+I76+I77+I78 -> 0 | P71: =+L71-M71-N71-O71 -> 0
J72: =+J71+H72-I72 -> 1911583
J73: =+J72+H73-I73 -> 1911583
J74: =+J73+H74-I74 -> 1911583
J75: =+J74+H75-I75 -> 1911583
J76: =+J75+H76-I76 -> 1911583
J77: =+J76+H77-I77 -> 1911583
J78: =+J77+H78-I78 -> 1911583
B79: NOVIEMBRE
F80: SUBVENCION | G80: SUBVENCION | H80: =+SUBVENCION!W15+SUBVENCION!X15 -> 0 | J80: =+J78+H80-I80 -> 1911583 | K80: NOVIEMBRE | L80: INGRESOS | M80: 10% ADM | N80: RR.HH. | O80: BNS Y SERV | P80: SALDO
F81: REMUNERACIONES | G81: REMUNERACIONES | J81: =+J80+H81-I81 -> 1911583 | L81: =+H80 -> 0 | M81: =+L81*10% -> 0 | N81: =+I81 -> 0 | O81: =SUM(I82:I87) -> 0 | P81: =+L81-M81-N81-O81 -> 0
J82: =+J81+H82-I82 -> 1911583
J83: =+J82+H83-I83 -> 1911583
J84: =+J83+H84-I84 -> 1911583
J85: =+J84+H85-I85 -> 1911583
J86: =+J85+H86-I86 -> 1911583
J87: =+J86+H87-I87 -> 1911583
B88: DICIEMBRE
F89: SUBVENCION | G89: SUBVENCION | H89: =+SUBVENCION!Y15+SUBVENCION!Z15 -> 0 | J89: =+J87+H89-I89 -> 1911583 | K89: DICIEMBRE | L89: INGRESOS | M89: 10% ADM | N89: RR.HH. | O89: BNS Y SERV | P89: SALDO
F90: REMUNERACIONES | G90: REMUNERACIONES | J90: =+J89+H90-I90 -> 1911583 | L90: =+H89 -> 0 | M90: =+L90*10% -> 0 | N90: =+I90 -> 0 | O90: =+I91 -> 0 | P90: =+L90-M90-N90-O90 -> 0
J91: =+J90+H91-I91 -> 1911583
J92: =+J91+H92-I92 -> 1911583
J93: =+J92+H93-I93 -> 1911583
F94: AC 10% | G94: AC 10% | H94: =(H11+H14+H17+H24+H32+H40+H47+H54+H61+H70+H80+H89)*-10% -> -882557.5 | J94: =+J93+H94-I94 -> 1029025.5 | K94: ANUAL | L94: INGRESOS | M94: 10% ADM | N94: RR.HH. | O94: BNS Y SERV | P94: SALDO
B95: x | C95: x | G95: TOTAL | H95: =SUM(H11:H94) -> 7943017.5 | I95: =SUM(I11:I94) -> 6913992 | J95: =H95-I95 -> 1029025.5 | L95: =+H11+H14+H17+H24+H32+H40+H47+H54+H61+H70+H80+H89 -> 8825575 | M95: =+L95*10% -> 882557.5 | N95: =+I12+I15+I18+I25+I33+I41+I48+I55+I62+I71+I81+I90 -> 4842802 | O95: =+I66+I65+I64+I63+I57+I56+I49+I35+I34+I20+I19 -> 2071190 | P95: =+L95-M95-N95-O95 -> 1029025.5
P97: =+P12+P15+P18+P25+P33+P41+P48+P55+P62+P71+P81+P90 -> 1029025.5
N99: =N97+O97 -> 0
G100: EJECUCION | H100: INGRESOS | I100: GASTOS | J100: %
H101: =+H95 -> 7943017.5 | I101: =+I95 -> 6913992 | J101: =+I101*100/H101 -> 87.044905

Sheet G-394
B2: UNIDAD DE FINANZAS DAEM
B3: LEY SEP
B4: ESCUELA: G-394 INES DE SUAREZ
B5: DIRECTOR: JULIO MUÑOZ
B6: SECTOR: RASTROJOS
B7: RBD: 3506
B8: FECHA | C8: SOL | D8: OC | E8: DP | F8: CATEGORIA | G8: DETALLE | H8: INGRESOS | I8: GASTOS | J8: SALDO
G9: SALDO SEP 2025 | H9: ='[1]G-394'!$J$105 -> -365551.5 | J9: =+H9-I9 -> -365551.5
B10: ENERO
F11: SUBVENCION | G11: SUBVENCION | H11: =SUBVENCION!C16+SUBVENCION!D16 -> 990720 | J11: =H11-I11 -> 990720 | K11: ENERO | L11: INGRESOS | M11: 10% ADM | N11: RR.HH. | O11: BNS Y SERV | P11: SALDO
F12: REMUNERACIONES | G12: REMUNERACIONES | I12: 159835 | J12: =+J11+H12-I12 -> 830885 | L12: =+H11 -> 990720 | M12: =+L12*10% -> 99072 | N12: =+I12 -> 159835 | O12: 0 | P12: =+L12-M12-N12-O12 -> 731813
B13: FEBRERO
F14: SUBVENCION | G14: SUBVENCION | H14: =SUBVENCION!E16+SUBVENCION!F16 -> 1051150 | J14: =+J12+H14-I14 -> 1882035 | K14: FEBRERO | L14: INGRESOS | M14: 10% ADM | N14: RR.HH. | O14: BNS Y SERV | P14: SALDO
F15: REMUNERACIONES | G15: REMUNERACIONES | I15: 163044 | J15: =+J14+H15-I15 -> 1718991 | L15: =+H14 -> 1051150 | M15: =+L15*10% -> 105115 | N15: =+I15 -> 163044 | O15: 0 | P15: =+L15-M15-N15-O15 -> 782991
B16: MARZO
F17: SUBVENCION | G17: SUBVENCION | H17: =SUBVENCION!G15+SUBVENCION!H15 -> 970357 | J17: =+J15+H17-I17 -> 2689348 | K17: MARZO | L17: INGRESOS | M17: 10% ADM | N17: RR.HH. | O17: BNS Y SERV | P17: SALDO
F18: REMUNERACIONES | G18: REMUNERACIONES | I18: 19021 | J18: =+J17+H18-I18 -> 2670327 | L18: =+H17 -> 970357 | M18: =+L18*10% -> 97035.7 | N18: =+I18 -> 19021 | O18: =I19+I20+I21+I22+I23+I24+I25+I26 -> 594018 | P18: =+L18-M18-N18-O18 -> 260282.3
B19: 46099 | C19: 3 | D19: 131 | E19: 379 | F19: MATERIALES ENSEÑANZA | G19: LIBRERÍA | I19: 205279 | J19: =+J18+H19-I19 -> 2465048
B20: 46100 | C20: 4 | D20: 144 | E20: 379 | F20: INSUMO COMPUTACIONES | G20: TINTAS | I20: 207839 | J20: =+J19+H20-I20 -> 2257209
B21: 46104 | C21: 5 | D21: 156 | E21: 411 | F21: EQUIPO DE OFICINA | G21: IMPRESORA | I21: 180900 | J21: =+J20+H21-I21 -> 2076309
J22: =+J21+H22-I22 -> 2076309
J23: =+J22+H23-I23 -> 2076309
J24: =+J23+H24-I24 -> 2076309
J25: =+J24+H25-I25 -> 2076309
J26: =+J25+H26-I26 -> 2076309
B27: ABRIL
F28: SUBVENCION | G28: SUBVENCION | H28: =SUBVENCION!I16+SUBVENCION!J16 -> 996191 | J28: =+J26+H28-I28 -> 3072500 | K28: ABRIL | L28: INGRESOS | M28: 10% ADM | N28: RR.HH. | O28: BNS Y SERV | P28: SALDO
F29: REMUNERACIONES | G29: REMUNERACIONES | I29: 81664 | J29: =+J28+H29-I29 -> 2990836 | L29: =+H28 -> 996191 | M29: =+L29*10% -> 99619.1 | N29: =+I29 -> 81664 | O29: =+I30+I31+I32+I33+I34+I35+I36+I37 -> 1568871 | P29: =+L29-M29-N29-O29 -> -753963.1
B30: 46118 | C30: 6 | D30: 254 | E30: 575 | F30: MATERIALES ENSEÑANZA | G30: LIBRERÍA | I30: 206630 | J30: =+J29+H30-I30 -> 2784206
B31: 46120 | C31: 8 | D31: 255 | E31: 606 | F31: MATERIALES ENSEÑANZA | G31: INSTRUMENTO MUSICALES | I31: 199000 | J31: =+J30+H31-I31 -> 2585206
B32: 46132 | C32: 9 | D32: 331 | E32: 568 | F32: VESTUARIO | G32: TRAJE FLOLCLORICO TALLER | I32: 202895 | J32: =+J31+H32-I32 -> 2382311
B33: 46136 | C33: 15 | D33: 341 | E33: 644 | F33: VESTUARIO | G33: BUZO DEPORTIVO TALLER | I33: 201000 | J33: =+J32+H33-I33 -> 2181311
B34: 46136 | C34: 16 | D34: 342 | E34: 703 | F34: COLACIONES | G34: COLACIONES | I34: 150000 | J34: =+J33+H34-I34 -> 2031311
B35: 46135 | C35: 13 | D35: 340 | E35: 750 | F35: MATERIALES ENSEÑANZA | G35: IMPLEMENTOS DEPORTIVO TALLER | I35: 205632 | J35: =+J34+H35-I35 -> 1825679
B36: 46140 | C36: 21 | D36: 364 | E36: 706 | F36: MOBILIARIO | G36: ESTUFA | I36: 209000 | J36: =+J35+H36-I36 -> 1616679
B37: 46136 | C37: 18 | D37: 359 | E37: 755 | F37: MOBILIARIA | G37: PARLANTE | I37: 194714 | J37: =+J36+H37-I37 -> 1421965
B38: MAYO
F39: SUBVENCION | G39: SUBVENCION | H39: =SUBVENCION!K16+SUBVENCION!L16 -> 963203 | J39: =+J37+H39-I39 -> 2385168 | K39: MAYO | L39: INGRESOS | M39: 10% ADM | N39: RR.HH. | O39: BNS Y SERV | P39: SALDO
F40: REMUNERACIONES | G40: REMUNERACIONES | I40: 84576 | J40: =+J39+H40-I40 -> 2300592 | L40: =+H39 -> 963203 | M40: =+L40*10% -> 96320.3 | N40: =+I40 -> 84576 | O40: =I41+I42+I43+I44 -> 808385 | P40: =+L40-M40-N40-O40 -> -26078.3
B41: 46148 | C41: 22 | D41: 393 | E41: 747 | F41: COLACIONES | G41: COLACIONES | I41: 209300 | J41: =+J40+H41-I41 -> 2091292
B42: 46155 | C42: 23 | D42: 475 | E42: 822 | F42: TRANSPORTE | G42: TRASLADO | I42: 195000 | J42: =+J41+H42-I42 -> 1896292
B43: 46156 | C43: 26 | D43: 476 | E43: 830 | F43: VESTUARIO | G43: BUZO DEPORTIVO TALLER | I43: 204085 | J43: =+J42+H43-I43 -> 1692207
B44: 46155 | C44: 24 | D44: 471 | E44: 824 | F44: COLACIONES | G44: COLACIONES | I44: 200000 | J44: =+J43+H44-I44 -> 1492207
J45: =+J44+H45-I45 -> 1492207
J46: =+J45+H46-I46 -> 1492207
B47: JUNIO
F48: SUBVENCION | G48: SUBVENCION | H48: =SUBVENCION!M16+SUBVENCION!N16 -> 852217 | J48: =+J46+H48-I48 -> 2344424 | K48: JUNIO | L48: INGRESOS | M48: 10% ADM | N48: RR.HH. | O48: BNS Y SERV | P48: SALDO
F49: REMUNERACIONES | G49: REMUNERACIONES | I49: 85760 | J49: =+J48+H49-I49 -> 2258664 | L49: =+H48 -> 852217 | M49: =+L49*10% -> 85221.7 | N49: =+I49 -> 85760 | O49: =I50+I51 -> 295918 | P49: =+L49-M49-N49-O49 -> 385317.3
B50: 46188 | C50: 30 | D50: 569 | F50: COLACIONES | G50: COLACIONES | I50: 91000 | J50: =+J49+H50-I50 -> 2167664
B51: 46188 | C51: 31 | D51: 594 | E51: 990 | F51: VESTUARIO | G51: TRAJE FLOLCLORICO TALLER | I51: 204918 | J51: =+J50+H51-I51 -> 1962746
B52: JULIO
F53: SUBVENCION | G53: SUBVENCION | H53: =+SUBVENCION!O16+SUBVENCION!P16 -> 943228 | J53: =+J51+H53-I53 -> 2905974 | K53: JULIO | L53: INGRESOS | M53: 10% ADM | N53: RR.HH. | O53: BNS Y SERV | P53: SALDO
F54: REMUNERACIONES | G54: REMUNERACIONES | I54: 82807 | J54: =+J53+H54-I54 -> 2823167 | L54: =+H53 -> 943228 | M54: =+L54*10% -> 94322.8 | N54: =+I54 -> 82807 | O54: =I55+I56 -> 523562 | P54: =+L54-M54-N54-O54 -> 242536.2
B55: 46232 | C55: 35 | D55: 745 | E55: 1240 | F55: MATERIALES ENSEÑANZA | G55: INSUMOS TALLER HUERTO | I55: 209100 | J55: =+J54+H55-I55 -> 2614067
B56: 46226 | C56: 33-34 | D56: 2321-235-AG26 | F56: MATERIALES ENSEÑANZA | G56: MATERIAL TALLER ARTISTICO | I56: 314462 | J56: =+J55+H56-I56 -> 2299605
J57: =+J56+H57-I57 -> 2299605
B58: AGOSTO
F59: SUBVENCION | G59: SUBVENCION | H59: =+SUBVENCION!Q16+SUBVENCION!R16 -> 943228 | J59: =+J57+H59-I59 -> 3242833 | K59: AGOSTO | L59: INGRESOS | M59: 10% ADM | N59: RR.HH. | O59: BNS Y SERV | P59: SALDO
F60: REMUNERACIONES | G60: REMUNERACIONES | I60: 83510 | J60: =+J59+H60-I60 -> 3159323 | L60: =+H59 -> 943228 | M60: =+L60*10% -> 94322.8 | N60: =+I60 -> 83510 | O60: =+I61+I62+I63+I64 -> 800358 | P60: =+L60-M60-N60-O60 -> -34962.8
B61: 46244 | C61: 36 | D61: 783 | F61: MOBILIARIO | G61: TELEVISOR | I61: 176446 | J61: =+J60+H61-I61 -> 2982877
B62: 46245 | C62: 38 | D62: 786 | E62: 1371 | F62: CONVIVENCIA | G62: CONVIVENCIA | I62: 209030 | J62: =+J61+H62-I62 -> 2773847
B63: 46252 | C63: 39 | D63: 828 | F63: MOBILIARIO | G63: TELEVISOR | I63: 209964 | J63: =+J62+H63-I63 -> 2563883
B64: 46252 | C64: 40 | D64: 829 | E64: 1372 | F64: VESTUARIO | G64: VESTUARIO | I64: 204918 | J64: =+J63+H64-I64 -> 2358965
J65: =+J64+H65-I65 -> 2358965
B66: SEPTIEMBRE
F67: SUBVENCION | G67: SUBVENCION | H67: =+SUBVENCION!S16+SUBVENCION!T16 -> 942429 | J67: =+J65+H67-I67 -> 3301394 | K67: SEPTIEMBRE | L67: INGRESOS | M67: 10% ADM | N67: RR.HH. | O67: BNS Y SERV | P67: SALDO
F68: REMUNERACIONES | G68: REMUNERACIONES | I68: 83512 | J68: =+J67+H68-I68 -> 3217882 | L68: =+H67 -> 942429 | M68: =+L68*10% -> 94242.9 | N68: =+I68 -> 83512 | O68: =SUM(I69:I72) -> 412160 | P68: =+L68-M68-N68-O68 -> 352514.1
B69: 46275 | C69: 43 | D69: 949 | F69: COLACIONES | G69: COLACIONES | I69: 205530 | J69: =+J68+H69-I69 -> 3012352
B70: 46286 | C70: 46 | D70: 989 | F70: MATERIALES ENSEÑANZA | G70: RESMAS | I70: 206630 | J70: =+J69+H70-I70 -> 2805722
J71: =+J70+H71-I71 -> 2805722
J72: =+J71+H72-I72 -> 2805722
B73: OCTUBRE
F74: SUBVENCION | G74: SUBVENCION | H74: =+SUBVENCION!U16+SUBVENCION!V16 -> 0 | J74: =+J72+H74-I74 -> 2805722 | K74: OCTUBRE | L74: INGRESOS | M74: 10% ADM | N74: RR.HH. | O74: BNS Y SERV | P74: SALDO
F75: REMUNERACIONES | G75: REMUNERACIONES | J75: =+J74+H75-I75 -> 2805722 | L75: =+H74 -> 0 | M75: =+L75*10% -> 0 | N75: =+I75 -> 0 | O75: =SUM(I76:I81) -> 0 | P75: =+L75-M75-N75-O75 -> 0
J76: =+J75+H76-I76 -> 2805722
J77: =+J76+H77-I77 -> 2805722
J78: =+J77+H78-I78 -> 2805722
J79: =+J78+H79-I79 -> 2805722
J80: =+J79+H80-I80 -> 2805722
J81: =+J80+H81-I81 -> 2805722
B82: NOVIEMBRE
F83: SUBVENCION | G83: SUBVENCION | H83: =+SUBVENCION!W16+SUBVENCION!X16 -> 0 | J83: =+J81+H83-I83 -> 2805722 | K83: NOVIEMBRE | L83: INGRESOS | M83: 10% ADM | N83: RR.HH. | O83: BNS Y SERV | P83: SALDO
F84: REMUNERACIONES | G84: REMUNERACIONES | J84: =+J83+H84-I84 -> 2805722 | L84: =+H83 -> 0 | M84: =+L84*10% -> 0 | N84: =+I84 -> 0 | O84: =SUM(I85:I94) -> 0 | P84: =+L84-M84-N84-O84 -> 0
J85: =+J84+H85-I85 -> 2805722
J86: =+J85+H86-I86 -> 2805722
J87: =+J86+H87-I87 -> 2805722
J88: =+J87+H88-I88 -> 2805722
J89: =+J88+H89-I89 -> 2805722
J90: =+J89+H90-I90 -> 2805722
J91: =+J90+H91-I91 -> 2805722
J92: =+J91+H92-I92 -> 2805722
J93: =+J92+H93-I93 -> 2805722
J94: =+J93+H94-I94 -> 2805722
B95: DICIEMBRE
F96: SUBVENCION | G96: SUBVENCION | H96: =+SUBVENCION!Y16+SUBVENCION!Z16 -> 0 | J96: =+J94+H96-I96 -> 2805722 | K96: DICIEMBRE | L96: INGRESOS | M96: 10% ADM | N96: RR.HH. | O96: BNS Y SERV | P96: SALDO
F97: REMUNERACIONES | G97: REMUNERACIONES | J97: =+J96+H97-I97 -> 2805722 | L97: =+H96 -> 0 | M97: =+L97*10% -> 0 | N97: =+I97 -> 0 | O97: =SUM(I97:I101) -> 0 | P97: =+L97-M97-N97-O97 -> 0
J98: =+J97+H98-I98 -> 2805722
J99: =+J98+H99-I99 -> 2805722
J100: =+J99+H100-I100 -> 2805722
J101: =+J100+H101-I101 -> 2805722
...

Sheet E-403
B3: LEY SEP
B4: ESCUELA: E-403 MANUEL BALMACEDA C.C. 2014
B5: DIRECTOR: RICARDO BRAVO
B6: SECTOR: SAN JAVIER
B7: RBD: 3480
B8: FECHA | C8: SOL | D8: OC | E8: DP | F8: CATEGORIA | G8: DETALLE | H8: INGRESOS | I8: GASTOS | J8: SALDO
G9: SALDO SEP 2025 | H9: ='[1]E-403'!$J$169 -> -2782179.7 | J9: =+H9-I9 -> -2782179.7
B10: ENERO
F11: SUBVENCION | G11: SUBVENCION | H11: =SUBVENCION!C4+SUBVENCION!D4 -> 38510402 | J11: =H11-I11 -> 38510402 | K11: ENERO | L11: INGRESOS | M11: 10% ADM | N11: RR.HH. | O11: BNS Y SERV | P11: SALDO
F12: REMUNERACIONES | G12: REMUNERACIONES | I12: 26268456 | J12: =+J11+H12-I12 -> 12241946 | L12: =+H11 -> 38510402 | M12: =+L12*10% -> 3851040.2 | N12: =+I12 -> 26268456 | O12: =I13+I14+I15+I16+I17 -> 11718988 | P12: =+L12-M12-N12-O12 -> -3328082.2
F13: ARRIENDO | G13: ARRIENDO TALLERES DICIEMBRE | I13: 4514400 | J13: =+J12+H13-I13 -> 7727546
B14: 46045 | C14: 1 | D14: 2321-56-AG26 | E14: 403 | F14: INSUMO COMPUTACIONALES | G14: TONER | I14: 1976019 | J14: =+J13+H14-I14 -> 5751527
E15: 55 | F15: INTERNET | G15: INTERNET | I15: 82557 | J15: =+J14+H15-I15 -> 5668970
E16: 55 | F16: INTERNET | G16: INTERNET | I16: 631612 | J16: =+J15+H16-I16 -> 5037358
E17: 13 | F17: ARRIENDO | G17: ARRIENDO TALLERES DICIEMBRE | I17: 4514400 | J17: =+J16+H17-I17 -> 522958
B18: FEBRERO
F19: SUBVENCION | G19: SUBVENCION | H19: =SUBVENCION!E4+SUBVENCION!F4 -> 40811856 | J19: =+J17+H19-I19 -> 41334814 | K19: FEBRERO | L19: INGRESOS | M19: 10% ADM | N19: RR.HH. | O19: BNS Y SERV | P19: SALDO
F20: REMUNERACIONES | G20: REMUNERACIONES | I20: 28099384 | J20: =+J19+H20-I20 -> 13235430 | L20: =+H19 -> 40811856 | M20: =+L20*10% -> 4081185.6 | N20: =+I20 -> 28099384 | O20: =+I22+I21 -> 713963 | P20: =+L20-M20-N20-O20 -> 7917323.4
E21: 161 | F21: INTERNET | G21: INTERNET | I21: 82741 | J21: =+J20+H21-I21 -> 13152689
E22: 161 | F22: INTERNET | G22: INTERNET | I22: 631222 | J22: =+J21+H22-I22 -> 12521467
B23: MARZO
F24: SUBVENCION | G24: SUBVENCION | H24: =SUBVENCION!G4+SUBVENCION!H4 -> 39280618 | J24: =+J22-I24+H24 -> 51802085 | K24: MARZO | L24: INGRESOS | M24: 10% ADM | N24: RR.HH. | O24: BNS Y SERV | P24: SALDO
F25: REMUNERACIONES | G25: REMUNERACIONES | I25: 22614496 | J25: =+J24+H25-I25 -> 29187589 | L25: =+H24 -> 39280618 | M25: =+L25*10% -> 3928061.8 | N25: =+I25 -> 22614496 | O25: =I26+I27+I28+I29+I30+I31+I32+I33+I34+I35+I36 -> 7367194 | P25: =+L25-M25-N25-O25 -> 5370866.2
E26: 375 | F26: ARRIENDO | G26: ARRIENDO TALLERES MARZO | I26: 4672404 | J26: =+J25+H26-I26 -> 24515185
B27: 46085 | C27: 3 | D27: 34 | E27: 382 | F27: MATERIALES OFICINA | G27: LIBRERÍA | I27: 208461 | J27: =+J26+H27-I27 -> 24306724
B28: 46091 | C28: 5 | D28: 100 | E28: 389 | F28: MATERIALES ENSEÑANZA | G28: LIBRERÍA | I28: 206510 | J28: =+J27+H28-I28 -> 24100214
E29: 223 | F29: INTERNET | G29: INTERNET | I29: 82210 | J29: =+J28+H29-I29 -> 24018004
E30: 293 | F30: INTERNET | G30: INTERNET | I30: 632698 | J30: =+J29+H30-I30 -> 23385306
B31: 45735 | C31: 9 | D31: 150 | E31: 379 | F31: MATERIALES ENSEÑANZA | G31: MATERIALES ENSEÑANZA | I31: 205930 | J31: =J30+H31-I31 -> 23179376
B32: 46100 | C32: 10 | D32: 151 | E32: 462 | F32: COLACIONES | G32: TORTA | I32: 155600 | J32: =J31+H32-I32 -> 23023776
B33: 45734 | C33: 6 | D33: 149 | E33: 390 | F33: INSUMO COMPUTACIONALES | G33: TINTAS | I33: 194850 | J33: =J32+H33-I33 -> 22828926
B34: 46108 | C34: 13 | D34: 203 | E34: 407 | F34: EQUIPO OFICINA | G34: IMPRESORA | I34: 189990 | J34: =J33+H34-I34 -> 22638936
B35: 46108 | C35: 15 | D35: 204 | E35: 429 | F35: MATERIALES ENSEÑANZA | G35: LIBRERÍA | I35: 208981 | J35: =J34+H35-I35 -> 22429955
B36: 46093 | C36: 12 | D36: 2321-109-AG26 | E36: 646 | F36: MATERIAL DE ENSEÑANZA | G36: JUEGO PEDAGOGICOS | I36: 609560 | J36: =J35+H36-I36 -> 21820395
B37: ABRIL
F38: SUBVENCION | G38: SUBVENCION | H38: =SUBVENCION!I4+SUBVENCION!J4 -> 35290486 | J38: =+J36+H38-I38 -> 57110881 | K38: ABRIL | L38: INGRESOS | M38: 10% ADM | N38: RR.HH. | O38: BNS Y SERV | P38: SALDO
F39: REMUNERACIONES | G39: REMUNERACIONES | I39: 24923503 | J39: =+J38+H39-I39 -> 32187378 | L39: =+H38 -> 35290486 | M39: =+L39*10% -> 3529048.6 | N39: =+I39 -> 24923503 | O39: =I40+I41+I42+I43+I44+I45+I46+I47 -> 14108069 | P39: =+L39-M39-N39-O39 -> -7270134.6
E40: 351 | F40: INTERNET | G40: INTERNET | I40: 82403 | J40: =+J39+H40-I40 -> 32104975
E41: 455 | F41: INTERNET | G41: INTERNET | I41: 633419 | J41: =+J40+H41-I41 -> 31471556
E42: 573 | F42: ARRIENDO | G42: ARRIENDO TALLERES ABRIL | I42: 4672404 | J42: =+J41+H42-I42 -> 26799152
B43: 46127 | C43: 18 | D43: 305 | E43: 705 | F43: MATERIALES ENSEÑANZA | G43: LIBRERÍA | I43: 209003 | J43: =+J42+H43-I43 -> 26590149
B44: 46128 | C44: 19 | D44: 306 | E44: 645 | F44: INSUMO COMPUTACIONALES | G44: TECLADO - MAUSE | I44: 202500 | J44: =+J43+H44-I44 -> 26387649
B45: 46128 | C45: 20 | D45: 307 | E45: 583 | F45: MATERIALES ENSEÑANZA | G45: LIBRERÍA | I45: 209440 | J45: =+J44+H45-I45 -> 26178209
B46: 46142 | C46: 23 | D46: 383 | E46: 745 | F46: MATERIALES ENSEÑANZA | G46: LIBRERÍA | I46: 209200 | J46: =+J45+H46-I46 -> 25969009
B47: 46142 | C47: 24 | D47: 2321-144-TD26 | E47: PP | F47: PLATAFORMA | G47: PLATAFORMA | I47: 7889700 | J47: =+J46+H47-I47 -> 18079309
B48: MAYO
F49: SUBVENCION | G49: SUBVENCION | H49: =SUBVENCION!K4+SUBVENCION!L4 -> 34799535 | J49: =+J47+H49-I49 -> 52878844 | K49: MAYO | L49: INGRESOS | M49: 10% ADM | N49: RR.HH. | O49: BNS Y SERV | P49: SALDO
F50: REMUNERACIONES | G50: REMUNERACIONES | I50: 25098532 | J50: =+J49+H50-I50 -> 27780312 | L50: =+H49 -> 34799535 | M50: =+L50*10% -> 3479953.5 | N50: =+I50 -> 25098532 | O50: =SUM(I51:I59) -> 6468858 | P50: =+L50-M50-N50-O50 -> -247808.5
B51: 46155 | E51: 564 | F51: INTERNET | G51: INTERNET | I51: 82403 | J51: =+J50+H51-I51 -> 27697909
E52: 564 | F52: INTERNET | G52: INTERNET | I52: 638059 | J52: =+J51+H52-I52 -> 27059850
B53: 46171 | E53: 715 | F53: INTERNET | G53: INTERNET | I53: 83102 | J53: =+J52+H53-I53 -> 26976748
E54: 783 | F54: ARRIENDO | G54: ARRIENDO TALLERES MAYO | I54: 4672404 | J54: =+J53+H54-I54 -> 22304344
B55: 46147 | C55: 25 | D55: 390 | E55: 753 | F55: INSUMO COMPUTACIONALES | G55: INSUMO COMPUTACIONALES | I55: 205900 | J55: =+J54+H55-I55 -> 22098444
B56: 46149 | C56: 30 | D56: 418 | E56: 806 | F56: MATERIALES ENSEÑANZA | G56: LIBRERÍA | I56: 207480 | J56: =+J55+H56-I56 -> 21890964
B57: 46149 | C57: 31 | D57: 419 | E57: 823 | F57: COLACIONES | G57: COLACIONES | I57: 191960 | J57: =+J56+H57-I57 -> 21699004 | L57: =H49-H61 -> 6359426
B58: 46170 | C58: 38 | D58: 500 | E58: 956 | F58: MATERIALES ENSEÑANZA | G58: LIBRERÍA | I58: 208550 | J58: =+J57+H58-I58 -> 21490454
B59: 46169 | C59: 36 | D59: 499 | E59: 987 | F59: INSUMO COMPUTACIONALES | G59: TONER | I59: 179000 | J59: =+J58+H59-I59 -> 21311454
B60: JUNIO
F61: SUBVENCION | G61: SUBVENCION | H61: =SUBVENCION!M4+SUBVENCION!N4 -> 28440109 | J61: =+J59+H61-I61 -> 49751563 | K61: JUNIO | L61: INGRESOS | M61: 10% ADM | N61: RR.HH. | O61: BNS Y SERV | P61: SALDO
F62: REMUNERACIONES | G62: REMUNERACIONES | I62: 25737074 | J62: =+J61+H62-I62 -> 24014489 | L62: =+H61 -> 28440109 | M62: =+L62*10% -> 2844010.9 | N62: =I62 -> 25737074 | O62: =I63+I64+I65+I66+I67+I68+I69+I70 -> 6309634 | P62: =+L62-M62-N62-O62 -> -6450609.9
E63: 715 | F63: INTERNET | G63: INTERNET | I63: 83102 | J63: =+J62+H63-I63 -> 23931387
E64: 791 | F64: INTERNET | G64: INTERNET | I64: 645914 | J64: =+J63+H64-I64 -> 23285473
E65: 783 | F65: ARRIENDO | G65: ARRIENDO TALLERES JUNIO | I65: 4672404 | J65: =+J64+H65-I65 -> 18613069
B66: 46175 | C66: 39 | D66: 527 | E66: 988 | F66: MATERIALES ENSEÑANZA | G66: FOTOCOPIAS | I66: 199965 | J66: =+J65+H66-I66 -> 18413104
B67: 46175 | C67: 42 | D67: 528 | E67: 953 | F67: MATERIALES ENSEÑANZA | G67: LIBRERÍA | I67: 206340 | J67: =+J66+H67-I67 -> 18206764
B68: 46175 | C68: 44 | D68: 529-530 | E68: 1026 | F68: MATERIALES ENSEÑANZA | G68: LIBRERÍA | I68: =50295+34104 -> 84399 | J68: =+J67+H68-I68 -> 18122365
B69: 46188 | C69: 46 | D69: 589 | F69: MATERIALES ENSEÑANZA | G69: LIBRERÍA | I69: 209610 | J69: =+J68+H69-I69 -> 17912755
B70: 46188 | C70: 49 | D70: 590 | E70: 1024 | F70: COLACIONES | G70: TORTAS | I70: 207900 | J70: =+J69+H70-I70 -> 17704855
B71: JULIO
F72: SUBVENCION | G72: SUBVENCION | H72: =+SUBVENCION!O4+SUBVENCION!P4 -> 33026146 | J72: =+J70+H72-I72 -> 50731001 | K72: JULIO | L72: INGRESOS | M72: 10% ADM | N72: RR.HH. | O72: BNS Y SERV | P72: SALDO
F73: REMUNERACIONES | G73: REMUNERACIONES | I73: 25761945 | J73: =+J72+H73-I73 -> 24969056 | L73: =+H72 -> 33026146 | M73: =+L73*10% -> 3302614.6 | N73: =+I73 -> 25761945 | O73: =+I74+I75+I76+I77 -> 5500078 | P73: =+L73-M73-N73-O73 -> -1538491.6
E74: 945 | F74: INTERNET | G74: INTERNET | I74: 94123 | J74: =+J73+H74-I74 -> 24874933
E75: 995 | F75: INTERNET | G75: INTERNET | I75: 649021 | J75: =+J74+H75-I75 -> 24225912
E76: 955 | F76: ARRIENDO | G76: ARRIENDO TALLERES JULIO | I76: 4672404 | J76: =+J75+H76-I76 -> 19553508
E77: 1107 | F77: INTERNET | G77: INTERNET | I77: 84530 | J77: =+J76+H77-I77 -> 19468978
J78: =+J77+H78-I78 -> 19468978
B79: AGOSTO
F80: SUBVENCION | G80: SUBVENCION | H80: =+SUBVENCION!Q4+SUBVENCION!R4 -> 31728901 | J80: =+J78+H80-I80 -> 51197879 | K80: AGOSTO | L80: INGRESOS | M80: 10% ADM | N80: RR.HH. | O80: BNS Y SERV | P80: SALDO
F81: REMUNERACIONES | G81: REMUNERACIONES | I81: 25130040 | J81: =+J80+H81-I81 -> 26067839 | L81: =+H80 -> 31728901 | M81: =+L81*10% -> 3172890.1 | N81: =+I81 -> 25130040 | O81: =I82+I83+I84+I85 -> 5490873 | P81: =+L81-M81-N81-O81 -> -2064902.1
E82: 1107 | F82: INTERNET | G82: INTERNET | I82: 84530 | J82: =+J81+H82-I82 -> 25983309
E83: 1399 | F83: INTERNET | G83: INTERNET | I83: 84573 | J83: =+J82+H83-I83 -> 25898736
E84: 1405 | F84: INTERNET | G84: INTERNET | I84: 649366 | J84: =+J83+H84-I84 -> 25249370
E85: 1215 | F85: ARRIENDO | G85: ARRIENDO TALLERES | I85: 4672404 | J85: =+J84+H85-I85 -> 20576966
J86: =+J85+H86-I86 -> 20576966
B87: SEPTIEMBRE
F88: SUBVENCION | G88: SUBVENCION | H88: =+SUBVENCION!S4+SUBVENCION!T4 -> 31774126 | J88: =+J86+H88-I88 -> 52351092 | K88: SEPTIEMBRE | L88: INGRESOS | M88: 10% ADM | N88: RR.HH. | O88: BNS Y SERV | P88: SALDO
F89: REMUNERACIONES | G89: REMUNERACIONES | I89: 25309341 | J89: =+J88+H89-I89 -> 27041751 | L89: =+H88 -> 31774126 | M89: =+L89*10% -> 3177412.6 | N89: =+I89 -> 25309341 | O89: =+I90+I91+I92+I93+I94+I95+I96+I97 -> 0 | P89: =+L89-M89-N89-O89 -> 3287372.4
F90: INTERNET | G90: INTERNET | J90: =+J89+H90-I90 -> 27041751
F91: INTERNET | G91: INTERNET | J91: =+J90+H91-I91 -> 27041751
J92: =+J91+H92-I92 -> 27041751
J93: =+J92+H93-I93 -> 27041751
J94: =+J93+H94-I94 -> 27041751
J95: =+J94+H95-I95 -> 27041751
J96: =+J95+H96-I96 -> 27041751
J97: =+J96+H97-I97 -> 27041751
J98: =+J97+H98-I98 -> 27041751
J99: =+J98+H99-I99 -> 27041751
J100: =+J99+H100-I100 -> 27041751
B101: OCTUBRE
F102: SUBVENCION | G102: SUBVENCION | H102: =+SUBVENCION!U4+SUBVENCION!V4 -> 0 | J102: =+J100+H102-I102 -> 27041751 | K102: OCTUBRE | L102: INGRESOS | M102: 10% ADM | N102: RR.HH. | O102: BNS Y SERV | P102: SALDO
...

Sheet F-405
B2: UNIDAD DE FINANZAS DAEM
B3: LEY SEP
B4: ESCUELA: F-405 JULIO MONTT SALAMANCA
B5: DIRECTOR: JACQUELINE GUZMAN
B6: SECTOR:
B7: REBD: 3490
B8: FECHA | C8: SOL | D8: OC | E8: DP | F8: CATEGORIA | G8: DETALLE | H8: INGRESOS | I8: GASTOS | J8: SALDO
G9: SALDO 2025 | H9: ='[1]F-405'!$J$125 -> 1076784.2 | J9: =+H9-I9 -> 1076784.2
B10: ENERO
F11: SUBVENCION | G11: SUBVENCION | H11: =SUBVENCION!C9+SUBVENCION!D9 -> 12694999 | J11: =J9+H11-I11 -> 13771783 | K11: ENERO | L11: INGRESOS | M11: 10% ADM | N11: RR.HH. | O11: BNS Y SERV | P11: SALDO
F12: REMUNERACIONES | G12: REMUNERACIONES | I12: 7861759 | J12: =+J11+H12-I12 -> 5910024.2 | L12: =+H11 -> 12694999 | M12: =+L12*10% -> 1269499.9 | N12: =+I12 -> 7861759 | O12: =I13 -> 38773 | P12: =+L12-M12-N12-O12 -> 3524967.1
E13: 12 | F13: INTERNET | G13: INTERNET | I13: 38773 | J13: =+J12+H13-I13 -> 5871251.2
B14: FEBRERO
F15: SUBVENCION | G15: SUBVENCION | H15: =SUBVENCION!E9+SUBVENCION!F9 -> 13454884 | J15: =+J13+H15-I15 -> 19326135 | K15: FEBRERO | L15: INGRESOS | M15: 10% ADM | N15: RR.HH. | O15: BNS Y SERV | P15: SALDO
F16: REMUNERACIONES | G16: REMUNERACIONES | I16: 8511945 | J16: =+J15+H16-I16 -> 10814190 | L16: =H15 -> 13454884 | M16: =+L16*10% -> 1345488.4 | N16: =+I16 -> 8511945 | O16: =+I17+I18 -> 247576 | P16: =+L16-M16-N16-O16 -> 3349874.6
B17: 46079 | C17: 1 | D17: 14 | E17: 634 | F17: INSUMOS COMPUTACIONALES | G17: TINTAS | I17: 208803 | J17: =+J16+H17-I17 -> 10605387
E18: 130 | F18: INTERNET | G18: INTERNET | I18: 38773 | J18: =+J17+H18-I18 -> 10566614
B19: MARZO
F20: SUBVENCION | G20: SUBVENCION | H20: =SUBVENCION!G9+SUBVENCION!H9 -> 12948901 | J20: =+J18+H20-I20 -> 23515515 | K20: MARZO
F21: REMUNERACIONES | G21: REMUNERACIONES | I21: 9306097 | J21: =+J20+H21-I21 -> 14209418
B22: 46084 | C22: 3 | D22: 22 | E22: 263 | F22: MATERIALES OFICINA | G22: LIBRERÍA | I22: 205302 | J22: =+J21+H22-I22 -> 14004116 | L22: INGRESOS | M22: 10% ADM | N22: RR.HH. | O22: BNS Y SERV | P22: SALDO
B23: 46085 | C23: 4 | D23: 35 | E23: 257 | F23: MATERIALES OFICINA | G23: LIBRERÍA | I23: 208900 | J23: =+J22+H23-I23 -> 13795216 | L23: =H20 -> 12948901 | M23: =+L23*10% -> 1294890.1 | N23: =I21 -> 9306097 | O23: =I22+I23+I24+I25+I26+I27 -> 1238624 | P23: =+L23-M23-N23-O23 -> 1109289.9
E24: 222 | F24: INTERNET | G24: INTERNET | I24: 38773 | J24: =+J23+H24-I24 -> 13756443
B25: 46104 | C25: 7 | D25: 157 | E25: 427 | F25: INSUMO COMPUTACIONALES | G25: INSUMO COMPUTACIONALES | I25: 197920 | J25: =+J24+H25-I25 -> 13558523
B26: 46112 | C26: 11 | D26: 206 | E26: 599 | F26: COLACIONES | G26: COLACIONES | I26: 208010 | J26: =+J25+H26-I26 -> 13350513
B27: 46105 | C27: 9 | D27: 2123-97-AG26 | E27: 613 | F27: MATERIALES OFICINA | G27: RESMAS | I27: 379719 | J27: =+J26+H27-I27 -> 12970794
J28: =+J27+H28-I28 -> 12970794
J29: =+J28+H29-I29 -> 12970794
J30: =+J29+H30-I30 -> 12970794
J31: =+J30+H31-I31 -> 12970794
J32: =+J31+H32-I32 -> 12970794
J33: =+J32+H33-I33 -> 12970794
B34: ABRIL
F35: SUBVENCION | G35: SUBVENCION | H35: =SUBVENCION!I9+SUBVENCION!J9 -> 11863643 | J35: =+J33+H35-I35 -> 24834437 | K35: ABRIL
F36: REMUNERACIONES | G36: REMUNERACIONES | I36: 8802976 | J36: =+J35+H36-I36 -> 16031461 | L36: INGRESOS | M36: 10% ADM | N36: RR.HH. | O36: BNS Y SERV | P36: SALDO
E37: 350 | F37: INTERNET | G37: INTERNET | I37: 38773 | J37: =+J36+H37-I37 -> 15992688 | L37: =H35 -> 11863643 | M37: =+L37*10% -> 1186364.3 | N37: =I36 -> 8802976 | O37: =I37+I38+I39+I40+I41+I42+I43+I44+I45+I46+I47 -> 1073149 | P37: =+L37-M37-N37-O37 -> 801153.7
B38: 45749 | C38: 12 | D38: 217 | E38: 419 | F38: PREMIOS | G38: PREMIOS | I38: 208506 | J38: =+J37+H38-I38 -> 15784182
B39: 45753 | C39: 13 | D39: 231 | E39: 574 | F39: INSUMO COMPUTACIONALES | G39: TONER | I39: 207969 | J39: =+J38+H39-I39 -> 15576213
B40: 46119 | C40: 14 | D40: 251 | E40: 653 | F40: MATERIALES DE ENSEÑANZA | G40: BALONES TALLER DEPORTIVO | I40: 206902 | J40: =+J39+H40-I40 -> 15369311
B41: 46128 | C41: 19 | D41: 294 | E41: 651 | F41: INSUMO COMPUTACIONALES | G41: INSUMO COMPUTACIONALES | I41: 203999 | J41: =+J40+H41-I41 -> 15165312
B42: 46134 | C42: 22 | D42: 328 | E42: 601 | F42: TRASPORTE | G42: TRASLADO | I42: 207000 | J42: =+J41+H42-I42 -> 14958312
J43: =+J42+H43-I43 -> 14958312
J44: =+J43+H44-I44 -> 14958312
J45: =+J44+H45-I45 -> 14958312
J46: =+J45+H46-I46 -> 14958312
J47: =+J46+H47-I47 -> 14958312
B48: MAYO
F49: SUBVENCION | G49: SUBVENCION | H49: =SUBVENCION!K9+SUBVENCION!L9 -> 11917513 | J49: =+J47+H49-I49 -> 26875825 | K49: MAYO
F50: REMUNERACIONES | G50: REMUNERACIONES | I50: 8852192 | J50: =+J49+H50-I50 -> 18023633
B51: 46148 | C51: 24 | D51: 404 | E51: 745 | F51: MATERIALES DE ENSEÑANZA | G51: MATERIALES DE ENSEÑANZA | I51: 208700 | J51: =+J50+H51-I51 -> 17814933 | L51: INGRESOS | M51: 10% ADM | N51: RR.HH. | O51: BNS Y SERV | P51: SALDO
B52: 46153 | C52: 26 | D52: 430 | E52: 752 | F52: MATERIALES DE ENSEÑANZA | G52: MATERIALES DE ENSEÑANZA | I52: 211399 | J52: =+J51+H52-I52 -> 17603534 | L52: =H49 -> 11917513 | M52: =+L52*10% -> 1191751.3 | N52: =I50 -> 8852192 | O52: =I51+I52+I53+I54+I55+I56+I57 -> 879445 | P52: =+L52-M52-N52-O52 -> 994124.7
B53: 46167 | C53: 27 | D53: 477 | E53: 834 | F53: MATERIALES DE ENSEÑANZA | G53: MATERIALES DE ENSEÑANZA | I53: 211770 | J53: =+J52+H53-I53 -> 17391764
B54: 46170 | C54: 28 | D54: 495 | E54: 958 | F54: INSUMO COMPUTACIONALES | G54: TONER | I54: 208803 | J54: =+J53+H54-I54 -> 17182961
E55: 563 | F55: INTERNET | G55: INTERNET | I55: 38773 | J55: =+J54+H55-I55 -> 17144188
J56: =+J55+H56-I56 -> 17144188
J57: =+J56+H57-I57 -> 17144188
B58: JUNIO
F59: SUBVENCION | G59: SUBVENCION | H59: =SUBVENCION!M9+SUBVENCION!N9 -> 10702041 | J59: =+J57+H59-I59 -> 27846229 | K59: JUNIO | L59: INGRESOS | M59: 10% ADM | N59: RR.HH. | O59: BNS Y SERV | P59: SALDO
F60: REMUNERACIONES | G60: REMUNERACIONES | I60: 8046594 | J60: =+J59+H60-I60 -> 19799635 | L60: =H59 -> 10702041 | M60: =+L60*10% -> 1070204.1 | N60: =I60 -> 8046594 | O60: =I61+I62+I63+I64+I65+I66+I68+I67 -> 5353064 | P60: =+L60-M60-N60-O60 -> -3767821.1
B61: 46175 | C61: 29 | D61: ABASTECIMIENTO | F61: IMPRESORA MULTIFUNCIONAL | G61: IMPRESORA MULTIFUNCIONAL | I61: 639960 | J61: =+J60+H61-I61 -> 19159675
B62: 46178 | C62: 32 | D62: 549 | E62: 957 | F62: TRANSPORTE | G62: TRASLADO | I62: 207000 | J62: =+J61+H62-I62 -> 18952675
B63: 46178 | C63: 33 | D63: 2321-225-AG26 | E63: 1194 | F63: MATERIALES DE ENSEÑANZA | G63: RESMAS | I63: 699000 | J63: =+J62+H63-I63 -> 18253675
B64: 46181 | C64: 34 | D64: 560 | E64: 956 | F64: MATERIALES DE ENSEÑANZA | G64: MATERIALES DE ENSEÑANZA | I64: 209930 | J64: =+J63+H64-I64 -> 18043745
E65: 734 | F65: INTERNET | G65: INTERNET | I65: 38773 | J65: =+J64+H65-I65 -> 18004972
B66: 46184 | C66: 35 | D66: 2321-214-AG26 | E66: 1190 | F66: SILLAS | G66: SILLAS | I66: 1180480 | J66: =+J65+H66-I66 -> 16824492
B67: 46252 | C67: 38 | D67: 2321-226-TD26 | E67: 1260 | F67: MATERIAL ENSEÑANZA | G67: LIBROS | I67: 2169111 | J67: =+J66+H67-I67 -> 14655381
B68: 46191 | C68: 37 | D68: 603 | E68: 981 | F68: MATERIALES DE ENSEÑANZA | G68: MATERIALES DE ENSEÑANZA | I68: 208810 | J68: =+J67+H68-I68 -> 14446571
B69: JULIO
F70: SUBVENCION | G70: SUBVENCION | H70: =+SUBVENCION!O9+SUBVENCION!P9 -> 11868329 | J70: =+J68+H70-I70 -> 26314900
F71: REMUNERACIONES | G71: REMUNERACIONES | I71: 7585170 | J71: =+J70+H71-I71 -> 18729730 | K71: JULIO | L71: INGRESOS | M71: 10% ADM | N71: RR.HH. | O71: BNS Y SERV | P71: SALDO
E72: 944 | F72: INTERNET | G72: INTERNET | I72: 38773 | J72: =+J71+H72-I72 -> 18690957 | L72: =H70 -> 11868329 | M72: =+L72*10% -> 1186832.9 | N72: =I71 -> 7585170 | O72: =I76+I80+I72+I73+I74+I75+I77+I78+I79+I81 -> 3850100 | P72: =+L72-M72-N72-O72 -> -753773.9
B73: 46227 | C73: 43 | D73: ABASTECIMIENTO | F73: EQUIPAMIENTO | G73: IMPRESORAS | I73: 1760000 | J73: =+J72+H73-I73 -> 16930957
B74: 46226 | C74: 47 | D74: 689 | E74: 1203 | F74: MATERIAL ENSEÑANZA | G74: MATERIALES ARTES | I74: 208480 | J74: =+J73+H74-I74 -> 16722477
B75: 46225 | C75: 46 | D75: 688 | E75: 1149 | F75: MANTENCION EQUIPOS | G75: TAMBOR FOTOCOPIADORA | I75: 214000 | J75: =+J74+H75-I75 -> 16508477
B76: 46225 | C76: 44 | D76: 687 | E76: 1210 | F76: COLACIONES | G76: COLACIONES | I76: 213500 | J76: =+J75+H76-I76 -> 16294977
B77: 46226 | C77: 48 | D77: 704 | E77: 1164 | F77: MATERIAL OFICINA | G77: TERMOLAMINAS | I77: 205696 | J77: =+J76+H77-I77 -> 16089281
B78: 46226 | C78: 50 | D78: 705 | E78: 1213 | F78: MATERIAL ENSEÑANZA | G78: MAT PARVULOS | I78: 213760 | J78: =+J77+H78-I78 -> 15875521
B79: 46217 | C79: 42 | D79: 711 | E79: 1204 | F79: INSUMOS COMPUTACIONALES | G79: TONER Y TINTAS | I79: 210891 | J79: =+J78+H79-I79 -> 15664630
B80: 46227 | C80: 51 | D80: 723 | E80: 1202 | F80: TRANSPORTE | G80: TRASLADO | I80: 207000 | J80: =+J79+H80-I80 -> 15457630
B81: 46226 | C81: 49 | D81: 2321-237-AG26 | E81: 1437 | F81: TRANSPORTE | G81: TRASLADO | I81: 578000 | J81: =+J80+H81-I81 -> 14879630
B82: AGOSTO
F83: SUBVENCION | G83: SUBVENCION | H83: =+SUBVENCION!Q9+SUBVENCION!R9 -> 11652405 | J83: =+J81+H83-I83 -> 26532035
F84: REMUNERACIONES | G84: REMUNERACIONES | I84: 7613561 | J84: =+J83+H84-I84 -> 18918474
E85: 1178 | F85: INTERNET | G85: INTERNET | I85: 38773 | J85: =+J84+H85-I85 -> 18879701
B86: 46244 | C86: 59 | D86: 2321-245-AG26 | E86: 1314 | F86: MANTENCION EQUIPOS | G86: IMPRESORA | I86: 654500 | J86: =+J85+H86-I86 -> 18225201
B87: 46244 | C87: 56 | D87: 779 | F87: JUEGOS INFLABLES | G87: JUEGOS INFLABLE | I87: 213000 | J87: =+J86+H87-I87 -> 18012201 | K87: AGOSTO | L87: INGRESOS | M87: 10% ADM | N87: RR.HH. | O87: BNS Y SERV | P87: SALDO
B88: 46244 | C88: 57 | D88: 778 | E88: 1393 | F88: COLACIONES | G88: COLACIONES | I88: 213010 | J88: =+J87+H88-I88 -> 17799191 | L88: =H83 -> 11652405 | M88: =+L88*10% -> 1165240.5 | N88: =I84 -> 7613561 | O88: =I86+I87+I88+I89+I90+I91+I96+I93+I92+I94+I95+I85 -> 7281572 | P88: =+L88-M88-N88-O88 -> -4407968.5
B89: 46244 | C89: 53 | D89: 777 | E89: 1301 | F89: PREMIOS | G89: PREMIOS | I89: 209109 | J89: =+J88+H89-I89 -> 17590082
B90: 46244 | C90: 52 | D90: 775 | E90: 1286 | F90: MATERIAL ENSEÑANZA | G90: CUADERNO | I90: 213720 | J90: =+J89+H90-I90 -> 17376362
B91: 46244 | C91: 58 | D91: 776 | E91: 1288 | F91: MATERIAL ENSEÑANZA | G91: MAT TALLER BAILE | I91: 209000 | J91: =+J90+H91-I91 -> 17167362
B92: 46247 | C92: 60 | D92: 794 | E92: 1421 | F92: MATERIAL ENSEÑANZA | G92: METALAFONO | I92: 209860 | J92: =+J91+H92-I92 -> 16957502
E93: 1403 | F93: CAJA CHICA | G93: CAJA CHICA | I93: 716490 | J93: =+J92+H93-I93 -> 16241012
B94: 46260 | C94: 62 | D94: 871 | F94: MATERIAL ENSEÑANZA | G94: TALLER DE COCINA | I94: 213010 | J94: =+J93+H94-I94 -> 16028002
B95: 46262 | C95: 64 | D95: 2321-268-AG26 | F95: EQUIPAMIENTO | G95: IMPRESORA | I95: 4391100 | J95: =+J94+H95-I95 -> 11636902
J96: =+J95+H96-I96 -> 11636902
B97: SEPTIEMBRE
F98: SUBVENCION | G98: SUBVENCION | H98: =+SUBVENCION!S9+SUBVENCION!T9 -> 11583142 | J98: =+J96+H98-I98 -> 23220044
F99: REMUNERACIONES | G99: REMUNERACIONES | I99: 7493108 | J99: =+J98+H99-I99 -> 15726936 | K99: SEPTIEMBRE | L99: INGRESOS | M99: 10% ADM | N99: RR.HH. | O99: BNS Y SERV | P99: SALDO
B100: 46275 | C100: 66 | D100: 971 | F100: COLACIONES | G100: ACTIVIDAD AIRE LIBRE | I100: 197030 | J100: =+J99+H100-I100 -> 15529906 | L100: =H98 -> 11583142 | M100: =+L100*10% -> 1158314.2 | N100: =I99 -> 7493108 | O100: =I100+I101+I102+I105+I103+I104 -> 954345 | P100: =+L100-M100-N100-O100 -> 1977374.8
B101: 46276 | C101: 67 | D101: 975 | F101: COLACIONES | G101: COLACIONES | I101: 113200 | J101: =+J100+H101-I101 -> 15416706
...

Sheet F-407
B2: UNIDAD DE FINANZAS DAEM
B3: LEY SEP
B4: ESCUELA: F-407 JUAN DE DIOS ALDEA
B5: DIRECTOR: MATIAS VALENZUELA
B6: SECTOR:
B7: RBD: 3491
B8: FECHA | C8: SOL | D8: OC | E8: DP | F8: CATEGORIA | G8: DETALLE | H8: INGRESOS | I8: GASTOS | J8: SALDO
G9: SALDO 2025 | H9: 2559585 | J9: =+H9-I9 -> 2559585
B10: ENERO
F11: SUBVENCION | G11: SUBVENCION | H11: =SUBVENCION!C10+SUBVENCION!D10 -> 7160173 | J11: =+H11 -> 7160173 | K11: ENERO | L11: INGRESOS | M11: 10% ADM | N11: RR.HH. | O11: BNS Y SERV | P11: SALDO
F12: REMUNERACIONES | G12: REMUNERACIONES | I12: 4323530 | J12: =+J11+H12-I12 -> 2836643 | L12: =+H11 -> 7160173 | M12: =+L12*10% -> 716017.3 | N12: =+I12 -> 4323530 | O12: =I13 -> 0 | P12: =+L12-M12-N12-O12 -> 2120625.7
J13: =+J12+H13-I13 -> 2836643
B14: FEBRERO
F15: SUBVENCION | G15: SUBVENCION | H15: =SUBVENCION!E10+SUBVENCION!F10 -> 7593265 | J15: =+J13+H15-I15 -> 10429908 | K15: FEBRERO | L15: INGRESOS | M15: 10% ADM | N15: RR.HH. | O15: BNS Y SERV | P15: SALDO
F16: REMUNERACIONES | G16: REMUNERACIONES | I16: 4653014 | J16: =+J15+H16-I16 -> 5776894 | L16: =+H15 -> 7593265 | M16: =+L16*10% -> 759326.5 | N16: =+I16 -> 4653014 | O16: =I17 -> 0 | P16: =+L16-M16-N16-O16 -> 2180924.5
J17: =+J16+H17-I17 -> 5776894
B18: MARZO
F19: SUBVENCION | G19: SUBVENCION | H19: =SUBVENCION!G10+SUBVENCION!H10 -> 7303374 | J19: =+J17+H19-I19 -> 13080268 | K19: MARZO | L19: INGRESOS | M19: 10% ADM | N19: RR.HH. | O19: BNS Y SERV | P19: SALDO
F20: REMUNERACIONES | G20: REMUNERACIONES | I20: 4690763 | J20: =+J19+H20-I20 -> 8389505 | L20: =+H19 -> 7303374 | M20: =+L20*10% -> 730337.4 | N20: =+I20 -> 4690763 | O20: =I21+I22+I23+I24+I25+I26+I27 -> 1510108 | P20: =+L20-M20-N20-O20 -> 372165.6
B21: 46083 | C21: 3 | D21: 24 | E21: 265 | F21: MATERIALES OFICINA | G21: LIBRERÍA | I21: 159030 | J21: =+J20+H21-I21 -> 8230475
B22: 46083 | C22: 1 | D22: 23 | E22: 265 | F22: MATERIALES ENSEÑANZA | G22: LIBROS | I22: 159030 | J22: =+J21+H22-I22 -> 8071445
B23: 46084 | C23: 2 | D23: 33 | E23: 265 | F23: MATERIALES ENSEÑANZA | G23: LIBROS TRAZOS Y LETRAS | I23: 155850 | J23: =+J22+H23-I23 -> 7915595
B24: 46087 | C24: 6 | D24: 54 | E24: 266 | F24: MATERIALES ENSEÑANZA | G24: LIBRERÍA | I24: 207010 | J24: =+J23+H24-I24 -> 7708585
B25: 46090 | C25: 7 | D25: 62 | E25: 261 | F25: CONSUMO | G25: CONSUMO | I25: 209000 | J25: =+J24+H25-I25 -> 7499585
B26: 46085 | C26: 4 | D26: 2321-55-AG26 | E26: 405 | F26: INSUMO COMPUTACIONALES | G26: TONER | I26: 415548 | J26: =+J25+H26-I26 -> 7084037
B27: 46098 | C27: 9 | D27: 130 | E27: 389 | F27: MATERIALES ENSEÑANZA | G27: LIBRERÍA | I27: 204640 | J27: =+J26+H27-I27 -> 6879397
J28: =+J27+H28-I28 -> 6879397
B29: ABRIL
F30: SUBVENCION | G30: SUBVENCION | H30: =SUBVENCION!I10+SUBVENCION!J10 -> 7031783 | J30: =+J28+H30-I30 -> 13911180 | K30: ABRIL | L30: INGRESOS | M30: 10% ADM | N30: RR.HH. | O30: BNS Y SERV | P30: SALDO
F31: REMUNERACIONES | G31: REMUNERACIONES | I31: 4902671 | J31: =+J30+H31-I31 -> 9008509 | L31: =+H30 -> 7031783 | M31: =+L31*10% -> 703178.3 | N31: =+I31 -> 4902671 | O31: =I32+I33+I34+I35+I36 -> 1873912 | P31: =+L31-M31-N31-O31 -> -447978.3
B32: 46114 | C32: 15 | D32: 214 | E32: 575 | F32: MATERILAES ENSEÑANZA | G32: RESMA | I32: 204590 | J32: =+J31+H32-I32 -> 8803919
B33: 46121 | C33: 16 | D33: 2123-117-AG26 | E33: 770 | F33: MATERILAES ENSEÑANZA | G33: LIBRERÍA | I33: 682843 | J33: =+J32+H33-I33 -> 8121076
B34: 46133 | C34: 17 | D34: 2321-129-AG26 | E34: 773 | F34: INSUMO COMPUTACIONALES | G34: TONER | I34: 380800 | J34: =+J33+H34-I34 -> 7740276
B35: 46139 | C35: 18 | D35: 2321-169-AG26 | E35: 1069 | F35: INSUMO COMPUTACIONALES | G35: MICROFONO -PARLANTES | I35: 605679 | J35: =+J34+H35-I35 -> 7134597
J36: =+J35+H36-I36 -> 7134597
B37: MAYO
F38: SUBVENCION | G38: SUBVENCION | H38: =SUBVENCION!K10+SUBVENCION!L10 -> 7033366 | J38: =+J36+H38-I38 -> 14167963 | K38: MAYO | L38: INGRESOS | M38: 10% ADM | N38: RR.HH. | O38: BNS Y SERV | P38: SALDO
F39: REMUNERACIONES | G39: REMUNERACIONES | I39: 4899288 | J39: =+J38+H39-I39 -> 9268675 | L39: =+H38 -> 7033366 | M39: =+L39*10% -> 703336.6 | N39: =+I39 -> 4899288 | O39: =I40+I41+I42 -> 496830 | P39: =+L39-M39-N39-O39 -> 933911.4
B40: 46149 | C40: 20 | D40: 400 | E40: 756 | F40: TRASLADO | G40: TRANSPORTE | I40: 80000 | J40: =+J39+H40-I40 -> 9188675
B41: 46153 | C41: 21 | D41: 433 | E41: 808 | F41: COLACIONES | G41: COLACIONES | I41: 210000 | J41: =+J40+H41-I41 -> 8978675
B42: 46153 | C42: 22 | D42: 434 | E42: 751 | F42: MATERIALES ENSEÑANZA | G42: LIBRERÍA | I42: 206830 | J42: =+J41+H42-I42 -> 8771845
B43: JUNIO
F44: SUBVENCION | G44: SUBVENCION | H44: =SUBVENCION!M10+SUBVENCION!N10 -> 6201474 | J44: =+J42+H44-I44 -> 14973319 | K44: JUNIO | L44: INGRESOS | M44: 10% ADM | N44: RR.HH. | O44: BNS Y SERV | P44: SALDO
F45: REMUNERACIONES | G45: REMUNERACIONES | I45: 6112468 | J45: =+J44+H45-I45 -> 8860851 | L45: =+H44 -> 6201474 | M45: =+L45*10% -> 620147.4 | N45: =+I45 -> 6112468 | O45: =I46+I47+I48+I49+I50 -> 2270920 | P45: =+L45-M45-N45-O45 -> -2802061.4
B46: 46162 | C46: 23 | D46: 2321-183-AG26 | E46: 1072 | F46: INSUMO COMPUTACIONALES | G46: INSUMO COMPUTACIONALES | I46: 1535100 | J46: =+J45+H46-I46 -> 7325751
B47: 46171 | C47: 24 | D47: 512 | F47: MATERIALES ENSEÑANZA | G47: LIBRERÍA | I47: 205820 | J47: =+J46+H47-I47 -> 7119931
B48: 46174 | C48: 25 | D48: 513 | E48: 975 | F48: TRASPORTE | G48: TRASLADO | I48: 200000 | J48: =+J47+H48-I48 -> 6919931
B49: 46178 | C49: 26 | D49: 548 | E49: 808 | F49: COLACIONES | G49: COLACIONES | I49: 210000 | J49: =+J48+H49-I49 -> 6709931
B50: 46184 | C50: 28 | D50: 578 | F50: TRASLADO | G50: TRASPORTE | I50: 120000 | J50: =+J49+H50-I50 -> 6589931
B51: JULIO
F52: SUBVENCION | G52: SUBVENCION | H52: =+SUBVENCION!O10+SUBVENCION!P10 -> 6822242 | J52: =+J50+H52-I52 -> 13412173 | K52: JULIO | L52: INGRESOS | M52: 10% ADM | N52: RR.HH. | O52: BNS Y SERV | P52: SALDO
F53: REMUNERACIONES | G53: REMUNERACIONES | I53: 5922000 | J53: =+J52+H53-I53 -> 7490173 | L53: =+H52 -> 6822242 | M53: =+L53*10% -> 682224.2 | N53: =+I53 -> 5922000 | O53: =I54+I55+I56 -> 181499 | P53: =+L53-M53-N53-O53 -> 36518.8
B54: 29-02-26 | C54: 33 | D54: 760 | E54: 1292 | F54: INSUMO COMPUTACIONALES | G54: TONER | I54: 181499 | J54: =+J53+H54-I54 -> 7308674
J55: =+J54+H55-I55 -> 7308674
J56: =+J55+H56-I56 -> 7308674
B57: AGOSTO
F58: SUBVENCION | G58: SUBVENCION | H58: =+SUBVENCION!Q10+SUBVENCION!R10 -> 6038214 | J58: =+J56+H58-I58 -> 13346888 | K58: AGOSTO | L58: INGRESOS | M58: 10% ADM | N58: RR.HH. | O58: BNS Y SERV | P58: SALDO
F59: REMUNERACIONES | G59: REMUNERACIONES | I59: 4739178 | J59: =+J58+H59-I59 -> 8607710 | L59: =+H58 -> 6038214 | M59: =+L59*10% -> 603821.4 | N59: =+I59 -> 4739178 | O59: =+I61+I62+I63+I60+I65+I64 -> 1104711 | P59: =+L59-M59-N59-O59 -> -409496.4
B60: 46247 | C60: 40 | D60: 797 | E60: 1339 | F60: INSUMO COMPUTACIONALES | G60: TONER | I60: 202300 | J60: =+J59+H60-I60 -> 8405410
B61: 46247 | C61: 41 | D61: 799 | E61: 1296 | F61: COLACIONES | G61: COLACIONES | I61: 214800 | J61: =+J60+H61-I61 -> 8190610
B62: 46251 | C62: 39 | D62: 2321-263-AG26 | F62: INSUMO COMPUTACIONALES | G62: TONER | I62: 270011 | J62: =+J61+H62-I62 -> 7920599
B63: 46253 | C63: 38 | D63: 835 | E63: 1387 | F63: MATERIALES ENSEÑANZA | G63: RESMAS | I63: 207600 | J63: =+J62+H63-I63 -> 7712999
B64: 46262 | C64: 42 | D64: 900 | F64: TRASLADO | G64: TRASLADO | I64: 210000 | J64: =+J63+H64-I64 -> 7502999
J65: =+J64+H65-I65 -> 7502999
B66: SEPTIEMBRE
F67: SUBVENCION | G67: SUBVENCION | H67: =+SUBVENCION!S10+SUBVENCION!T10 -> 6799097 | J67: =+J65+H67-I67 -> 14302096 | K67: SEPTIEMBRE | L67: INGRESOS | M67: 10% ADM | N67: RR.HH. | O67: BNS Y SERV | P67: SALDO
F68: REMUNERACIONES | G68: REMUNERACIONES | I68: 4739675 | J68: =+J67+H68-I68 -> 9562421 | L68: =+H67 -> 6799097 | M68: =+L68*10% -> 679909.7 | N68: =+I68 -> 4739675 | O68: =SUM(I69:I73) -> 742420 | P68: =+L68-M68-N68-O68 -> 637092.3
B69: 46267 | C69: 43 | D69: 922 | F69: MATERIALES ENSEÑANZA | G69: MATERIALES ACTIVIDADES PEDAGOGICAS | I69: 214020 | J69: =+J68+H69-I69 -> 9348401
B70: 46267 | C70: 44 | D70: 923 | F70: COLACIONES | G70: COFFE | I70: 213400 | J70: =+J69+H70-I70 -> 9135001
B71: 46279 | C71: 45 | D71: 983 | F71: TRASLADO | G71: TRASLADO | I71: 100000 | J71: =+J70+H71-I71 -> 9035001
B72: 46281 | C72: 46 | D72: 986 | E72: PP | F72: COLACIONES | G72: COFFEE | I72: 215000 | J72: =+J71+H72-I72 -> 8820001
J73: =+J72+H73-I73 -> 8820001
B74: OCTUBRE
F75: SUBVENCION | G75: SUBVENCION | H75: =+SUBVENCION!U10+SUBVENCION!V10 -> 0 | J75: =+J73+H75-I75 -> 8820001 | K75: OCTUBRE | L75: INGRESOS | M75: 10% ADM | N75: RR.HH. | O75: BNS Y SERV | P75: SALDO
F76: REMUNERACIONES | G76: REMUNERACIONES | J76: =+J75+H76-I76 -> 8820001 | L76: =+H75 -> 0 | M76: =+L76*10% -> 0 | N76: =+I76 -> 0 | O76: =SUM(I77:I86) -> 0 | P76: =+L76-M76-N76-O76 -> 0
J77: =+J76+H77-I77 -> 8820001
J78: =+J77+H78-I78 -> 8820001
J79: =+J78+H79-I79 -> 8820001
J80: =+J79+H80-I80 -> 8820001
J81: =+J80+H81-I81 -> 8820001
J82: =+J81+H82-I82 -> 8820001
J83: =+J82+H83-I83 -> 8820001
J84: =+J83+H84-I84 -> 8820001
J85: =+J84+H85-I85 -> 8820001
J86: =+J85+H86-I86 -> 8820001
J87: =+J86+H87-I87 -> 8820001
B88: NOVIEMBRE
F89: SUBVENCION | G89: SUBVENCION | H89: =+SUBVENCION!W10+SUBVENCION!X10 -> 0 | J89: =J87+H89-I89 -> 8820001 | K89: NOVIEMBRE | L89: INGRESOS | M89: 10% ADM | N89: RR.HH. | O89: BNS Y SERV | P89: SALDO
F90: REMUNERACIONES | G90: REMUNERACIONES | J90: =+J89+H90-I90 -> 8820001 | L90: =+H89 -> 0 | M90: =+L90*10% -> 0 | N90: =+I90 -> 0 | O90: =SUM(I91:I102) -> 0 | P90: =+L90-M90-N90-O90 -> 0
J91: =+J90+H91-I91 -> 8820001
J92: =+J91+H92-I92 -> 8820001
J93: =+J92+H93-I93 -> 8820001
J94: =+J93+H94-I94 -> 8820001
J95: =+J94+H95-I95 -> 8820001
J96: =+J95+H96-I96 -> 8820001
J97: =+J96+H97-I97 -> 8820001
J98: =+J97+H98-I98 -> 8820001
J99: =+J98+H99-I99 -> 8820001
J100: =+J99+H100-I100 -> 8820001
J101: =+J100+H101-I101 -> 8820001
...

Sheet G-412
B2: UNIDAD DE FINANZAS DAEM
B3: LEY SEP
B4: ESCUELA: G-412 RAMON CARNICER
B5: DIRECTOR: GABRIEL JAQUE MARIN
B6: SECTOR:
B7: RBD: 3515
B8: FECHA | C8: SOL | D8: OC | E8: DP | F8: CATEGORIA | G8: DETALLE | H8: INGRESOS | I8: GASTOS | J8: SALDO
G9: SALDO 2025 | H9: ='[1]G-412'!$J$94 -> 516412.6 | J9: =+H9-I9 -> 516412.6
B10: ENERO
F11: SUBVENCION | G11: SUBVENCION | H11: =SUBVENCION!C17+SUBVENCION!D17 -> 3279538 | J11: =J9+H11-I11 -> 3795950.6 | K11: ENERO | L11: INGRESOS | M11: 10% ADM | N11: RR.HH. | O11: BNS Y SERV | P11: SALDO
F12: REMUNERACIONES | G12: REMUNERACIONES | I12: 2514764 | J12: =+J11+H12-I12 -> 1281186.6 | L12: =+H11 -> 3279538 | M12: =+L12*10% -> 327953.8 | N12: =+I12 -> 2514764 | O12: 0 | P12: =+L12-M12-N12-O12 -> 436820.2
B13: FEBRERO
F14: SUBVENCION | G14: SUBVENCION | H14: =SUBVENCION!E17+SUBVENCION!F17 -> 3478421 | J14: =+J12+H14-I14 -> 4759607.6 | K14: FEBRERO | L14: INGRESOS | M14: 10% ADM | N14: RR.HH. | O14: BNS Y SERV | P14: SALDO
F15: REMUNERACIONES | G15: REMUNERACIONES | I15: 3755289 | J15: =+J14+H15-I15 -> 1004318.6 | L15: =+H14 -> 3478421 | M15: =+L15*10% -> 347842.1 | N15: =+I15 -> 3755289 | O15: 0 | P15: =+L15-M15-N15-O15 -> -624710.1
B16: MARZO
F17: SUBVENCION | G17: SUBVENCION | H17: =SUBVENCION!G17+SUBVENCION!H17 -> 3345129 | J17: =+J15+H17-I17 -> 4349447.6 | K17: MARZO | L17: INGRESOS | M17: 10% ADM | N17: RR.HH. | O17: BNS Y SERV | P17: SALDO
F18: REMUNERACIONES | G18: REMUNERACIONES | I18: 2584197 | J18: =+J17+H18-I18 -> 1765250.6 | L18: =+H17 -> 3345129 | M18: =+L18*10% -> 334512.9 | N18: =+I18 -> 2584197 | O18: =I19++I20+I21+I22+I23+I24+I25+I26+I27 -> 824974 | P18: =+L18-M18-N18-O18 -> -398554.9
B19: 46086 | C19: 2 | D19: 51 | E19: 270 | F19: INSUMO COMPUTACIONALES | G19: TONER | I19: 208250 | J19: =+J18+H19-I19 -> 1557000.6
B20: 46092 | C20: 4 | D20: 84 | E20: 398 | F20: MATERIALES ENSEÑANZA | G20: MATERIALES | I20: 204894 | J20: =+J19+H20-I20 -> 1352106.6
B21: 46093 | C21: 6 | D21: 104 | E21: 379 | F21: MATERIALES ENSEÑANZA | G21: LIBRERÍA | I21: 202830 | J21: =+J20+H21-I21 -> 1149276.6
B22: 46098 | C22: 8 | D22: 124 | E22: 382 | F22: MATERIALES ENSEÑANZA | G22: LIBRERÍA | I22: 209000 | J22: =+J21+H22-I22 -> 940276.6
J23: =+J22+H23-I23 -> 940276.6
J24: =+J23+H24-I24 -> 940276.6
J25: =+J24+H25-I25 -> 940276.6
J26: =+J25+H26-I26 -> 940276.6
J27: =+J26+H27-I27 -> 940276.6
B28: ABRIL
F29: SUBVENCION | G29: SUBVENCION | H29: =SUBVENCION!I17+SUBVENCION!J17 -> 3654868 | J29: =+J27+H29-I29 -> 4595144.6 | K29: ABRIL | L29: INGRESOS | M29: 10% ADM | N29: RR.HH. | O29: BNS Y SERV | P29: SALDO
F30: REMUNERACIONES | G30: REMUNERACIONES | I30: 2526058 | J30: =+J29+H30-I30 -> 2069086.6 | L30: =+H29 -> 3654868 | M30: =+L30*10% -> 365486.8 | N30: =+I30 -> 2526058 | O30: =I31+I32+I33+I34+I35+I36 -> 149420 | P30: =+L30-M30-N30-O30 -> 613903.2
B31: 46133 | C31: 10 | D31: 327 | E31: 745 | F31: MATERIALES ENSEÑANZA | G31: LIBRERÍA | I31: 149420 | J31: =+J30+H31-I31 -> 1919666.6
J32: =+J31+H32-I32 -> 1919666.6
J33: =+J32+H33-I33 -> 1919666.6
J34: =+J33+H34-I34 -> 1919666.6
J35: =+J34+H35-I35 -> 1919666.6
J36: =+J35+H36-I36 -> 1919666.6
B37: MAYO
F38: SUBVENCION | G38: SUBVENCION | H38: =SUBVENCION!K17+SUBVENCION!L17 -> 3665311 | J38: =+J36+H38-I38 -> 5584977.6 | K38: MAYO | L38: INGRESOS | M38: 10% ADM | N38: RR.HH. | O38: BNS Y SERV | P38: SALDO
F39: REMUNERACIONES | G39: REMUNERACIONES | I39: 2552862 | J39: =+J38+H39-I39 -> 3032115.6 | L39: =+H38 -> 3665311 | M39: =+L39*10% -> 366531.1 | N39: =+I39 -> 2552862 | O39: =I40 -> 211130 | P39: =+L39-M39-N39-O39 -> 534787.9
B40: 46162 | C40: 13 | D40: 467 | E40: 746 | F40: MATERIALES OFICINA | G40: LIBRERÍA | I40: 211130 | J40: =+J39+H40-I40 -> 2820985.6
B41: 46162 | C41: 12 | D41: 468 | E41: NULA | F41: MOBILIARIO Y OTROS | G41: MOBILIARIO Y OTROS | I41: 0 | J41: =+J40+H41-I41 -> 2820985.6
B42: JUNIO
F43: SUBVENCION | G43: SUBVENCION | H43: =SUBVENCION!M17+SUBVENCION!N17 -> 3891595 | J43: =+J41+H43-I43 -> 6712580.6 | K43: JUNIO | L43: INGRESOS | M43: 10% ADM | N43: RR.HH. | O43: BNS Y SERV | P43: SALDO
F44: REMUNERACIONES | G44: REMUNERACIONES | I44: 2595862 | J44: =+J43+H44-I44 -> 4116718.6 | L44: =+H43 -> 3891595 | M44: =+L44*10% -> 389159.5 | N44: =+I44 -> 2595862 | O44: =I45+I46+I47+I48+I49+I50 -> 1033387 | P44: =+L44-M44-N44-O44 -> -126813.5
B45: 46174 | C45: 15 | D45: 508 | E45: 840 | F45: MOBILIARIO Y OTROS | G45: MOBILIARIO Y OTROS | I45: 129990 | J45: =+J44+H45-I45 -> 3986728.6
B46: 46171 | C46: 14 | D46: 518 | E46: 989 | F46: MATERIALES ENSEÑANZA | G46: LIBRERÍA | I46: 207948 | J46: =+J45+H46-I46 -> 3778780.6
B47: 46175 | C47: 16 | D47: 519 | E47: 833 | F47: INSUMO COMPUTACIONALES | G47: TINTAS | I47: 204550 | J47: =+J46+H47-I47 -> 3574230.6
B48: 46177 | C48: 17 | D48: 538 | F48: MATERIALES ENSEÑANZA | G48: LIBRERÍA | I48: 214000 | J48: =+J47+H48-I48 -> 3360230.6
B49: 46185 | C49: 18 | D49: 581 | E49: 950 | F49: MATERIALES ENSEÑANZA | G49: LIBRERÍA | I49: 206999 | J49: =+J48+H49-I49 -> 3153231.6
B50: 46188 | C50: 19 | D50: 593 | E50: 963 | F50: INSUMO COMPUTACIONALES | G50: MICROFONO | I50: 69900 | J50: =+J49+H50-I50 -> 3083331.6
B51: JULIO
F52: SUBVENCION | G52: SUBVENCION | H52: =+SUBVENCION!O17+SUBVENCION!P17 -> 3677841 | J52: =+J50+H52-I52 -> 6761172.6 | K52: JULIO | L52: INGRESOS | M52: 10% ADM | N52: RR.HH. | O52: BNS Y SERV | P52: SALDO
F53: REMUNERACIONES | G53: REMUNERACIONES | I53: 2540901 | J53: =+J52+H53-I53 -> 4220271.6 | L53: =+H52 -> 3677841 | M53: =+L53*10% -> 367784.1 | N53: =+I53 -> 2540901 | O53: =I59+I58+I57+I56+I55+I54 -> 1092870 | P53: =+L53-M53-N53-O53 -> -323714.1
B54: 46211 | C54: 20-21 | D54: 631-632 | E54: 1155 | F54: MATERIAL ENSEÑANZA | G54: MATERIAL DIDACTICO | I54: =154724+59245 -> 213969 | J54: =+J53+H54-I54 -> 4006302.6
B55: 46218 | C55: 22 | D55: 658 | E55: 1258 | F55: MATERIAL ENSEÑANZA | G55: MATERIALES ARTISTICOS | I55: 208130 | J55: =+J54+H55-I55 -> 3798172.6
B56: 46225 | C56: 25 | D56: 681 | E56: 1148 | F56: INSUMO COMPUTACIONALES | G56: TONER | I56: 144990 | J56: =+J55+H56-I56 -> 3653182.6
B57: 46224 | C57: 24 | D57: 680 | E57: 1154 | F57: MATERIAL ENSEÑANZA | G57: MAT DEPORTIVOS | I57: 211301 | J57: =+J56+H57-I57 -> 3441881.6
B58: 46224 | C58: 23 | D58: 679 | E58: 1161 | F58: MATERIAL ENSEÑANZA | G58: LIBRERÍA | I58: 214480 | J58: =+J57+H58-I58 -> 3227401.6
B59: 46230 | C59: 26 | D59: 721 | E59: 1304 | F59: TRANSPORTE | G59: TARSLADO | I59: 100000 | J59: =+J58+H59-I59 -> 3127401.6
B60: AGOSTO
F61: SUBVENCION | G61: SUBVENCION | H61: =+SUBVENCION!Q17+SUBVENCION!R17 -> 3615045 | J61: =+J59+H61-I61 -> 6742446.6 | K61: AGOSTO | L61: INGRESOS | M61: 10% ADM | N61: RR.HH. | O61: BNS Y SERV | P61: SALDO
F62: REMUNERACIONES | G62: REMUNERACIONES | I62: 2550953 | J62: =+J61+H62-I62 -> 4191493.6 | L62: =+H61 -> 3615045 | M62: =+L62*10% -> 361504.5 | N62: =+I62 -> 2550953 | O62: =I66+I65+I64+I63 -> 471570 | P62: =+L62-M62-N62-O62 -> 231017.5
B63: 46239 | C63: 27 | D63: 756 | E63: 1316 | F63: GASTOS MENORES | G63: ARRIENDO JUEGOS INFLABLES | I63: 136850 | J63: =+J62+H63-I63 -> 4054643.6
B64: 46248 | C64: 30 | D64: 810 | E64: 1317 | F64: MATERIAL ENSEÑANZA | G64: LIBRERÍA | I64: 214720 | J64: =+J63+H64-I64 -> 3839923.6
B65: 46251 | C65: 31 | D65: 816 | E65: 1389 | F65: TRANSPORTE | G65: TRASLADO | I65: 120000 | J65: =+J64+H65-I65 -> 3719923.6
J66: =+J65+H66-I66 -> 3719923.6
B67: SEPTIEMBRE
F68: SUBVENCION | G68: SUBVENCION | H68: =+SUBVENCION!S17+SUBVENCION!T17 -> 3652710 | J68: =+J66+H68-I68 -> 7372633.6 | K68: SEPTIEMBRE | L68: INGRESOS | M68: 10% ADM | N68: RR.HH. | O68: BNS Y SERV | P68: SALDO
F69: REMUNERACIONES | G69: REMUNERACIONES | I69: 2551386 | J69: =+J68+H69-I69 -> 4821247.6 | L69: =+H68 -> 3652710 | M69: =+L69*10% -> 365271 | N69: =+I69 -> 2551386 | O69: =SUM(I70:I72) -> 611000 | P69: =+L69-M69-N69-O69 -> 125053
B70: 46293 | C70: 34 | D70: 1028 | E70: PP | F70: IMPRESORA | G70: IMPRESORA | I70: 215000 | J70: =+J69+H70-I70 -> 4606247.6
B71: 46293 | C71: 35 | D71: 1023 | F71: MATERIAL ENSEÑANZA | G71: PIZARRA MOVIL | I71: 181000 | J71: =+J70+H71-I71 -> 4425247.6
B72: 46293 | C72: 33 | D72: 1024 | E72: PP | F72: MATERIAL ENSEÑANZA | G72: MATERIAL ENSEÑANZA | I72: 215000 | J72: =+J71+H72-I72 -> 4210247.6
J73: =+J72+H73-I73 -> 4210247.6
B74: OCTUBRE
F75: SUBVENCION | G75: SUBVENCION | H75: =+SUBVENCION!U17+SUBVENCION!V17 -> 0 | J75: =+J73+H75-I75 -> 4210247.6 | K75: OCTUBRE | L75: INGRESOS | M75: 10% ADM | N75: RR.HH. | O75: BNS Y SERV | P75: SALDO
F76: REMUNERACIONES | G76: REMUNERACIONES | J76: =+J75+H76-I76 -> 4210247.6 | L76: =+H75 -> 0 | M76: =+L76*10% -> 0 | N76: =+I76 -> 0 | O76: 0 | P76: =+L76-M76-N76-O76 -> 0
J77: =+J76+H77-I77 -> 4210247.6
J78: =+J77+H78-I78 -> 4210247.6
J79: =+J78+H79-I79 -> 4210247.6
J80: =+J79+H80-I80 -> 4210247.6
J81: =+J80+H81-I81 -> 4210247.6
J82: =+J81+H82-I82 -> 4210247.6
J83: =+J82+H83-I83 -> 4210247.6
J84: =+J83+H84-I84 -> 4210247.6
J85: =+J84+H85-I85 -> 4210247.6
J86: =+J85+H86-I86 -> 4210247.6
B87: NOVIEMBRE
F88: SUBVENCION | G88: SUBVENCION | H88: =+SUBVENCION!W17+SUBVENCION!X17 -> 0 | J88: =+J86+H88-I88 -> 4210247.6 | K88: NOVIEMBRE | L88: INGRESOS | M88: 10% ADM | N88: RR.HH. | O88: BNS Y SERV | P88: SALDO
F89: REMUNERACIONES | G89: REMUNERACIONES | J89: =+J88+H89-I89 -> 4210247.6 | L89: =+H88 -> 0 | M89: =+L89*10% -> 0 | N89: =+I89 -> 0 | O89: =+I90+I91+I92+I93+I94+I99 -> 0 | P89: =+L89-M89-N89-O89 -> 0
J90: =+J89+H90-I90 -> 4210247.6
J91: =+J90+H91-I91 -> 4210247.6
J92: =+J91+H92-I92 -> 4210247.6
J93: =+J92+H93-I93 -> 4210247.6
J94: =+J93+H94-I94 -> 4210247.6
J95: =+J94+H95-I95 -> 4210247.6
J96: =+J95+H96-I96 -> 4210247.6
J97: =+J96+H97-I97 -> 4210247.6
J98: =+J97+H98-I98 -> 4210247.6
J99: =+J98+H99-I99 -> 4210247.6
J100: =+J99+H100-I100 -> 4210247.6
B101: DICIEMBRE
...

Sheet F-413
B2: UNIDAD DE FINANZAS DAEM
B3: LEY SEP
B4: Escuela: F-413 BERNARDO O´HIGGINS - RBD 3492
B5: Director: STEFANIE FAUNDEZ
B6: SECTOR:
B7: RBD: 3492
B8: FECHA | C8: SOL | D8: OC | E8: DP | F8: CATEGORIA | G8: DETALLE | H8: INGRESOS | I8: GASTOS | J8: SALDO
G9: SALDO 2025 | H9: ='[1]F-413'!$J$127 -> 1010389.5 | J9: =+H9-I9 -> 1010389.5
B10: ENERO
F11: SUBVENCION | G11: SUBVENCION | H11: =SUBVENCION!C11+SUBVENCION!D11 -> 11263770 | J11: =+J9+H11-I11 -> 12274160 | L11: ENERO | M11: INGRESOS | N11: 10% ADM | O11: RR.HH. | P11: BNS Y SERV | Q11: SALDO
F12: REMUNERACIONES | G12: REMUNERACIONES | I12: 9558021 | J12: =J11+H12-I12 -> 2716138.5 | M12: =+H11 -> 11263770 | N12: =+M12*10% -> 1126377 | O12: =+I12 -> 9558021 | P12: 0 | Q12: =+M12-N12-O12-P12 -> 579372
B13: FEBRERO
F14: SUBVENCION | G14: SUBVENCION | H14: =SUBVENCION!E11+SUBVENCION!F11 -> 11947720 | J14: =+J12+H14-I14 -> 14663858 | L14: FEBRERO | M14: INGRESOS | N14: 10% ADM | O14: RR.HH. | P14: BNS Y SERV | Q14: SALDO
F15: REMUNERACIONES | G15: REMUNERACIONES | I15: 10220190 | J15: =+J14+H15-I15 -> 4443668.5 | M15: =+H14 -> 11947720 | N15: =+M15*10% -> 1194772 | O15: =+I15 -> 10220190 | P15: 0 | Q15: =+M15-N15-O15-P15 -> 532758
B16: MARZO
F17: SUBVENCION | G17: SUBVENCION | H17: =SUBVENCION!G11+SUBVENCION!H11 -> 11489045 | J17: =+J15+H17-I17 -> 15932714 | L17: MARZO | M17: INGRESOS | N17: 10% ADM | O17: RR.HH. | P17: BNS Y SERV | Q17: SALDO
F18: REMUNERACIONES | G18: REMUNERACIONES | I18: 9348835 | J18: =+J17+H18-I18 -> 6583878.5 | M18: =+H17 -> 11489045 | N18: =+M18*10% -> 1148904.5 | O18: =+I18 -> 9348835 | P18: =I19+I20+I21+I22+I23+I24+I25+I26 -> 1422665 | Q18: =+M18-N18-O18-P18 -> -431359.5
B19: 46086 | C19: 5 | D19: 63 | E19: 569 | F19: MATERIALES OFICINA | G19: MATERIALES OFICINA | I19: 208131 | J19: =+J18+H19-I19 -> 6375747.5
B20: 46087 | C20: 6 | D20: 64 | E20: 583 | F20: MATERIALES ENSEÑANZA | G20: MATERIALES ENSEÑANZA | I20: 207740 | J20: =+J19+H20-I20 -> 6168007.5
B21: 46097 | C21: 9 | D21: 121 | E21: 571 | F21: MATERIALES ENSEÑANZA | G21: MATERIALES ENSEÑANZA | I21: 203659 | J21: =+J20+H21-I21 -> 5964348.5
B22: 46093 | C22: 7 | D22: 129 | E22: 392 | F22: MATERIALES ENSEÑANZA | G22: LIBRERÍA | I22: 208000 | J22: =+J21+H22-I22 -> 5756348.5
B23: 46097 | C23: 8 | D23: 128 | E23: 396 | F23: EQUIPO OFICINA | G23: IMPRESORA | I23: 199990 | J23: =+J22+H23-I23 -> 5556358.5
B24: 46100 | C24: 10 | D24: 143 | E24: 384 | F24: INSUMO COMPUTACIONALES | G24: TONER | I24: 195636 | J24: =+J23+H24-I24 -> 5360722.5
B25: 46104 | C25: 11 | D25: 207-208 | E25: 714 | F25: MATERIALES ENSEÑANZA | G25: JUEGO DIDACTICOS | I25: 199509 | J25: =+J24+H25-I25 -> 5161213.5
J26: =+J25+H26-I26 -> 5161213.5
J27: =+J26+H27-I27 -> 5161213.5
B28: ABRIL
F29: SUBVENCION | G29: SUBVENCION | H29: =SUBVENCION!I11+SUBVENCION!J11 -> 12555792 | J29: =+J27+H29-I29 -> 17717006 | L29: ABRIL | M29: INGRESOS | N29: 10% ADM | O29: RR.HH. | P29: BNS Y SERV | Q29: SALDO
F30: REMUNERACIONES | G30: REMUNERACIONES | I30: 9382193 | J30: =+J29+H30-I30 -> 8334812.5 | M30: =+H29 -> 12555792 | N30: =+M30*10% -> 1255579.2 | O30: =+I30 -> 9382193 | P30: =I31+I32+I33+I34 -> 1076048 | Q30: =+M30-N30-O30-P30 -> 841971.8
B31: 46113 | C31: 13 | D31: 209 | E31: 701 | F31: TEXTILES | G31: TEXTILES | I31: 207098 | J31: =+J30+H31-I31 -> 8127714.5
B32: 46114 | C32: 16 | D32: 2321-110-AG26 | E32: 775 | F32: INSUMO COMPUTACIONALES | G32: INSUMO COMPUTACIONALES | I32: 452200 | J32: =+J31+H32-I32 -> 7675514.5
B33: 46114 | C33: 14 | D33: 225 | E33: 572 | F33: MATERIALES ENSEÑANZA | G33: MATERIALES ENSEÑANZA | I33: 208500 | J33: =+J32+H33-I33 -> 7467014.5
B34: 46114 | C34: 15 | D34: 226 | E34: 613 | F34: MATERIALES ENSEÑANZA | G34: MATERIALES ENSEÑANZA | I34: 208250 | J34: =+J33+H34-I34 -> 7258764.5
B35: MAYO
F36: SUBVENCION | G36: SUBVENCION | H36: =SUBVENCION!K11+SUBVENCION!L11 -> 12345924 | J36: =+J34+H36-I36 -> 19604688 | L36: MAYO | M36: INGRESOS | N36: 10% ADM | O36: RR.HH. | P36: BNS Y SERV | Q36: SALDO
F37: REMUNERACIONES | G37: REMUNERACIONES | I37: 9373972 | J37: =+J36+H37-I37 -> 10230716 | M37: =+H36 -> 12345924 | N37: =+M37*10% -> 1234592.4 | O37: =+I37 -> 9373972 | P37: =I38+I39+I40+I41+I42+I43+I44+I45+I46 -> 2358614 | Q37: =+M37-N37-O37-P37 -> -621254.4
B38: 46146 | C38: 21 | D38: 406 | E38: 977 | F38: MATERIALES ENSEÑANZA | G38: LIBRERÍA | I38: 74300 | J38: =+J37+H38-I38 -> 10156416
B39: 46146 | C39: 22 | D39: 407 | E39: 960 | F39: MATERIALES ENSEÑANZA | G39: LIBRERÍA | I39: =152844+56095 -> 208939 | J39: =+J38+H39-I39 -> 9947477.5
I40: 180900 | J40: =+J39+H40-I40 -> 9766577.5
B41: 46146 | C41: 24-25 | D41: 409-410 | E41: 885 | F41: MATERIALES ENSEÑANZA | G41: LIBRERÍA | I41: 150170 | J41: =+J40+H41-I41 -> 9616407.5
B42: 46146 | C42: 26 | D42: 411 | E42: 884 | F42: COLACIONES | G42: COLACIONES | I42: 209000 | J42: =+J41+H42-I42 -> 9407407.5
B43: 46149 | C43: 33 | D43: 412 | E43: 952 | F43: INSUMO COMPUTACIONALES | G43: INSUMO COMPUTACIONALES | I43: 208488 | J43: =+J42+H43-I43 -> 9198919.5
B44: 46146 | C44: 27-28-29-30-31-32 | D44: 2321-227-AG26 | F44: MATERIALES ENSEÑANZA | G44: LIBRERÍA | I44: 907939 | J44: =+J43+H44-I44 -> 8290980.5
B45: 46150 | C45: 34 | D45: 408 | E45: 828 | F45: MATERIALES ENSEÑANZA | G45: LIBRERÍA | I45: 209952 | J45: =+J44+H45-I45 -> 8081028.5
B46: 46146 | C46: 20 | D46: 473 | E46: 1022 | F46: COLACIONES | G46: COLACIONES | I46: 208926 | J46: =+J45+H46-I46 -> 7872102.5
B47: JUNIO
F48: SUBVENCION | G48: SUBVENCION | H48: =SUBVENCION!M11+SUBVENCION!N11 -> 12610519 | J48: =+J46+H48-I48 -> 20482622 | L48: JUNIO | M48: INGRESOS | N48: 10% ADM | O48: RR.HH. | P48: BNS Y SERV | Q48: SALDO
F49: REMUNERACIONES | G49: REMUNERACIONES | I49: 10218305 | J49: =+J48+H49-I49 -> 10264316 | M49: =H48 -> 12610519 | N49: =M49*10% -> 1261051.9 | O49: =I49 -> 10218305 | P49: =I50 -> 650000 | Q49: =M49-N49-O49-P49 -> 481162.1
B50: 46174 | C50: 36 | D50: ABASTECIMIENTO | F50: TRANSPORTE | G50: TRASLADO STGO | I50: 650000 | J50: =+J49+H50-I50 -> 9614316.5
J51: =+J50+H51-I51 -> 9614316.5
B52: JULIO
F53: SUBVENCION | G53: SUBVENCION | H53: =+SUBVENCION!O11+SUBVENCION!P11 -> 12107410 | J53: =+J51+H53-I53 -> 21721726 | L53: JULIO | M53: INGRESOS | N53: 10% ADM | O53: RR.HH. | P53: BNS Y SERV | Q53: SALDO
F54: REMUNERACIONES | G54: REMUNERACIONES | I54: 10136103 | J54: =+J53+H54-I54 -> 11585624 | M54: =+H53 -> 12107410 | N54: =+M54*10% -> 1210741 | O54: =+I54 -> 10136103 | P54: =I55+I56+I57 -> 617590 | Q54: =+M54-N54-O54-P54 -> 142976
B55: 46181 | C55: 37 | D55: 612 | E55: 1033 | F55: MATERIALES ENSEÑANZA | G55: LIBRERÍA | I55: 205100 | J55: =+J54+H55-I55 -> 11380524
B56: 46181 | C56: 38 | D56: 613 | E56: 1031 | F56: MATERIALES ENSEÑANZA | G56: RESMAS | I56: 203490 | J56: =+J55+H56-I56 -> 11177034
B57: 46209 | C57: 40 | D57: 614 | E57: 1078 | F57: COLACIONES | G57: COLACIONES | I57: 209000 | J57: =+J56+H57-I57 -> 10968034
B58: AGOSTO
F59: SUBVENCION | G59: SUBVENCION | H59: =+SUBVENCION!Q11+SUBVENCION!R11 -> 11912843 | J59: =+J57+H59-I59 -> 22880876 | L59: AGOSTO | M59: INGRESOS | N59: 10% ADM | O59: RR.HH. | P59: BNS Y SERV | Q59: SALDO
F60: REMUNERACIONES | G60: REMUNERACIONES | I60: 9554945 | J60: =+J59+H60-I60 -> 13325932 | M60: =+H59 -> 11912843 | N60: =+M60*10% -> 1191284.3 | O60: =+I60 -> 9554945 | P60: =+I61+I62 -> 214920 | Q60: =+M60-N60-O60-P60 -> 951693.7
B61: 46248 | C61: 44-45 | D61: 806-807 | E61: 1365-1366 | F61: MATERIALES ENSEÑANZA | G61: LIBRERÍA | I61: 214920 | J61: =+J60+H61-I61 -> 13111012
J62: =+J61+H62-I62 -> 13111012
B63: SEPTEIMBRE
F64: SUBVENCION | G64: SUBVENCION | H64: =+SUBVENCION!S11+SUBVENCION!T11 -> 11835191 | J64: =+J62+H64-I64 -> 24946202 | L64: SEPTIEMBRE | M64: INGRESOS | N64: 10% ADM | O64: RR.HH. | P64: BNS Y SERV | Q64: SALDO
F65: REMUNERACIONES | G65: REMUNERACIONES | I65: 9756984 | J65: =+J64+H65-I65 -> 15189218 | M65: =+H64 -> 11835191 | N65: =+M65*10% -> 1183519.1 | O65: =+I65 -> 9756984 | P65: =SUM(I66) -> 0 | Q65: =+M65-N65-O65-P65 -> 894687.9
J66: =+J65+H66-I66 -> 15189218
B67: OCTUBRE
F68: SUBVENCION | G68: SUBVENCION | H68: =+SUBVENCION!U11+SUBVENCION!V11 -> 0 | J68: =+J66+H68-I68 -> 15189218 | L68: OCTUBRE | M68: INGRESOS | N68: 10% ADM | O68: RR.HH. | P68: BNS Y SERV | Q68: SALDO
F69: REMUNERACIONES | G69: REMUNERACIONES | J69: =+J68+H69-I69 -> 15189218 | M69: =+H68 -> 0 | N69: =+M69*10% -> 0 | O69: =+I69 -> 0 | Q69: =+M69-N69-O69-P69 -> 0
J70: =+J69+H70-I70 -> 15189218
J71: =+J70+H71-I71 -> 15189218
J72: =+J71+H72-I72 -> 15189218
J73: =+J72+H73-I73 -> 15189218
J74: =+J73+H74-I74 -> 15189218
B75: NOVIEMBRE
F76: SUBVENCION | G76: SUBVENCION | H76: =+SUBVENCION!W11+SUBVENCION!X11 -> 0 | J76: =+J74+H76-I76 -> 15189218 | L76: NOVIEMBRE | M76: INGRESOS | N76: 10% ADM | O76: RR.HH. | P76: BNS Y SERV | Q76: SALDO
F77: REMUNERACIONES | G77: REMUNERACIONES | J77: =+J76+H77-I77 -> 15189218 | M77: =+H76 -> 0 | N77: =+M77*10% -> 0 | O77: =+I77 -> 0 | Q77: =+M77-N77-O77-P77 -> 0
J78: =+J77+H78-I78 -> 15189218
J79: =+J78+H79-I79 -> 15189218
J80: =+J79+H80-I80 -> 15189218
J81: =+J80+H81-I81 -> 15189218
J82: =+J81+H82-I82 -> 15189218
J83: =+J82+H83-I83 -> 15189218
J84: =+J83+H84-I84 -> 15189218
J85: =+J84+H85-I85 -> 15189218
J86: =+J85+H86-I86 -> 15189218
J87: =+J86+H87-I87 -> 15189218
J88: =+J87+H88-I88 -> 15189218
J89: =+J88+H89-I89 -> 15189218
... J92: =+J91+H92-I92 -> 15189218
B93: DICIEMBRE
F94: SUBVENCION | G94: SUBVENCION | H94: =+SUBVENCION!Y11+SUBVENCION!Z11 -> 0 | J94: =+J92+H94-I94 -> 15189218 | L94: DICIEMBRE | M94: INGRESOS | N94: 10% ADM | O94: RR.HH. | P94: BNS Y SERV | Q94: SALDO
F95: REMUNERACIONES | G95: REMUNERACIONES | J95: =+J94+H95-I95 -> 15189218 | M95: =+H94 -> 0 | N95: =+M95*10% -> 0 | O95: =+I95 -> 0 | P95: 0 | Q95: =+M95-N95-O95-P95 -> 0
J96: =+J95+H96-I96 -> 15189218
J97: =+J96+H97-I97 -> 15189218
J98: =+J97+H98-I98 -> 15189218
J99: =+J98+H99-I99 -> 15189218
J100: =+J99+H100-I100 -> 15189218
J101: =+J100+H101-I101 -> 15189218
J102: =+J101+H102-I102 -> 15189218
J103: =+J102+H103-I103 -> 15189218
...

Sheet E-414
B2: UNIDAD DE FINANZAS DAEM
B3: LEY SEP
B4: ESCUELA: E-414 MANUEL DE SALAS - RBD 3481
B5: DIRECTOR: CARLOS ASBUN SEPULVEDA
B6: SECTOR:
B7: RBD: 3481
B8: FECHA | C8: SOL | D8: OC | E8: DP | F8: CATEGORIA | G8: DETALLE | H8: INGRESOS | I8: GASTOS | J8: SALDO
G9: SALDO 2025 | H9: 30224473 | J9: =+H9-I9 -> 30224473
B10: ENERO
F11: SUBVENCION | G11: SUBVENCION | H11: =SUBVENCION!C5+SUBVENCION!D5 -> 24238665 | J11: =+J9+H11-I11 -> 54463138 | L11: ENERO | M11: INGRESOS | N11: 10% ADM | O11: RR.HH. | P11: BNS Y SERV | Q11: SALDO
F12: REMUNERACIONES | G12: REMUNERACIONES | I12: 15695889 | J12: =+J11+H12-I12 -> 38767249 | M12: =+H11 -> 24238665 | N12: =+M12*10% -> 2423866.5 | O12: =+I12 -> 15695889 | P12: =I13+I14+I15+I16+I17+I18+I19 -> 15104547 | Q12: =+M12-N12-O12-P12 -> -8985637.5
B13: 45966 | C13: 431 | D13: 2321-445-AG25 | E13: 15 | F13: COLACIONES | G13: COLACIONES | I13: 789565 | J13: =+J12+H13-I13 -> 37977684
B14: 45973 | C14: 434 | D14: 2321-477-AG25 | E14: 16 | F14: TRASPORTE | G14: TRASLADO | I14: 319800 | J14: =+J13+H14-I14 -> 37657884
B15: 45989 | C15: 455 | D15: 2321-480-AG25 | E15: 167 | F15: MATERIAL ENSEÑANZA | G15: LIBROS | I15: 2578106 | J15: =+J14+H15-I15 -> 35079778 | K15: =I13+I14+I15+I16+I17+I18 -> 14610038
B16: 45989 | C16: 459 | D16: 2321-478-AG25 | E16: 164 | F16: MATERIALE ENSEÑANZA | G16: MATERIALE ENSEÑANZA | I16: 521238 | J16: =+J15+H16-I16 -> 34558540
B17: 45989 | C17: 458 | D17: 2321-4-AG26 | E17: 166 | F17: EQUIPO COMPUTACIONEALES | G17: EQUIPO COMPUTACIONEALES | I17: 6490001 | J17: =+J16+H17-I17 -> 28068539
B18: 45981 | C18: 445 | D18: 2321-2-AG26 | E18: 393 | F18: MATERIAL ENSEÑANZA | G18: LIBRERÍA | I18: 3911328 | J18: =+J17+H18-I18 -> 24157211
E19: 55 | F19: INTERNET | G19: INTERNET | I19: 494509 | J19: =+J18+H19-I19 -> 23662702
J20: =+J19+H20-I20 -> 23662702
B21: FEBRERO
F22: SUBVENCION | G22: SUBVENCION | H22: =SUBVENCION!E5+SUBVENCION!F5 -> 25683022 | J22: =+J20+H22-I22 -> 49345724 | L22: FEBRERO | M22: INGRESOS | N22: 10% ADM | O22: RR.HH. | P22: BNS Y SERV | Q22: SALDO
F23: REMUNERACIONES | G23: REMUNERACIONES | I23: 17093190 | J23: =+J22+H23-I23 -> 32252534 | M23: =+H22 -> 25683022 | N23: =+M23*10% -> 2568302.2 | O23: =+I23 -> 17093190 | P23: =I24+I25+I26 -> 494206 | Q23: =+M23-N23-O23-P23 -> 5527323.8
E24: 161 | F24: INTERNET | G24: INTERNET | I24: 494206 | J24: =+J23+H24-I24 -> 31758328
J25: =+J24+H25-I25 -> 31758328
J26: =+J25+H26-I26 -> 31758328
J27: =+J26+H27-I27 -> 31758328 | N27: =M27*10% -> 0
B28: MARZO
F29: SUBVENCION | G29: SUBVENCION | H29: 15571734 | J29: =+J27+H29-I29 -> 47330062 | L29: MARZO | M29: INGRESOS | N29: 10% ADM | O29: RR.HH. | P29: BNS Y SERV | Q29: SALDO
F30: REMUNERACIONES | G30: REMUNERACIONES | I30: 15571734 | J30: =+J29+H30-I30 -> 31758328 | M30: =+H29 -> 15571734 | N30: =+M30*10% -> 1557173.4 | O30: =+I30 -> 15571734 | P30: =I31+I32+I33+I34+I35+I36+I37+I38+I39+I40+I41+I42 -> 9375798 | Q30: =+M30-N30-O30-P30 -> -10932971
F31: FONDO A RENDIR | G31: FONDO A RENDIR | I31: 698890 | J31: =+J30+H31-I31 -> 31059438
B32: 46090 | C32: 6 | D32: 2321-153-TD26 | E32: 1205 | F32: LICENCIA SOFWARE | G32: LICENCIA SOFWARE | I32: 5236000 | J32: =+J31+H32-I32 -> 25823438
B33: 46092 | C33: 8 | D33: 85 | E33: 273 | F33: VESTUARIO | G33: VESTUARIO DEPORTIVO | I33: 124950 | J33: =+J32+H33-I33 -> 25698488
B34: 46092 | C34: 7 | D34: 86 | E34: 383 | F34: MATERIALES ENSEÑANZA | G34: LIBRERÍA | I34: 204600 | J34: =+J33+H34-I34 -> 25493888
B35: 46090 | C35: 4 | D35: 88 | E35: 376 | F35: INSUMO COMPUTACIONES | G35: TAMBOR | I35: 186002 | J35: =+J34+H35-I35 -> 25307886
B36: 46090 | C36: 5 | D36: 87 | E36: 274 | F36: GASTOS MENORES | G36: ALARGADORES | I36: 207603 | J36: =+J35+H36-I36 -> 25100283
E37: 293 | F37: INTERNET | G37: INTERNET | I37: 495360 | J37: =+J36+H37-I37 -> 24604923
E38: 292 | F38: FONDO A RENDIR | G38: FONDO A RENDIR | I38: 698890 | J38: =+J37+H38-I38 -> 23906033
B39: 46106 | C39: 12 | D39: 172 | E39: 600 | F39: MATERIALES ENSEÑANZA | G39: INSUMO GASTRONOMICOS | I39: 209492 | J39: =+J38+H39-I39 -> 23696541
B40: 46106 | C40: 13 | D40: 2321-158-AG236 | E40: 875 | F40: EQUIPO DE OFICINA | G40: LAPTOP | I40: 899990 | J40: =+J39+H40-I40 -> 22796551
B41: 46106 | C41: 14 | D41: 173 | E41: 422 | F41: MATERIALES ENSEÑANZA | G41: JUEGO AJEDREZ | I41: 206999 | J41: =+J40+H41-I41 -> 22589552
B42: 46107 | C42: 16 | D42: 215 | E42: 759 | F42: TEXTILES | G42: TEXTILES | I42: 207022 | J42: =+J41+H42-I42 -> 22382530
J43: =+J42+H43-I43 -> 22382530
J44: =+J43+H44-I44 -> 22382530
J45: =+J44+H45-I45 -> 22382530
J46: =+J45+H46-I46 -> 22382530
J47: =+J46+H47-I47 -> 22382530
B48: ABRIL
F49: SUBVENCION | G49: SUBVENCION | H49: =SUBVENCION!I5+SUBVENCION!J5 -> 23258553 | J49: =+J47+H49-I49 -> 45641083 | L49: ABRIL | M49: INGRESOS | N49: 10% ADM | O49: RR.HH. | P49: BNS Y SERV | Q49: SALDO
F50: REMUNERACIONES | G50: REMUNERACIONES | I50: 17728688 | J50: =+J49+H50-I50 -> 27912395 | M50: =+H49 -> 23258553 | N50: =+M50*10% -> 2325855.3 | O50: =+I50 -> 17728688 | P50: =SUM(I51:I65) -> 5023003 | Q50: =+M50-N50-O50-P50 -> -1818993.3
E51: 455 | F51: INTERNET | G51: INTERNET | I51: 488340 | J51: =+J50+H51-I51 -> 27424055
B52: 46114 | C52: 18 | D52: 216 | E52: 417 | F52: MATERIALES ENSEÑANZA | G52: MATERIALES ENSEÑANZA | I52: 206540 | J52: =+J51+H52-I52 -> 27217515
B53: 46121 | C53: 25 | D53: 2321-203-AG26 | E53: 1189 | F53: EQUIPO | G53: AIRE ACONDICINADO | I53: 1905000 | J53: =+J52+H53-I53 -> 25312515
B54: 46120 | C54: 22 | D54: 246 | E54: 600 | F54: MATERIALES ENSEÑANZA | G54: LIBRERÍA | I54: 209009 | J54: =+J53+H54-I54 -> 25103506
B55: 46120 | C55: 23 | D55: 248 | E55: 583 | F55: MATERIALES ENSEÑANZA | G55: RESMA | I55: 209620 | J55: =+J54+H55-I55 -> 24893886
B56: 46120 | C56: 24 | D56: 249 | E56: 883 | F56: COLACIONES | G56: COLACIONES | I56: 208500 | J56: =+J55+H56-I56 -> 24685386
B57: 46121 | C57: 27 | D57: 260 | E57: 572 | F57: PREMIOS | G57: PREMIOS | I57: 206774 | J57: =+J56+H57-I57 -> 24478612
B58: 46129 | C58: 31 | D58: 322 | E58: 655 | F58: COLACIONES | G58: COLACIONES | I58: 192780 | J58: =+J57+H58-I58 -> 24285832
B59: 46129 | C59: 32 | D59: 323 | E59: 574 | F59: INSUMO COMPUTACIONES | G59: TONER | I59: 173959 | J59: =+J58+H59-I59 -> 24111873
B60: 46132 | C60: 33 | D60: 324 | E60: 638 | F60: MATERIALES ENSEÑANZA | G60: MATERIALES ENSEÑANZA | I60: 209607 | J60: =+J59+H60-I60 -> 23902266
B61: 46132 | C61: 35 | D61: 344 | E61: 583 | F61: MATERIALES ENSEÑANZA | G61: MATERIALES ENSEÑANZA | I61: 209500 | J61: =+J60+H61-I61 -> 23692766
B62: 46135 | C62: 37 | D62: 345 | E62: 576 | F62: INSUMO COMPUTACIONES | G62: TINTAS | I62: 202500 | J62: =+J61+H62-I62 -> 23490266
B63: 46135 | C63: 38 | D63: 346 | E63: 600 | F63: MATERIALES ENSEÑANZA | G63: MATERIALES ENSEÑANZA | I63: 206741 | J63: =+J62+H63-I63 -> 23283525
B64: 46135 | C64: 39 | D64: 347 | E64: 574 | F64: INSUMO COMPUTACIONES | G64: TAMBOR | I64: 186002 | J64: =+J63+H64-I64 -> 23097523
B65: 46136 | C65: 41 | D65: 357 | E65: 700 | F65: MATERIALES ENSEÑANZA | G65: MATERIALES ENSEÑANZA | I65: 208131 | J65: =+J64+H65-I65 -> 22889392
J66: =+J65+H66-I66 -> 22889392
B67: MAYO
F68: SUBVENCION | H68: =SUBVENCION!K5+SUBVENCION!L5 -> 25259627 | J68: =+J66+H68-I68 -> 48149019 | L68: MAYO | M68: INGRESOS | N68: 10% ADM | O68: RR.HH. | P68: BNS Y SERV | Q68: SALDO
F69: REMUNERACIONES | G69: REMUNERACIONES | I69: 17776958 | J69: =+J68+H69-I69 -> 30372061 | M69: =+H68 -> 25259627 | N69: =+M69*10% -> 2525962.7 | O69: =+I69 -> 17776958 | P69: =I70+I71+I72+I73+I74+I75+I76+I77+I78+I79+I80+I81 -> 13806835 | Q69: =+M69-N69-O69-P69 -> -8850128.7
B70: 46155 | C70: 43 | D70: 453 | E70: 745 | F70: MATERIALES ENSEÑANZA | G70: LIBRERÍA | I70: 208900 | J70: =+J69+H70-I70 -> 30163161
E71: 564 | I71: 499557 | J71: =+J70+H89-I71 -> 29663604
B72: 45932 | C72: 141 | D72: 2321-128-SE26 | E72: 776 | F72: MATERIAL ENSEÑANZA | G72: PANTALLAS INTERACTIVAS | I72: 11839405 | J72: =+J71+H72-I72 -> 17824199
B73: 46167 | C73: 47 | D73: 472 | E73: 746 | F73: MATERIALES ENSEÑANZA | G73: MATERIALES ENSEÑANZA | I73: 211359 | J73: =+J72+H73-I73 -> 17612840
B74: 46168 | C74: 48 | D74: 480 | E74: 744 | F74: INSUMO COMPUTACIONES | G74: INSUMO COMPUTACIONES | I74: 210873 | J74: =+J73+H74-I74 -> 17401967
B75: 46168 | C75: 50 | D75: 487 | E75: 841 | F75: COLACIONES | G75: COLACIONES | I75: 208500 | J75: =+J74+H75-I75 -> 17193467
B76: 46168 | C76: 49 | D76: 486 | E76: 876 | F76: COLACIONES | G76: COLACIONES | I76: 209440 | J76: =+J75+H76-I76 -> 16984027
B77: 46171 | C77: 51 | D77: 510 | E77: PP | F77: MATERIALES ENSEÑANZA | G77: MATERIALES ENSEÑANZA | I77: 209000 | J77: =+J76+H77-I77 -> 16775027
B78: 46171 | C78: 52 | D78: 511 | E78: 832 | F78: MATERIALES ENSEÑANZA | G78: RESMAS | I78: 209801 | J78: =+J77+H78-I78 -> 16565226
J79: =+J78+H79-I79 -> 16565226
J80: =+J79+H80-I80 -> 16565226
J81: =+J80+H81-I81 -> 16565226
B82: JUNIO
F83: SUBVENCION | G83: SUBVENCION | H83: =SUBVENCION!M5+SUBVENCION!N5 -> 27611342 | J83: =+J81+H83-I83 -> 44176568 | L83: JUNIO | M83: INGRESOS | N83: 10% ADM | O83: RR.HH. | P83: BNS Y SERV | Q83: SALDO
F84: REMUNERACIONES | G84: REMUNERACIONES | I84: 18065302 | J84: =+J83+H84-I84 -> 26111266 | M84: =+H83 -> 27611342 | N84: =+M84*10% -> 2761134.2 | O84: =+I84 -> 18065302 | P84: =SUM(I85:I93) -> 4041630 | Q84: =+M84-N84-O84-P84 -> 2743275.8
B85: 46174 | C85: 53 | D85: 520 | E85: 960 | F85: MATERIALES ENSEÑANZA | G85: LIBRERÍA | I85: 214500 | J85: =+J84+H85-I85 -> 25896766
B86: 46178 | C86: 54 | D86: 2321-179-AG26 | E86: 962 | F86: COLACIONES | G86: COLACIONES | I86: 1901620 | J86: =+J85+H86-I86 -> 23995146
B87: 46179 | C87: 55 | D87: 545 | E87: 1022 | F87: MATERIALES ENSEÑANZA | G87: LIBRERÍA | I87: 213842 | J87: =+J86+H87-I87 -> 23781304
B88: 46178 | C88: 57 | D88: 546 | E88: 958 | F88: INSUMO COMPUTACIONALES | G88: INSUMO COMPUTACIONALES | I88: 210002 | J88: =+J87+H88-I88 -> 23571302
E89: 791 | F89: INTERNET | G89: INTERNET | I89: 505708 | J89: =+J88+H89-I89 -> 23065594
B90: 46182 | C90: 60 | D90: 570 | E90: 951 | F90: MATERIALES ENSEÑANZA | G90: BALON DE FUTBON | I90: 214200 | J90: =+J89+H90-I90 -> 22851394
B91: 46191 | C91: 64 | D91: 2321-207-AG26 | E91: 1353 | F91: MATERIALES ENSEÑANZA | G91: MATERIALES ENSEÑANZA | I91: 361284 | J91: =+J90+H91-I91 -> 22490110
B92: 46183 | C92: 61 | D92: 606 | E92: PP | F92: COLACIONES | G92: COLACIONES | I92: 207584 | J92: =+J91+H92-I92 -> 22282526
B93: 46191 | C93: 63 | D93: 604 | E93: 1025 | F93: TELAS | G93: TELAS | I93: 212890 | J93: =+J92+H93-I93 -> 22069636
J94: =+J93+H94-I94 -> 22069636
B95: JULIO
F96: SUBVENCION | G96: SUBVENCION | H96: =+SUBVENCION!O5+SUBVENCION!P5 -> 25407336 | J96: =+J94+H96-I96 -> 47476972 | L96: JULIO | M96: INGRESOS | N96: 10% ADM | O96: RR.HH. | P96: BNS Y SERV | Q96: SALDO
F97: REMUNERACIONES | G97: REMUNERACIONES | I97: 18724435 | J97: =+J96+H97-I97 -> 28752537 | M97: =+H96 -> 25407336 | N97: =+M97*10% -> 2540733.6 | O97: =+I97 -> 18724435 | P97: =I98+I99+I100+I101+I102+I103+I104+I105+I106 -> 5317722 | Q97: =+M97-N97-O97-P97 -> -1175554.6
B98: 46210 | C98: 67 | D98: 633 | E98: 1074 | F98: INSUMOS COMPUTACIONALES | G98: TINTAS | I98: 214600 | J98: =+J97+H98-I98 -> 28537937
B99: 46212 | C99: 69 | D99: 2321-212-AG26 | E99: 1352 | F99: MATERIALES ENSEÑANZA | G99: MATERIALES LIBRERÍA | I99: 3678219 | J99: =+J98+H99-I99 -> 24859718
B100: 46217 | C100: 70 | D100: 661 | E100: 1153 | F100: MATERIAL ENSEÑANZA | G100: IMPLEMENTOS DEPORTIVOS | I100: 209601 | J100: =+J99+H100-I100 -> 24650117
B101: 46223 | C101: 74 | D101: 686 | E101: 1152 | F101: MATERIAL ENSEÑANZA | G101: INSUMOS TALLER GASTRONOMIA | I101: 213271 | J101: =+J100+H101-I101 -> 24436846
...

Sheet G-416
B2: UNIDAD DE FINANZAS DAEM
B3: LEY SEP
B4: ESCUELA: G-416 CANDELARIA PEREZ
B5: DIRECTOR: PAULINA TOLEDO HERNANDEZ
B6: SECTOR:
B7: RBD: 3517
B8: FECHA | C8: SOL | D8: OC | E8: DP | F8: CATEGORIA | G8: DETALLE | H8: INGRESOS | I8: GASTOS | J8: SALDO
G9: SALDO SEP 2025 | H9: 5512238 | J9: =+H9-I9 -> 5512238
B10: ENERO
F11: SUBVENCION | G11: SUBVENCION | H11: =SUBVENCION!C18+SUBVENCION!D18 -> 5498136 | J11: =+H11-I11+J9 -> 11010374 | L11: INGRESOS | M11: 10% ADM | N11: RR.HH. | O11: BNS Y SERV | P11: SALDO
F12: REMUNERACIONES | G12: REMUNERACIONES | I12: 3558445 | J12: =+J11+H12-I12 -> 7451929 | L12: =H11 -> 5498136 | M12: =L12*10% -> 549813.6 | N12: =I12 -> 3558445 | O12: =I13+I14+I15+I16+I17 -> 1284578 | P12: =L12-M12-N12-O12 -> 105299.4
B13: 45952 | C13: 137 | D13: 2321-459-AG25 | E13: 14 | F13: MATERIALES OFICINA | G13: LIBRERÍA | I13: 1263676 | J13: =+J12+H13-I13 -> 6188253
E14: 12 | F14: INTERNET | G14: INTERNET | I14: 20902 | J14: =+J13+H14-I14 -> 6167351
J15: =+J14+H15-I15 -> 6167351
J16: =+J15+H16-I16 -> 6167351
J17: =+J16+H17-I17 -> 6167351
B18: FEBRERO
F19: SUBVENCION | G19: SUBVENCION | H19: =SUBVENCION!E18+SUBVENCION!F18 -> 5832393 | J19: =+J17+H19-I19 -> 11999744 | L19: INGRESOS | M19: 10% ADM | N19: RR.HH. | O19: BNS Y SERV | P19: SALDO
F20: REMUNERACIONES | G20: REMUNERACIONES | I20: 3558445 | J20: =+J19+H20-I20 -> 8441299 | L20: =H19 -> 5832393 | M20: =L20*10% -> 583239.3 | N20: =I20 -> 3558445 | O20: =I21 -> 20766 | P20: =L20-M20-N20-O20 -> 1669942.7
E21: 130 | F21: INTERNET | G21: INTERNET | I21: 20766 | J21: =+J20+H21-I21 -> 8420533
B22: MARZO
F23: SUBVENCION | G23: SUBVENCION | H23: =SUBVENCION!G18+SUBVENCION!H18 -> 5608104 | J23: =+J21+H23-I23 -> 14028637
F24: REMUNERACIONES | G24: REMUNERACIONES | I24: 3065789 | J24: =+J23+H24-I24 -> 10962848 | L24: INGRESOS | M24: 10% ADM | N24: RR.HH. | O24: BNS Y SERV | P24: SALDO
B25: 46090 | C25: 3 | D25: 69 | E25: 272 | F25: MATERIALES ENSEÑANZA | G25: MATERIALES ENSEÑANZA | I25: 200000 | J25: =+J24+H25-I25 -> 10762848 | L25: =H23 -> 5608104 | M25: =L25*10% -> 560810.4 | N25: =I24 -> 3065789 | O25: =I25+I26+I27+I28+I29++I30+I31+I32+I33 -> 1607660 | P25: =L25-M25-N25-O25 -> 373844.6
B26: 46097 | C26: 5 | D26: 120 | E26: 382 | F26: MATERIALES DE ENSEÑANZA | G26: LIBROS | I26: 209651 | J26: =+J25+H26-I26 -> 10553197
E27: 222 | F27: INTERNET | G27: INTERNET | I27: 20766 | J27: =+J26+H27-I27 -> 10532431
B28: 46098 | C28: 7 | D28: 138 | E28: 404 | F28: MATERIALES ENSEÑANZA | G28: SET MALLA TALLER DEPORTE | I28: 44000 | J28: =+J27+H28-I28 -> 10488431
B29: 46097 | C29: 6 | D29: 139 | E29: 425 | F29: MATERIALES ENSEÑANZA | G29: MATERIALES ARTES | I29: 209000 | J29: =+J28+H29-I29 -> 10279431
B30: 23-03-206 | C30: 9 | D30: 2321-120-AG26 | E30: 778 | F30: BATERIAS EVALUA | G30: BATERIAS EVALUA | I30: 494624 | J30: =+J29+H30-I30 -> 9784807
B31: 46104 | C31: 10 | D31: 155 | E31: 607 | F31: MATERIALES ENSEÑANZA | G31: LIBRERÍA | I31: 194780 | J31: =+J30+H31-I31 -> 9590027
B32: 46106 | C32: 12 | D32: 171 | E32: 407 | F32: INSUMO COMPUTACIONALES | G32: TINTAS | I32: 207840 | J32: =+J31+H32-I32 -> 9382187
B33: 45741 | C33: 13 | D33: 175 | E33: 386 | F33: PREMIOS | G33: PREMIOS | I33: 26999 | J33: =+J32+H33-I33 -> 9355188
B34: ABRIL
F35: SUBVENCION | G35: SUBVENCION | H35: =SUBVENCION!I18+SUBVENCION!J18 -> 5678407 | J35: =+J33+H35-I35 -> 15033595
F36: REMUNERACIONES | G36: REMUNERACIONES | I36: 2902406 | J36: =+J35+H36-I36 -> 12131189 | L36: INGRESOS | M36: 10% ADM | N36: RR.HH. | O36: BNS Y SERV | P36: SALDO
E37: 350 | F37: INTERNET | G37: INTERNET | I37: 20968 | J37: =+J36+H37-I37 -> 12110221 | L37: =H35 -> 5678407 | M37: =L37*10% -> 567840.7 | N37: =I36 -> 2902406 | O37: =I37+I38+I39+I40+I41+I42+I43+I44+I45+I46 -> 1791909 | P37: =L37-M37-N37-O37 -> 416251.3
B38: 46114 | C38: 15 | D38: 218 | E38: 408 | F38: MANTENCION EQUIPO | G38: MANTENCION EQUIPO | I38: 194999 | J38: =+J37+H38-I38 -> 11915222
B39: 46126 | C39: 22 | D39: 2321-123-AG26 | E39: 777 | F39: COLACIONES | G39: COLACIONES | I39: 390737 | J39: =+J38+H39-I39 -> 11524485
B40: 46126 | C40: 21 | D40: 2321-135-AG26 | E40: 961 | F40: MOBILIARIO | G40: BANCA CAMARIN | I40: 380800 | J40: =+J39+H40-I40 -> 11143685
B41: 46126 | C41: 20 | D41: 290 | E41: 601 | F41: TRASNPORTE | G41: TRASLADO | I41: 207000 | J41: =+J40+H41-I41 -> 10936685
B42: 46126 | C42: 19 | D42: 289 | E42: 600 | F42: COLACIONES | G42: COLACIONES | I42: 208964 | J42: =+J41+H42-I42 -> 10727721
B43: 46126 | C43: 18 | D43: 288 | E43: 602 | F43: INSUMO COMPUTACIONALES | G43: INSUMO COMPUTACIONALES | I43: 181840 | J43: =+J42+H43-I43 -> 10545881
B44: 46126 | C44: 17 | D44: 287 | E44: 576 | F44: MATERIALES DE ENSEÑANZA | G44: LIBRERÍA | I44: 206601 | J44: =+J43+H44-I44 -> 10339280
B45: 46141 | C45: 25 | D45: NULA | E45: NULA | F45: MATERIALES CONSTRUCCION | G45: MATERIALES CONSTRUCCION | I45: 0 | J45: =+J44+H45-I45 -> 10339280
B46: 46140 | C46: 24 | D46: 387 | E46: NULA | I46: 0 | J46: =+J45+H46-I46 -> 10339280
B47: MAYO
F48: SUBVENCION | G48: SUBVENCION | H48: =SUBVENCION!K18+SUBVENCION!L18 -> 5636204 | J48: =+J46+H48-I48 -> 15975484
F49: REMUNERACIONES | G49: REMUNERACIONES | I49: 2884277 | J49: =+J48+H49-I49 -> 13091207 | L49: INGRESOS | M49: 10% ADM | N49: RR.HH. | O49: BNS Y SERV | P49: SALDO
B50: 46148 | C50: 26 | D50: 391 | E50: 747 | F50: COLACIONES | G50: COLACIONES | I50: 209000 | J50: =+J49+H50-I50 -> 12882207 | L50: =H48 -> 5636204 | M50: =L50*10% -> 563620.4 | N50: =I49 -> 2884277 | O50: =I50+I51+I52+I53+I54+I55 -> 23729557 | P50: =L50-M50-N50-O50 -> -21541250
B51: 46148 | C51: 27 | D51: 392 | E51: 1418 | F51: MANTECION EQUIPO OFICINA | G51: MANTECION EQUIPO OFICINA | I51: 208250 | J51: =+J50+H51-I51 -> 12673957
B52: 46149 | C52: 28 | D52: 415 | E52: 827 | F52: PREMIOS | G52: PREMIOS | I52: 208845 | J52: =+J51+H52-I52 -> 12465112
B53: 46150 | C53: 29 | D53: 2321-205-SE26 | F53: MATERIALES CONSTRUCCION | G53: MATERIALES CONSTRUCCION | I53: 22909404 | J53: =+J52+H53-I53 -> -10444292
B54: 46167 | C54: 32 | D54: 478 | E54: 726 | F54: OTROS SERVICIOS | G54: SHOW TEATRAL | I54: 172890 | J54: =+J53+H54-I54 -> -10617182
E55: 563 | F55: INTERNET | G55: INTERNET | I55: 21168 | J55: =+J54+H55-I55 -> -10638350
B56: JUNIO
F57: SUBVENCION | G57: SUBVENCION | H57: =SUBVENCION!M18+SUBVENCION!N18 -> 5340174 | J57: =+J55+H57-I57 -> -5298176 | L57: INGRESOS | M57: 10% ADM | N57: RR.HH. | O57: BNS Y SERV | P57: SALDO
F58: REMUNERACIONES | G58: REMUNERACIONES | I58: 2960791 | J58: =+J57+H58-I58 -> -8258967 | L58: =H57 -> 5340174 | M58: =L58*10% -> 534017.4 | N58: =I58 -> 2960791 | O58: =I59+I60+I61+I62 -> 21212 | P58: =L58-M58-N58-O58 -> 1824153.6
E59: 734 | F59: INTERNET | G59: INTERNET | I59: 21212 | J59: =+J58+H59-I59 -> -8280179
J60: =+J59+H60-I60 -> -8280179
J61: =+J60+H61-I61 -> -8280179
J62: =+J61+H62-I62 -> -8280179
B63: JULIO
F64: SUBVENCION | G64: SUBVENCION | H64: =+SUBVENCION!O18+SUBVENCION!P18 -> 5485314 | J64: =+J62+H64-I64 -> -2794865 | L64: INGRESOS | M64: 10% ADM | N64: RR.HH. | O64: BNS Y SERV | P64: SALDO
F65: REMUNERACIONES | G65: REMUNERACIONES APROX JULIO | I65: 2892589 | J65: =+J64+H65-I65 -> -5687454 | L65: =H64 -> 5485314 | M65: =L65*10% -> 548531.4 | N65: =I65 -> 2892589 | O65: =I66+I67 -> 21012 | P65: =L65-M65-N65-O65 -> 2023181.6
E66: 944 | F66: INTERNET | G66: INTERNET | I66: 21012 | J66: =+J65+H66-I66 -> -5708466
J67: =+J66+H67-I67 -> -5708466
B68: AGOSTO
F69: SUBVENCION | G69: SUBVENCION | H69: =SUBVENCION!Q18+SUBVENCION!R18 -> 5312763 | J69: =+J67+H69-I69 -> -395703
F70: REMUNERACIONES | G70: REMUNERACIONES | I70: 2899727 | J70: =+J69+H70-I70 -> -3295430 | L70: INGRESOS | M70: 10% ADM | N70: RR.HH. | O70: BNS Y SERV | P70: SALDO
E71: 1178 | F71: INTERNET | G71: INTERNET | I71: 21358 | J71: =+J70+H71-I71 -> -3316788 | L71: =H69 -> 5312763 | M71: =L71*10% -> 531276.3 | N71: =I70 -> 2899727 | O71: =I71+I72 -> 21358 | P71: =L71-M71-N71-O71 -> 1860401.7
J72: =+J71+H72-I72 -> -3316788
B73: SEPTIEMBRE
F74: SUBVENCION | G74: SUBVENCION | H74: =SUBVENCION!S18+SUBVENCION!T18 -> 5161923 | J74: =+J72+H74-I74 -> 1845135 | L74: INGRESOS | M74: 10% ADM | N74: RR.HH. | O74: BNS Y SERV | P74: SALDO
F75: REMUNERACIONES | G75: REMUNERACIONES | I75: 2900234 | J75: =+J74+H75-I75 -> -1055099 | L75: =H74 -> 5161923 | M75: =L75*10% -> 516192.3 | N75: =I75 -> 2900234 | O75: =SUM(I76:I77) -> 214736 | P75: =L75-M75-N75-O75 -> 1530760.7
B76: 46289 | C76: 39 | D76: 1012 | F76: COLACIONES | G76: COLACIONES | I76: 214736 | J76: =+J75+H76-I76 -> -1269835
J77: =+J76+H77-I77 -> -1269835
B78: OCTUBRE
F79: SUBVENCION | G79: SUBVENCION | H79: =SUBVENCION!U18+SUBVENCION!V18 -> 0 | J79: =J77+H79-I79 -> -1269835 | L79: INGRESOS | M79: 10% ADM | N79: RR.HH. | O79: BNS Y SERV | P79: SALDO
F80: REMUNERACIONES | G80: REMUNERACIONES | J80: =+J79+H80-I80 -> -1269835 | L80: =H79 -> 0 | M80: =H79*10% -> 0 | N80: =I80 -> 0 | O80: =I81+I82+I83+I84+I85 -> 0 | P80: =L80-M80-N80-O80 -> 0
J81: =+J80+H81-I81 -> -1269835
J82: =+J81+H82-I82 -> -1269835
J83: =+J82+H83-I83 -> -1269835
J84: =+J83+H84-I84 -> -1269835
J85: =+J84+H85-I85 -> -1269835
B86: NOVIEMBRE
F87: SUBVENCION | G87: SUBVENCION | H87: =SUBVENCION!W18+SUBVENCION!X18 -> 0 | J87: =+J85+H87-I87 -> -1269835 | L87: INGRESOS | M87: 10% ADM | N87: RR.HH. | O87: BNS Y SERV | P87: SALDO
F88: REMUNERACIONES | G88: REMUNERACIONES | J88: =+J87+H88-I88 -> -1269835 | L88: =H87 -> 0 | M88: =H87*10% -> 0 | N88: =I88 -> 0 | O88: =I89+I90+I91+I92+I93+I94 -> 0 | P88: =L88-M88-N88-O88 -> 0
J89: =+J88+H89-I89 -> -1269835
J90: =+J89+H90-I90 -> -1269835
J91: =+J90+H91-I91 -> -1269835
J92: =+J91+H92-I92 -> -1269835
J93: =+J92+H93-I93 -> -1269835
J94: =+J93+H94-I94 -> -1269835
B95: DICIEMBRE
F96: SUBVENCION | G96: SUBVENCION | H96: =SUBVENCION!Y18+SUBVENCION!Z18 -> 0 | J96: =+J94+H96-I96 -> -1269835 | L96: INGRESOS | M96: 10% ADM | N96: RR.HH. | O96: BNS Y SERV | P96: SALDO
F97: REMUNERACIONES | G97: REMUNERACIONES | J97: =+J96+H97-I97 -> -1269835 | L97: =H96 -> 0 | M97: =H96*10% -> 0 | N97: =I97 -> 0 | P97: =L97-M97-N97-O97 -> 0
J98: =+J97+H98-I98 -> -1269835
J99: =+J98+H99-I99 -> -1269835
J100: =+J99+H100-I100 -> -1269835
J101: =+J100+H101-I101 -> -1269835
...

Sheet E-417
B2: UNIDAD DE FINANZAS DAEM
B3: LEY SEP
B4: ESCUELA: E-417 JUSTA NARVAEZ RBD 3482
B5: DIRECTOR: FERNANDO JARAMILLO
B6: SECTOR:
B7: RBD: 3482
B8: FECHA | C8: SOL | D8: OC | E8: DP | F8: CATEGORIA | G8: DETALLE | H8: INGRESOS | I8: GASTOS | J8: SALDO
G9: SALDO SEP 2025 | H9: ='[1]E-417'!$J$149 -> 5843683 | J9: =+H9-I9 -> 5843683
B10: ENERO
F11: SUBVENCION | G11: SUBVENCION | H11: =SUBVENCION!C6+SUBVENCION!D6 -> 14182089 | J11: =+J9+H11-I11 -> 20025772 | K11: ENERO | L11: INGRESOS | M11: 10% ADM | N11: RR.HH. | O11: BNS Y SERV | P11: SALDO
F12: REMUNERACIONES | G12: REMUNERACIONES | I12: 10527943 | J12: =+J11+H12-I12 -> 9497829 | L12: =+H11 -> 14182089 | M12: =+L12*10% -> 1418208.9 | N12: =+I12 -> 10527943 | O12: =I13+I14 -> 55462 | P12: =+L12-M12-N12-O12 -> 2180475.1
E13: 11 | F13: INTERNET | G13: INTERNET | I13: 27731 | J13: =+J12+H13-I13 -> 9470098
E14: 92 | F14: INTERNET | G14: INTERNET | I14: 27731 | J14: =+J13+H14-I14 -> 9442367
B15: FEBRERO
F16: SUBVENCION | G16: SUBVENCION | H16: =SUBVENCION!E6+SUBVENCION!F6 -> 14313112 | J16: =+J14+H16-I16 -> 23755479 | K16: FEBRERO | L16: INGRESOS | M16: 10% ADM | N16: RR.HH. | O16: BNS Y SERV | P16: SALDO
F17: REMUNERACIONES | G17: REMUNERACIONES | I17: 11157706 | J17: =+J16+H17-I17 -> 12597773 | L17: =+H16 -> 14313112 | M17: =+L17*10% -> 1431311.2 | N17: =+I17 -> 11157706 | O17: =+I18+I19 -> 1827772 | P17: =+L17-M17-N17-O17 -> -103677.2
B18: 46079 | C18: 1 | D18: 2321-279-TD26 | E18: PP | F18: PLATAFORMA | G18: PLATAFORMA | I18: 1800000 | J18: =+J17+H18-I18 -> 10797773
E19: 163 | F19: INTERNET | G19: INTERNET | I19: 27772 | J19: =+J18+H19-I19 -> 10770001
J20: =+J19+H20-I20 -> 10770001
B21: MARZO
F22: SUBVENCION | G22: SUBVENCION | H22: =SUBVENCION!G6+SUBVENCION!H6 -> 14225576 | J22: =+J20+H22-I22 -> 24995577 | K22: MARZO | L22: INGRESOS | M22: 10% ADM | N22: RR.HH. | O22: BNS Y SERV | P22: SALDO
F23: REMUNERACIONES | G23: REMUNERACIONES | I23: 9385199 | J23: =+J22+H23-I23 -> 15610378 | L23: =+H22 -> 14225576 | M23: =+L23*10% -> 1422557.6 | N23: =+I23 -> 9385199 | O23: =I24+I25+I26+I27+I28+I29+I30+I31+I32+I33+I34+I35 -> 2289316 | P23: =+L23-M23-N23-O23 -> 1128503.4
B24: 46084 | C24: 5 | D24: 25 | E24: 575 | F24: MATERIALES DE ENSEÑANZA | G24: LIBRERÍA | I24: 205459 | J24: =+J23+H24-I24 -> 15404919
B25: 46084 | C25: 6 | D25: 26 | E25: 257 | F25: MATERIALES DE ENSEÑANZA | G25: LIBRERÍA | I25: 205500 | J25: =+J24+H25-I25 -> 15199419
B26: 46085 | C26: 12 | D26: 40 | E26: 574 | F26: INSUMO COMPUTACIONALES | G26: TINTAS | I26: 205555 | J26: =+J25+H26-I26 -> 14993864
B27: 46087 | C27: 16 | D27: 58 | E27: 380 | F27: MATERIALES DE ENSEÑANZA | G27: MATERIALES DIDACTICOS | I27: 191860 | J27: =+J26+H27-I27 -> 14802004
B28: 46090 | C28: 17 | D28: 59 | E28: 424 | F28: COLACIONES | G28: COLACIONES | I28: 208000 | J28: =+J27+H28-I28 -> 14594004
B29: 46099 | C29: 18 | D29: 134 | E29: 376 | F29: INSUMO COMPUTACIONALES | G29: TINTAS | I29: 208803 | J29: =+J28+H29-I29 -> 14385201
B30: 46099 | C30: 19 | D30: 135 | E30: 385 | F30: GASTOS MENORES | G30: LIENZO- PENDON - PIOCHA | I30: 208559 | J30: =+J29+H30-I30 -> 14176642
F31: INTERNET | G31: INTERNET | I31: 27731 | J31: =+J30+H31-I31 -> 14148911
B32: 46101 | C32: 20 | D32: 177 | E32: 374 | F32: COLACIONES | G32: COLACIONES | I32: 207970 | J32: =+J31+H32-I32 -> 13940941
B33: 46107 | C33: 21 | D33: 178 | E33: 379 | F33: MATERIALES DE ENSEÑANZA | G33: INSTRUMENTO MUSICALES | I33: 202889 | J33: =+J32+H33-I33 -> 13738052
B34: 46107 | C34: 23 | D34: 179 | E34: 426 | F34: COLACIONES | G34: COLACIONES | I34: 208000 | J34: =+J33+H34-I34 -> 13530052
B35: 46108 | C35: 24 | D35: 180 | E35: 408 | F35: EQUIPO DE OFICINA | G35: IMPRESORA | I35: 208990 | J35: =+J34+H35-I35 -> 13321062
B36: ABRIL
F37: SUBVENCION | G37: SUBVENCION | H37: =SUBVENCION!I6+SUBVENCION!J6 -> 13989832 | J37: =+J35+H37-I37 -> 27310894 | K37: ABRIL | L37: INGRESOS | M37: 10% ADM | N37: RR.HH. | O37: BNS Y SERV | P37: SALDO
F38: REMUNERACIONES | G38: REMUNERACIONES | I38: 10858560 | J38: =+J37+H38-I38 -> 16452334 | L38: =+H37 -> 13989832 | M38: =+L38*10% -> 1398983.2 | N38: =+I38 -> 10858560 | O38: =I39+I40+I41+I42+I43+I44+I45+I46+I47+I48+I49 -> 2603700 | P38: =+L38-M38-N38-O38 -> -871411.2
B39: 46119 | C39: 29 | D39: 259 | E39: 567 | F39: TRANSPORTE | G39: TRASLADO | I39: 150000 | J39: =+J38+H39-I39 -> 16302334
B40: 46121 | C40: 30 | D40: 295 | E40: 599 | F40: COLACIONES | G40: COLACIONES | I40: 209080 | J40: =+J39+H40-I40 -> 16093254
B41: 46128 | C41: 35 | D41: 2321-240-AG26 | E41: 1349 | F41: EQUIPO DE OFICINA | G41: PROYECTOR | I41: 547138 | J41: =+J40+H41-I41 -> 15546116
B42: 46121 | C42: 31 | D42: 308 | E42: 575 | F42: MATERIALES DE ENSEÑANZA | G42: LIBRERÍA | I42: 209000 | J42: =+J41+H42-I42 -> 15337116
B43: 46121 | C43: 33 | D43: 309 | E43: 574 | F43: EQUIPO DE OFICINA | G43: IMPRESORA | I43: 208990 | J43: =+J42+H43-I43 -> 15128126
B44: 46129 | C44: 40 | D44: 313 | E44: 643 | F44: MATERIALES DE ENSEÑANZA | G44: LIBRERÍA | I44: 207790 | J44: =+J43+H44-I44 -> 14920336
B45: 46134 | C45: 41 | D45: 311 | E45: 649 | F45: COLACIONES | G45: COLACIONES | I45: 209000 | J45: =+J44+H45-I45 -> 14711336
B46: 46134 | C46: 42 | D46: 312 | E46: 699 | F46: PREMIOS | G46: JUEGOS | I46: 209000 | J46: =+J45+H46-I46 -> 14502336
B47: 46136 | C47: 43 | D47: 2321-149-AG26 | E47: 1167 | F47: ESTUFA | G47: ESTUFA | I47: 420967 | J47: =+J46+H47-I47 -> 14081369
B48: 46141 | C48: 44 | D48: 371 | E48: 744 | F48: EQUIPO DE OFICINA | G48: IMPRESORA | I48: 208990 | J48: =+J47+H48-I48 -> 13872379
E49: 549 | F49: INTERNET | G49: INTERNET | I49: 23745 | J49: =+J48+H49-I49 -> 13848634
J50: =+J49+H50-I50 -> 13848634
J51: =+J50+H51-I51 -> 13848634
B52: MAYO
F53: SUBVENCION | G53: SUBVENCION | H53: =SUBVENCION!K6+SUBVENCION!L6 -> 13981020 | J53: =+J51+H53-I53 -> 27829654 | K53: MAYO | L53: INGRESOS | M53: 10% ADM | N53: RR.HH. | O53: BNS Y SERV | P53: SALDO
F54: REMUNERACIONES | G54: REMUNERACIONES | I54: 10911342 | J54: =+J53+H54-I54 -> 16918312 | L54: =+H53 -> 13981020 | M54: =+L54*10% -> 1398102 | N54: =+I54 -> 10911342 | O54: =I55+I57+I58+I59+I56 -> 3535407 | P54: =+L54-M54-N54-O54 -> -1863831
B55: 46153 | C55: 47 | D55: 440 | E55: 747 | F55: COLACIONES | G55: COLACIONES | I55: 209040 | J55: =+J54+H55-I55 -> 16709272
B56: 46162 | C56: 49 | D56: 485 | F56: MATERIALES DE ENSEÑANZA | G56: LIBRERÍA | I56: 206000 | J56: =+J55+H56-I56 -> 16503272
B57: 46170 | C57: 53 | D57: 2321-202-AG26 | E57: 1165 | F57: EQUIPOS COMPUTACIONALES | G57: EQUIPOS COMPUTACIONALES | I57: 2888832 | J57: =+J56+H57-I57 -> 13614440
B58: 46170 | C58: 52 | D58: 501 | E58: 1197 | F58: INSUMO COMPUTACIONALES | G58: TINTAS | I58: 203834 | J58: =+J57+H58-I58 -> 13410606
E59: 564 | F59: INTERNET | G59: INTERNET | I59: 27701 | J59: =+J58+H59-I59 -> 13382905
J60: =+J59+H60-I60 -> 13382905
B61: JUNIO
F62: SUBVENCION | G62: SUBVENCION | H62: =SUBVENCION!M6+SUBVENCION!N6 -> 10288671 | J62: =+J60+H62-I62 -> 23671576 | L62: INGRESOS | M62: 10% ADM | N62: RR.HH. | O62: BNS Y SERV | P62: SALDO
F63: REMUNERACIONES | G63: REMUNERACIONES | I63: 10734895 | J63: =+J62+H63-I63 -> 12936681 | L63: =+H62 -> 10288671 | M63: =+L63*10% -> 1028867.1 | N63: =+I63 -> 10734895 | O63: =I64+I65 -> 28041 | P63: =+L63-M63-N63-O63 -> -1503132.1
E64: 793 | F64: INTERNET | G64: INTERNET | I64: 28041 | J64: =+J63+H64-I64 -> 12908640
J65: =+J64+H65-I65 -> 12908640
B66: JULIO
F67: SUBVENCION | G67: SUBVENCION | H67: =+SUBVENCION!O6+SUBVENCION!P6 -> 13407107 | J67: =+J65+H67-I67 -> 26315747 | L67: INGRESOS | M67: 10% ADM | N67: RR.HH. | O67: BNS Y SERV | P67: SALDO
F68: REMUNERACIONES | G68: REMUNERACIONES | I68: 11221929 | J68: =+J67+H68-I68 -> 15093818 | L68: =+H67 -> 13407107 | M68: =+L68*10% -> 1340710.7 | N68: =+I68 -> 11221929 | O68: =I69+I70+I71+I72+I73+I74+I75+I78+I76+I77 -> 1928477 | P68: =+L68-M68-N68-O68 -> -1084009.7
B69: 46162 | C69: 137 | D69: 629 | E69: 1027 | F69: PREMIOS | G69: MEDALLAS | I69: 164220 | J69: =+J68+H69-I69 -> 14929598
B70: 46162 | C70: 50 | D70: 683 | E70: 1212 | F70: MATERIAL ENSEÑANZA | G70: OPALINA PLUMONES ETC | I70: 209100 | J70: =+J69+H70-I70 -> 14720498
B71: 46226 | C71: 143 | D71: 725 | E71: 1198 | F71: MATERIAL DE OFICINA | G71: RESMAS | I71: 205630 | J71: =+J70+H71-I71 -> 14514868
B72: 46226 | C72: 144 | D72: 726 | E72: 1199 | F72: MATERIAL ENSEÑANZA | G72: MATERIALES TALLER COCINA | I72: 209750 | J72: =+J71+H72-I72 -> 14305118
B73: 46230 | C73: 145 | D73: 727 | E73: 1196 | F73: COLACIONES | G73: COLACIONES | I73: 214290 | J73: =+J72+H73-I73 -> 14090828
E74: 995 | F74: INTERNET | G74: INTERNET | I74: 28177 | J74: =+J73+H74-I74 -> 14062651
B75: 46233 | C75: 148 | D75: 770 | E75: 1257 | F75: INSUMO COMPUTACIONALES | G75: ACCESORIOS COMPUTACIONALES | I75: 189438 | J75: =+J74+H75-I75 -> 13873213
B76: 46231 | C76: 146 | D76: 2321-238-AG26 | E76: 1298 | F76: TRANSPORTE | G76: TRASLADO | I76: 477000 | J76: =+J75+H76-I76 -> 13396213
B77: 46231 | C77: 147 | D77: 2321-243-AG26 | E77: 1298 | F77: VISITA PEDAGOGICA | G77: VISITA PEDAGOGICA | I77: 230872 | J77: =+J76+H77-I77 -> 13165341
J78: =+J77+H78-I78 -> 13165341
B79: AGOSTO
F80: SUBVENCION | G80: SUBVENCION | H80: =+SUBVENCION!Q6+SUBVENCION!R6 -> 13398689 | J80: =+J78+H80-I80 -> 26564030 | L80: INGRESOS | M80: 10% ADM | N80: RR.HH. | O80: BNS Y SERV | P80: SALDO
F81: REMUNERACIONES | G81: REMUNERACIONES | I81: 11784182 | J81: =+J80+H81-I81 -> 14779848 | L81: =+H80 -> 13398689 | M81: =+L81*10% -> 1339868.9 | N81: =+I81 -> 11784182 | O81: =+I83+I84+I85+I86+I87+I88+I89+I93+I90+I91+I82 -> 1735057 | P81: =+L81-M81-N81-O81 -> -1460418.9
E82: 1324 | F82: INTERNET | G82: INTERNET | I82: 28191 | J82: =+J81+H82-I82 -> 14751657
B83: 46239 | C83: 149 | D83: 771 | E83: 1256 | F83: MATERIAL DE OFICINA | G83: RESMAS | I83: 213300 | J83: =+J82+H83-I83 -> 14538357
B84: 46245 | C84: 150 | D84: 787 | E84: 1291 | F84: COLACIONES | G84: COLACIONES | I84: 84700 | J84: =+J83+H84-I84 -> 14453657
B85: 46245 | C85: 151 | D85: 788 | E85: 1318 | F85: MATERIAL ENSEÑANZA | G85: UTILES ESCOLARES | I85: 207919 | J85: =+J84+H85-I85 -> 14245738
B86: 46245 | C86: 152 | D86: 789 | E86: 1293 | F86: COLACIONES | G86: COLACIONES | I86: 214000 | J86: =+J85+H86-I86 -> 14031738
B87: 46255 | C87: 157 | D87: 851 | E87: 1413 | F87: MATERIAL ENSEÑANZA | G87: RESMAS | I87: 213619 | J87: =+J86+H87-I87 -> 13818119
B88: 46255 | C88: 156 | D88: 854 | E88: 1436 | F88: COLACIONES | G88: COLACIONES | I88: 214500 | J88: =+J87+H88-I88 -> 13603619
B89: 46255 | C89: 155 | D89: 852 | E89: 1415 | F89: INSUMO COMPUTACIONALES | G89: TINTAS | I89: 128970 | J89: =+J88+H89-I89 -> 13474649
B90: 46261 | C90: 161 | D90: 887 | F90: MATERIAL ENSEÑANZA | G90: ARTICULOS TALLER DEPORTIVO | I90: 214944 | J90: =+J89+H90-I90 -> 13259705
B91: 46261 | C91: 162 | D91: 888 | F91: MATERIAL ENSEÑANZA | G91: BALON FUTBOL | I91: 214914 | J91: =+J90+H91-I91 -> 13044791
J92: =+J91+H92-I92 -> 13044791
J93: =+J92+H93-I93 -> 13044791
B95: SEPTIEMBRE
F96: SUBVENCION | G96: SUBVENCION | H96: =+SUBVENCION!S6+SUBVENCION!T6 -> 13416052 | J96: =+J93+H96-I96 -> 26460843 | L96: INGRESOS | M96: 10% ADM | N96: RR.HH. | O96: BNS Y SERV | P96: SALDO
F97: REMUNERACIONES | G97: REMUNERACIONES | I97: 11336045 | J97: =+J96+H97-I97 -> 15124798 | L97: =+H96 -> 13416052 | M97: =+L97*10% -> 1341605.2 | N97: =+I97 -> 11336045 | O97: =I98+I99+I100+I101+I102+I103+I104+I105+I106+I107 -> 1337828 | P97: =+L97-M97-N97-O97 -> -599426.2
B98: 46268 | C98: 165 | D98: 930 | F98: MATERIAL ENSEÑANZA | G98: ARTICULOS ESCOLARES | I98: 214063 | J98: =+J97+H98-I98 -> 14910735
B99: 46268 | C99: 164 | D99: 929 | F99: MATERIAL OFICINA | G99: MATERIAL OFICINA | I99: 209410 | J99: =+J98+H99-I99 -> 14701325
B100: 46268 | C100: 167 | D100: 931 | E100: PP | F100: COLACIONES | G100: PAJARITOS | I100: 212500 | J100: =+J99+H100-I100 -> 14488825
B101: 46275 | C101: 168 | D101: 970 | F101: MATERIAL ENSEÑANZA | G101: RESMAS | I101: 214500 | J101: =+J100+H101-I101 -> 14274325
B102: 46279 | C102: 169 | D102: 976 | F102: PRESENTACION | G102: PRESENTACION ARTISTICA | I102: 214536 | J102: =+J101+H102-I102 -> 14059789
...

Sheet G-418
B2: UNIDAD DE FINANZAS DAEM
B3: LEY SEP
B4: ESCUELA: G-418 MARIANO EGAÑA
B5: DIRECTOR: DOLY ROJAS FUENTES
B6: SECTOR:
B7: RBD: 3518
B8: FECHA | C8: SOL | D8: OC | E8: DP | F8: CATEGORIA | G8: DETALLE | H8: INGRESOS | I8: GASTOS | J8: SALDO
G9: SALDO 2025 | H9: -177954 | J9: =+H9-I9 -> -177954
B10: ENERO | K10: ENERO | L10: INGRESOS | M10: 10% ADM | N10: RR.HH. | O10: BNS Y SERV | P10: SALDO
F11: SUBVENCION | G11: SUBVENCION | H11: =SUBVENCION!C19+SUBVENCION!D19 -> 655614 | J11: =+J9+H11-I11 -> 477660 | L11: =H11 -> 655614 | M11: =L11*10% -> 65561.4 | P11: =L11-M11 -> 590052.6
B12: FEBRERO | K12: FEBRERO | L12: INGRESOS | M12: 10% ADM | N12: RR.HH. | O12: BNS Y SERV | P12: SALDO
F13: SUBVENCION | G13: SUBVENCION | H13: =SUBVENCION!E19+SUBVENCION!F19 -> 694449 | J13: =+J11+H13-I13 -> 1172109 | L13: =H13 -> 694449 | M13: =L13*10% -> 69444.9 | P13: =L13-M13 -> 625004.1
B14: MARZO
F15: SUBVENCION | G15: SUBVENCION | H15: =SUBVENCION!G19+SUBVENCION!H19 -> 668721 | J15: =+J13+H15-I15 -> 1840830 | K15: MARZO | L15: INGRESOS | M15: 10% ADM | N15: RR.HH. | O15: BNS Y SERV | P15: SALDO
B16: 46087 | C16: 1 | D16: 55 | E16: 340 | F16: VESTUARIO | G16: VESTUARIO DEPORTIVO | I16: 205000 | J16: =+J15+H16-I16 -> 1635830 | L16: =H15 -> 668721 | M16: =H15*10% -> 66872.1 | N16: 0 | O16: =I16+I17+I18 -> 589799 | P16: =L16-M16-O16 -> 12049.9
B17: 46087 | C17: 2 | D17: 60 | E17: 377 | F17: EQUIPO DE OFICNA | G17: IMPRESORA | I17: 180900 | J17: =+J16+H17-I17 -> 1454930
B18: 46087 | C18: 3 | D18: 73 | E18: 383 | F18: MATERIALES ENSEÑANZA | G18: LIBRERÍA | I18: 203899 | J18: =+J17+H18-I18 -> 1251031
J19: =+J18+H19-I19 -> 1251031
B20: ABRIL
F21: SUBVENCION | G21: SUBVENCION | H21: =SUBVENCION!I19+SUBVENCION!J19 -> 869820 | J21: =+J19+H21-I21 -> 2120851 | K21: ABRIL | L21: INGRESOS | M21: 10% ADM | N21: RR.HH. | O21: BNS Y SERV | P21: SALDO
B22: 46114 | C22: 5 | D22: 213 | E22: 410 | F22: MATERIALES ENSEÑANZA | G22: MATERIALES ENSEÑANZA | I22: 209540 | J22: =+J21+H22-I22 -> 1911311 | L22: =H21 -> 869820 | M22: =L22*10% -> 86982 | O22: =I22+I23+I24+I25+I26+I27+I28+I29+I30 -> 1806983 | P22: =L22-M22-O22 -> -1024145
B23: 46125 | C23: 8 | D23: 283 | E23: 636 | F23: MATERIALES ENSEÑANZA | G23: MATERIALES ENSEÑANZA | I23: 207655 | J23: =+J22+H23-I23 -> 1703656
B24: 46125 | C24: 7 | D24: 282 | E24: 702 | F24: OTROS SERVICIOS | G24: DIFUCIIÓN | I24: 178500 | J24: =+J23+H24-I24 -> 1525156
B25: 46127 | C25: 6 | D25: 281 | E25: 642 | F25: MATERIALES ENSEÑANZA | G25: LIBRERÍA | I25: 209000 | J25: =+J24+H25-I25 -> 1316156
B26: 46127 | C26: 11 | D26: 297-298 | E26: 599 | F26: COLACIONES | G26: COLACIONES | I26: 200640 | J26: =+J25+H26-I26 -> 1115516
B27: 46127 | C27: 9 | D27: 296 | E27: 750 | F27: MATERIALES ENSEÑANZA | G27: MATERIALES ENSEÑANZA | I27: 197008 | J27: =+J26+H27-I27 -> 918508
B28: 46136 | C28: 12 | D28: 351 | E28: 727 | F28: VESTUARIO | G28: VESTUARIO DEPORTIVO | I28: 205000 | J28: =+J27+H28-I28 -> 713508
B29: 46136 | C29: 14 | D29: 352 | E29: 583 | F29: MATERIALES ENSEÑANZA | G29: MATERIALES ENSEÑANZA | I29: 209640 | J29: =+J28+H29-I29 -> 503868
B30: 46136 | C30: 13 | D30: 353 | E30: 696 | F30: INSUMO COMPUTRACIONALES | G30: INSUMO COMPUTRACIONALES | I30: 190000 | J30: =+J29+H30-I30 -> 313868
J31: =+J30+H31-I31 -> 313868
B32: MAYO
F33: SUBVENCION | G33: SUBVENCION | H33: 869820 | J33: =+J31+H33-I33 -> 1183688 | K33: MAYO | L33: INGRESOS | M33: 10% ADM | N33: RR.HH. | O33: BNS Y SERV | P33: SALDO
B34: 46149 | C34: 17 | D34: 405 | E34: 746 | F34: MATERIALES ENSEÑANZA | G34: LIBRERÍA | I34: 211750 | J34: =+J33+H34-I34 -> 971938 | L34: =H33 -> 869820 | M34: =L34*10% -> 86982 | O34: =I34+I35+I36 -> 629050 | P34: =H33-M34-O34 -> 153788
B35: 46153 | C35: 18 | D35: 429 | E35: 747 | F35: COLACIONES | G35: COLACIONES | I35: 209050 | J35: =+J34+H35-I35 -> 762888
B36: 46149 | C36: 15 | D36: 439 | E36: 761 | F36: OTROS SERVICIOS | G36: OTROS SERVICIOS | I36: 208250 | J36: =+J35+H36-I36 -> 554638
B37: JUNIO
F38: SUBVENCION | G38: SUBVENCION | H38: =SUBVENCION!M19+SUBVENCION!N19 -> 1293635 | J38: =+J36+H38-I38 -> 1848273 | K38: JUNIO | L38: INGRESOS | M38: 10% ADM | N38: RR.HH. | O38: BNS Y SERV | P38: SALDO
B39: 46177 | C39: 19 | D39: 540 | E39: 881 | F39: VESTUARIO | G39: VESTUARIO DEPORTIVO | I39: 205000 | J39: =+J38+H39-I39 -> 1643273 | L39: =H38 -> 1293635 | M39: =L39*10% -> 129363.5 | O39: =I39+I40+I41+I42 -> 847600 | P39: =L39-M39-O39 -> 316671.5
B40: 46184 | C40: 21 | D40: 567 | F40: MATERIALES ENSEÑANZA | G40: MATERIALES ENSEÑANZA | I40: 214400 | J40: =+J39+H40-I40 -> 1428873
B41: 46185 | C41: 22 | D41: 579 | E41: 1159 | F41: PREMIOS | G41: PREMIOS | I41: 214200 | J41: =+J40+H41-I41 -> 1214673
B42: 46189 | C42: 23 | D42: 598 | E42: 886 | F42: VESTUARIO | G42: VESTUARIO DEPORTIVO | I42: 214000 | J42: =+J41+H42-I42 -> 1000673
J43: =+J42+H43-I43 -> 1000673
B44: JULIO
F45: SUBVENCION | G45: SUBVENCION | H45: =+SUBVENCION!O19+SUBVENCION!P19 -> 980215 | J45: =+J43+H45-I45 -> 1980888 | K45: JULIO | L45: INGRESOS | M45: 10% ADM | N45: RR.HH. | O45: BNS Y SERV | P45: SALDO
B46: 46226 | C46: 28 | D46: 706 | E46: 1214 | F46: COLACIONES | G46: COLACIONES | I46: 185440 | J46: =+J45+H46-I46 -> 1795448 | L46: =H45 -> 980215 | M46: =L46*10% -> 98021.5 | O46: =I46+I47+I49+I48 -> 826088 | P46: =L46-M46-O46 -> 56105.5
B47: 46226 | C47: 27 | D47: 709 | E47: 1211 | F47: MATERIAL ENSEÑANZA | G47: MAT DIDACTICOS | I47: 213400 | J47: =+J46+H47-I47 -> 1582048
B48: 46226 | C48: 26 | D48: 710 | E48: 1188 | F48: VESTUARIO | G48: TRAJES NORTE | I48: 214000 | J48: =+J47+H48-I48 -> 1368048
B49: 46191 | C49: 24 | D49: 722 | E49: 1207 | F49: VESTUARIO | G49: TRAJES RAPA NUI | I49: 213248 | J49: =+J48+H49-I49 -> 1154800
B50: AGOSTO
F51: SUBVENCION | G51: SUBVENCION | H51: =+SUBVENCION!Q19+SUBVENCION!R19 -> 923630 | J51: =+J49+H51-I51 -> 2078430 | K51: AGOSTO | L51: INGRESOS | M51: 10% ADM | N51: RR.HH. | O51: BNS Y SERV | P51: SALDO
B52: 46253 | C52: 30 | D52: 850 | E52: 1385 | F52: MATERIAL ENSEÑANZA | G52: MATERIALES ENSEÑANZA | I52: 213997 | J52: =+J51+H52-I52 -> 1864433 | L52: =H51 -> 923630 | M52: =L52*10% -> 92363 | O52: =I52+I53+I54+I55 -> 571797 | P52: =L52-M52-O52 -> 259470
E53: 1404 | F53: CAJA CHICA | G53: CAJA CHICA | I53: 143000 | J53: =+J52+H53-I53 -> 1721433
B54: 46261 | C54: 31 | D54: 886 | F54: MATERIAL ENSEÑANZA | G54: MATERIALES ENSEÑANZA | I54: 214800 | J54: =+J53+H54-I54 -> 1506633
J55: =+J54+H55-I55 -> 1506633
B56: SEPTIEMBRE
F57: SUBVENCION | G57: SUBVENCION | H57: =+SUBVENCION!S19+SUBVENCION!T19 -> 862876 | J57: =+J55+H57-I57 -> 2369509 | K57: SEPTIEMBRE | L57: INGRESOS | M57: 10% ADM | N57: RR.HH. | O57: BNS Y SERV | P57: SALDO
B58: 46266 | C58: 32 | D58: 914 | F58: COLACIONES | G58: COLACIONES | I58: 214574 | J58: =+J57+H58-I58 -> 2154935 | L58: =H57 -> 862876 | M58: =L58*10% -> 86287.6 | O58: =I58+I59+I60 -> 642738 | P58: =L58-M58-N58-O58 -> 133850.4
B59: 46288 | C59: 33 | D59: 999 | F59: VESTUARIO | G59: VESTUARIO TIPICO | I59: 214000 | J59: =+J58+H59-I59 -> 1940935
B60: 46295 | C60: 34 | D60: 1051 | F60: COLACIONES | G60: COLACIONES | I60: 214164 | J60: =+J59+H60-I60 -> 1726771
J61: =+J60+H61-I61 -> 1726771
J62: =+J61+H62-I62 -> 1726771
B63: OCTUBRE
F64: SUBVENCION | G64: SUBVENCION | H64: =+SUBVENCION!U19+SUBVENCION!V19 -> 0 | J64: =+J62+H64-I64 -> 1726771 | L64: INGRESOS | M64: 10% ADM | N64: RR.HH. | O64: BNS Y SERV | P64: SALDO
J65: =+J64+H65-I65 -> 1726771 | L65: =H64 -> 0 | M65: =L65*10% -> 0 | O65: =I65+I66 -> 0 | P65: =L65-M65-N65-O65 -> 0
J66: =+J65+H66-I66 -> 1726771
J67: =+J66+H67-I67 -> 1726771
G68: FONDO POR RENDIR | J68: =+J67+H68-I68 -> 1726771
J69: =+J68+H69-I69 -> 1726771
J70: =+J69+H70-I70 -> 1726771
B71: NOVIEMBRE
F72: SUBVENCION | G72: SUBVENCION | H72: =+SUBVENCION!W19+SUBVENCION!X19 -> 0 | J72: =+J70+H72-I72 -> 1726771
J73: =+J72+H73-I73 -> 1726771 | L73: INGRESOS | M73: 10% ADM | N73: RR.HH. | O73: BNS Y SERV | P73: SALDO
J74: =+J73+H74-I74 -> 1726771 | L74: =H72 -> 0 | M74: =L74*10% -> 0 | P74: =L74-M74-N74-O74 -> 0
J75: =+J74+H75-I75 -> 1726771
J76: =+J75+H76-I76 -> 1726771
J77: =+J76+H77-I77 -> 1726771
B78: DICIEMBRE
F79: SUBVENCION | G79: SUBVENCION | H79: =+SUBVENCION!Y19+SUBVENCION!Z19 -> 0 | J79: =+J77+H79-I79 -> 1726771 | L79: INGRESOS | M79: 10% ADM | N79: RR.HH. | O79: BNS Y SERV | P79: SALDO
J80: =+J79+H80-I80 -> 1726771 | L80: =H79 -> 0 | M80: =L80*10% -> 0 | P80: =L80-M80-N80-O80 -> 0
J81: =+J80+H81-I81 -> 1726771
J82: =+J81+H82-I82 -> 1726771
J83: =+J82+H83-I83 -> 1726771
J84: =+J83+H84-I84 -> 1726771
J85: =+J84+H85-I85 -> 1726771
J86: =+J85+H86-I86 -> 1726771
F87: AC 10% | G87: AC | H87: =(H11+H13+H15+H21+H33+H38+H45+H51+H57+H64+H72+H79)*-10% -> -781878 | J87: =+J86+H87-I87 -> 944893 | L87: INGRESOS | M87: 10% ADM | N87: RR.HH. | O87: BNS Y SERV | P87: SALDO
B88: x | C88: x | G88: TOTAL | H88: =SUM(H9:H87) -> 6858948 | I88: =SUM(I11:I87) -> 5914055 | J88: =+H88-I88 -> 944893 | L88: =+H11+H13+H15+H21+H33+H38+H45+H51+H57+H64+H72+H79 -> 7818780 | M88: =+L88*10% -> 781878 | N88: 0 | O88: =+I16+I17+I18+I22+I23+I24+I25+I26+I27+I28+I29+I30+I34+I35+I36+I39+I40+I41+I42+I46+I47+I48+I49+I52+I53+I54+I58+I59+I60 -> 5914055 | P88: =+L88-M88-N88-O88 -> 1122847
L91: =L11+L13+L16+L22+L34+L39+L46+L52+L58+L65+L74+L80 -> 7818780 | M91: =M11+M13+M16+M22+M34+M39+M46+M52+M58+M65+M74+M80 -> 781878 | N91: =N11+N13+N16+N22+N34+N39+N46+N52+N58+N65+N74+N80 -> 0 | O91: =O11+O13+O16+O22+O34+O39+O46+O52+O58+O65+O74+O80 -> 5914055 | P91: =P11+P13+P16+P22+P34+P39+P46+P52+P58+P65+P74+P80 -> 1122847
G93: EJECUCION | H93: INGRESOS | I93: GASTOS | J93: %
H94: =+H88 -> 6858948 | I94: =+I88 -> 5914055 | J94: =+I94*100/H94 -> 86.223937

Sheet G-419
B3: LEY SEP
B4: Escuela: G-419 MARIANO LATORRE RBD 3520
B5: Director: PEDRO CACERES
B6: FECHA | C6: SOL | D6: OC | E6: DP | F6: CATEGORIA | G6: DETALLE | H6: INGRESOS | I6: GASTOS | J6: SALDO
G7: SALDO 2025 | H7: 5298959 | J7: =+H7-I7 -> 5298959
B8: ENERO | K8: ENERO | L8: INGRESOS | M8: 10% ADM | N8: RR.HH. | O8: BNS Y SERV | P8: SALDO
F9: SUBVENCION | G9: SUBVENCION | H9: =SUBVENCION!C20+SUBVENCION!D20 -> 1225815 | J9: =+J7+H9-I9 -> 6524774 | L9: =H9 -> 1225815 | M9: =L9*10% -> 122581.5 | N9: =I10 -> 203856 | O9: =I11 -> 0 | P9: =L9-M9-N9-O9 -> 899377.5
F10: REMUNERACIONES | G10: REMUNERACIONES | I10: 203856 | J10: =+J9+H10-I10 -> 6320918
J11: =+J10+H11-I11 -> 6320918
B12: FEBRERO
F13: SUBVENCION | G13: SUBVENCION | H13: =SUBVENCION!E20+SUBVENCION!F20 -> 1236346 | J13: =+J11+H13-I13 -> 7557264 | K13: FEBRERO | L13: INGRESOS | M13: 10% ADM | N13: RR.HH. | O13: BNS Y SERV | P13: SALDO
F14: REMUNERACIONES | G14: REMUNERACIONES | I14: 207948 | J14: =+J13+H14-I14 -> 7349316 | L14: =H13 -> 1236346 | M14: =L14*10% -> 123634.6 | N14: =I14 -> 207948 | O14: 0 | P14: =L14-M14-N14 -> 904763.4
B15: MARZO
F16: SUBVENCION | G16: SUBVENCION | H16: =SUBVENCION!G20+SUBVENCION!H20 -> 1229349 | J16: =+J14+H16-I16 -> 8578665 | K16: MARZO | L16: INGRESOS | M16: 10% ADM | N16: RR.HH. | O16: BNS Y SERV | P16: SALDO
F17: REMUNERACIONES | G17: REMUNERACIONES | I17: 207948 | J17: =+J16+H17-I17 -> 8370717 | L17: =H16 -> 1229349 | M17: =L17*10% -> 122934.9 | N17: =I17 -> 207948 | O17: =I18+I19+I20+I21+I22+I23+I24 -> 1394372 | P17: =L17-M17-N17-O17 -> -495905.9
B18: 46086 | C18: 5 | D18: 70 | E18: 391 | F18: MATERIALES ENSEÑANZA | G18: LIBRERÍA | I18: 204536 | J18: =+J17+H18-I18 -> 8166181
B19: 45725 | C19: 4 | D19: 71 | E19: 382 | F19: MATERIALES ENSEÑANZA | G19: LIBRERÍA | I19: 208430 | J19: =+J18+H19-I19 -> 7957751
B20: 46086 | C20: 2 | D20: 83 | E20: 385 | F20: VESTUARIO | G20: VESTUARIO DEPORTIVO | I20: 208548 | J20: =+J19+H20-I20 -> 7749203
B21: 46108 | C21: 6 | D21: 181 | E21: 600 | F21: COLACIONES | G21: COLACIONES | I21: 208678 | J21: =+J20+H21-I21 -> 7540525
B22: 46110 | C22: 7 | D22: 200 | E22: 747 | F22: COLACIONES | G22: COLACIONES | I22: 172810 | J22: =+J21+H22-I22 -> 7367715
B23: 46110 | C23: 8 | D23: 201 | E23: 431 | F23: MATERIALES ENSEÑANZA | G23: LIBRERÍA | I23: 209300 | J23: =+J22+H23-I23 -> 7158415
B24: 46111 | C24: 12 | D24: 205 | E24: 430 | F24: GASTOS MENORES | G24: GASTOS MENORES | I24: 182070 | J24: =+J23+H24-I24 -> 6976345
J25: =+J24+H25-I25 -> 6976345
J26: =+J25+H26-I26 -> 6976345
B27: ABRIL
F28: SUBVENCION | G28: SUBVENCION | H28: =SUBVENCION!I20+SUBVENCION!J20 -> 1205332 | J28: =+J26+H28-I28 -> 8181677 | K28: ABRIL | L28: INGRESOS | M28: 10% ADM | N28: RR.HH. | O28: BNS Y SERV | P28: SALDO
F29: REMUNERACIONES | G29: REMUNERACIONES | I29: 208309 | J29: =+J28+H29-I29 -> 7973368 | L29: =H28 -> 1205332 | M29: =L29*10% -> 120533.2 | N29: =I29 -> 208309 | O29: =+I30+I31+I32+I33 -> 829042 | P29: =L29-M29-N29-O29 -> 47447.8
B30: 46113 | C30: 13 | D30: 210 | E30: 432 | F30: TRASLADO | G30: TRANSPORTE | I30: 207000 | J30: =+J29+H30-I30 -> 7766368
B31: 46128 | C31: 14 | D31: 293 | E31: 576 | F31: MATERIALES ENSEÑANZA | G31: LIBRERÍA | I31: 207000 | J31: =+J30+H31-I31 -> 7559368
B32: 46132 | C32: 15 | D32: 314 | E32: 600 | F32: COLACIONES | G32: COLACIONES | I32: 208678 | J32: =+J31+H32-I32 -> 7350690
B33: 46133 | C33: 16 | D33: 332 | E33: 599 | F33: COLACIONES | G33: COLACIONES | I33: 206364 | J33: =+J32+H33-I33 -> 7144326
J34: =+J33+H34-I34 -> 7144326
B35: MAYO
F36: SUBVENCION | G36: SUBVENCION | H36: =SUBVENCION!K20+SUBVENCION!L20 -> 1211485 | J36: =+J34+H36-I36 -> 8355811 | K36: MAYO | L36: INGRESOS | M36: 10% ADM | N36: RR.HH. | O36: BNS Y SERV | P36: SALDO
F37: REMUNERACIONES | G37: REMUNERACIONES | I37: 214858 | J37: =+J36+H37-I37 -> 8140953 | L37: =H36 -> 1211485 | M37: =L37*10% -> 121148.5 | N37: =I37 -> 214858 | O37: =I38+I39+I40 -> 211000 | P37: =L37-M37-N37-O37 -> 664478.5
B38: 46167 | C38: 17 | D38: 479 | F38: MATERIALES ENSEÑANZA | G38: LIBRERÍA | I38: 211000 | J38: =+J37+H38-I38 -> 7929953
J39: =+J38+H39-I39 -> 7929953
J40: =+J39+H40-I40 -> 7929953
B41: JUNIO
F42: SUBVENCION | G42: SUBVENCION | H42: =SUBVENCION!M20+SUBVENCION!N20 -> 1037348 | J42: =+J40+H42-I42 -> 8967301 | K42: JUNIO | L42: INGRESOS | M42: 10% ADM | N42: RR.HH. | O42: BNS Y SERV | P42: SALDO
F43: REMUNERACIONES | G43: REMUNERACIONES | I43: 220103 | J43: =+J42+H43-I43 -> 8747198 | L43: =H42 -> 1037348 | M43: =L43*10% -> 103734.8 | N43: =I43 -> 220103 | O43: =I44+I45 -> 320838 | P43: =L43-M43-N43-O43 -> 392672.2
B44: 46183 | C44: 18 | D44: 582 | E44: 922 | F44: COLACIONES | G44: COLACIONES | I44: 112519 | J44: =+J43+H44-I44 -> 8634679
B45: 46190 | C45: 20 | D45: 600 | E45: 1032 | F45: MATERIALES ENSEÑANZA | G45: LIBRERÍA | I45: 208319 | J45: =+J44+H45-I45 -> 8426360
B46: JULIO
F47: SUBVENCION | G47: SUBVENCION | H47: =+SUBVENCION!O20+SUBVENCION!P20 -> 1205149 | J47: =+J45+H47-I47 -> 9631509 | K47: JULIO | L47: INGRESOS | M47: 10% ADM | N47: RR.HH. | O47: BNS Y SERV | P47: SALDO
F48: REMUNERACIONES | G48: REMUNERACIONES | I48: 212000 | J48: =+J47+H48-I48 -> 9419509 | L48: =H47 -> 1205149 | M48: =L48*10% -> 120514.9 | N48: =I48 -> 212000 | O48: =I49+I50 -> 93520 | P48: =L48-M48-N48-O48 -> 779114.1
B49: 46224 | C49: 21 | D49: 682 | E49: 1319 | F49: MATERIAL ENSEÑANZA | G49: MATERIALES MANUALIDADES | I49: 93520 | J49: =+J48+H49-I49 -> 9325989
J50: =+J49+H50-I50 -> 9325989
B51: AGOSTO
F52: SUBVENCION | G52: SUBVENCION | H52: =+SUBVENCION!Q20+SUBVENCION!R20 -> 1203265 | J52: =+J50+H52-I52 -> 10529254 | K52: AGOSTO | L52: INGRESOS | M52: 10% ADM | N52: RR.HH. | O52: BNS Y SERV | P52: SALDO
F53: REMUNERACIONES | G53: REMUNERACIONES | I53: 219278 | J53: =+J52+H53-I53 -> 10309976 | L53: =H52 -> 1203265 | M53: =L53*10% -> 120326.5 | N53: =I53 -> 219278 | O53: =I54+I55+I56 -> 1162518 | P53: =L53-M53-N53-O53 -> -298857.5
B54: 46244 | C54: 23 | D54: 773 | E54: 1363 | F54: MATERIAL ENSEÑANZA | G54: MATERIALES MANUALIDADES | I54: 62558 | J54: =+J53+H54-I54 -> 10247418
B55: 46251 | C55: 24 | D55: ABASTECIMIENTO | F55: MATERIAL ENSEÑANZA | G55: INSUMOS TECNOLOGICOS | I55: 1099960 | J55: =+J54+H55-I55 -> 9147458
J56: =+J55+H56-I56 -> 9147458
B57: SEPTIEMBRE
F58: SUBVENCION | G58: SUBVENCION | H58: =+SUBVENCION!S20+SUBVENCION!T20 -> 1194866 | J58: =+J56+H58-I58 -> 10342324 | K58: SEPTIEMBRE | L58: INGRESOS | M58: 10% ADM | N58: RR.HH. | O58: BNS Y SERV | P58: SALDO
F59: REMUNERACIONES | G59: REMUNERACIONES | I59: 219278 | J59: =+J58+H59-I59 -> 10123046 | L59: =H58 -> 1194866 | M59: =L59*10% -> 119486.6 | N59: =I59 -> 219278 | O59: =I60+I61+I62+I63 -> 269050 | P59: =L59-M59-N59-O59 -> 587051.4
B60: 46274 | C60: 30 | D60: 960 | F60: GASTOS MENORES | G60: VISITA BUIN ZOO | I60: 89600 | J60: =+J59+H60-I60 -> 10033446
B61: 46275 | C61: 32 | D61: 961 | F61: COLACIONES | G61: COLACIONES | I61: 179450 | J61: =+J60+H61-I61 -> 9853996
J62: =+J61+H62-I62 -> 9853996
J63: =+J62+H63-I63 -> 9853996
J64: =+J63+H64-I64 -> 9853996
B65: OCTUBRE
F66: SUBVENCION | G66: SUBVENCION | H66: =+SUBVENCION!U20+SUBVENCION!V20 -> 0 | J66: =+J64+H66-I66 -> 9853996 | L66: INGRESOS | M66: 10% ADM | N66: RR.HH. | O66: BNS Y SERV | P66: SALDO
F67: REMUNERACIONES | G67: REMUNERACIONES | J67: =+J66+H67-I67 -> 9853996 | L67: =H66 -> 0 | M67: =L67*10% -> 0 | N67: =I67 -> 0 | O67: =I68+I69+I70+I71+I72+I73 -> 0 | P67: =L67-M67-N67-O67 -> 0
J68: =+J67+H68-I68 -> 9853996
J69: =+J68+H69-I69 -> 9853996
J70: =+J69+H70-I70 -> 9853996
J71: =+J70+H71-I71 -> 9853996
J72: =+J71+H72-I72 -> 9853996
J73: =+J72+H73-I73 -> 9853996
J74: =+J73+H74-I74 -> 9853996
J75: =+J74+H75-I75 -> 9853996
J76: =+J75+H76-I76 -> 9853996
J77: =+J76+H77-I77 -> 9853996
J78: =+J77+H78-I78 -> 9853996
B79: NOVIEMBRE
F80: SUBVENCION | G80: SUBVENCION | H80: =+SUBVENCION!W20+SUBVENCION!X20 -> 0 | J80: =J78+H80-I80 -> 9853996 | L80: INGRESOS | M80: 10% ADM | N80: RR.HH. | O80: BNS Y SERV | P80: SALDO
F81: REMUNERACIONES | G81: REMUNERACIONES | J81: =+J80+H81-I81 -> 9853996 | L81: =H80 -> 0 | M81: =L81*10% -> 0 | N81: =I81 -> 0 | P81: =L81-M81-N81-O81 -> 0
J82: =+J81+H82-I82 -> 9853996
J83: =+J82+H83-I83 -> 9853996
J84: =+J83+H84-I84 -> 9853996
J85: =+J84+H85-I85 -> 9853996
J86: =+J85+H86-I86 -> 9853996
J87: =+J86+H87-I87 -> 9853996
J88: =+J87+H88-I88 -> 9853996
J89: =+J88+H89-I89 -> 9853996
J90: =+J89+H90-I90 -> 9853996
J91: =+J90+H91-I91 -> 9853996
B92: DICIEMBRE
F93: SUBVENCION | G93: SUBVENCION | H93: =+SUBVENCION!Y20+SUBVENCION!Z20 -> 0 | J93: =+J91+H93-I93 -> 9853996 | L93: INGRESOS | M93: 10% ADM | N93: RR.HH. | O93: BNS Y SERV | P93: SALDO
F94: REMUNERACIONES | G94: REMUNERACIONES | J94: =+J93+H94-I94 -> 9853996 | L94: =H93 -> 0 | M94: =H93*10% -> 0 | N94: =I94 -> 0 | P94: =L94-M94-N94-O94 -> 0
J95: =+J94+H95-I95 -> 9853996
J96: =+J95+H96-I96 -> 9853996
J97: =+J96+H97-I97 -> 9853996
J98: =+J97+H98-I98 -> 9853996
J99: =+J98+H99-I99 -> 9853996
J100: =+J99+H100-I100 -> 9853996
J101: =+J100+H101-I101 -> 9853996
F102: AC 10% | G102: AC | H102: =(H9+H13+H16+H28+H36+H42+H47+H52+H58+H66+H80+H93)*-10% -> -1074895.5 | J102: =+J101+H102-I102 -> 8779100.5 | L102: INGRESOS | M102: 10% ADM | N102: RR.HH. | O102: BNS Y SERV | P102: SALDO
...

Sheet E-424
B2: UNIDAD DE FINANZAS DAEM
B3: LEY SEP
B4: ESCUELA: E-424 GERONIMO LAGOS LISBOA
B5: DIRECTOR: PATRICIO YAÑEZ
B6: RBD: 3483
B7: SECTOR:
B8: FECHA | C8: SOL | D8: OC | E8: DP | F8: CATEGORIA | G8: DETALLE | H8: INGRESOS | I8: GASTOS | J8: SALDO
G9: SALDO SEP 2025 | H9: -2405121 | J9: =+H9-I9 -> -2405121
B10: ENERO
F11: SUBVENCION | G11: SUBVENCION | H11: =SUBVENCION!C7+SUBVENCION!D7 -> 36332097 | J11: =+H11 -> 36332097 | K11: ENERO | L11: INGRESOS | M11: 10% ADM | N11: RR.HH. | O11: BNS Y SERV | P11: SALDO
F12: REMUNERACIONES | G12: REMUNERACIONES | I12: 29886050 | J12: =+J11+H12-I12 -> 6446047 | L12: =H11 -> 36332097 | M12: =L12*10% -> 3633209.7 | N12: =I12 -> 29886050 | O12: =I13+I14 -> 486946 | P12: =L12-M12-N12-O12 -> 2325891.3
E13: 55 | F13: INTERNET | G13: INTERNET | I13: 486946 | J13: =+J12+H13-I13 -> 5959101
J14: =+J13+H14-I14 -> 5959101
B15: FEBRERO | R15: =P12+P17 -> 4035424.7
F16: SUBVENCION | G16: SUBVENCION | H16: =SUBVENCION!E7+SUBVENCION!F7 -> 38440236 | J16: =+J14+H16-I16 -> 44399337 | K16: FEBRERO | L16: INGRESOS | M16: 10% ADM | N16: RR.HH. | O16: BNS Y SERV | P16: SALDO
F17: REMUNERACIONES | G17: REMUNERACIONES | I17: 32400033 | J17: =+J16+H17-I17 -> 11999304 | L17: =H16 -> 38440236 | M17: =L17*10% -> 3844023.6 | N17: =I17 -> 32400033 | O17: =I18+I19+I20 -> 486646 | P17: =L17-M17-N17-O17 -> 1709533.4
E18: 161 | F18: INTERNET | G18: INTERNET | I18: 486646 | J18: =+J17+H18-I18 -> 11512658
J19: =+J18+H19-I19 -> 11512658
J20: =+J19+H20-I20 -> 11512658
B21: MARZO
F22: SUBVENCION | G22: SUBVENCION | H22: =SUBVENCION!G7+SUBVENCION!H7 -> 36993977 | J22: =+J20+H22-I22 -> 48506635 | K22: MARZO | L22: INGRESOS | M22: 10% ADM | N22: RR.HH. | O22: BNS Y SERV | P22: SALDO
F23: REMUNERACIONES | G23: REMUNERACIONES | I23: 25445960 | J23: =+J22+H23-I23 -> 23060675 | L23: =H22 -> 36993977 | M23: =L23*10% -> 3699397.7 | N23: =I23 -> 25445960 | O23: =SUM(I24:I32) -> 9706312 | P23: =L23-M23-N23-O23 -> -1857692.7
B24: 46090 | C24: 17 | D24: 82 | E24: 382 | F24: MATERIALE ENSEÑANZA | G24: LIBRERÍA | I24: 207960 | J24: =+J23+H24-I24 -> 22852715
B25: 46090 | C25: 18 | D25: 2321-69-AG26 | E25: 394 | F25: INSUMO COMPUTACIONEALES | G25: TINTAS - TONER | I25: 1900430 | J25: =+J24+H25-I25 -> 20952285
B26: 46091 | C26: 19 | D26: 103 | E26: 598 | F26: MATERIALES DE ENSEÑANZA | G26: LIBRERÍA | I26: 183297 | J26: =+J25+H26-I26 -> 20768988
B27: 46091 | C27: 20 | D27: 106 | E27: 598 | F27: MATERIALES DE ENSEÑANZA | G27: LIBRERÍA | I27: 26037 | J27: =+J26+H27-I27 -> 20742951
B28: 46091 | C28: 21 | D28: 2321-65-AG26 | E28: 771 | F28: MATERIALES DE ENSEÑANZA | G28: LIBRERÍA | I28: 1926217 | J28: =+J27+H28-I28 -> 18816734
B29: 46091 | C29: 23 | D29: 2321-93-AG26 | E29: 616 | F29: MATERIALES DE ENSEÑANZA | G29: LIBRERÍA | I29: 586016 | J29: =+J28+H29-I29 -> 18230718
B30: 46099 | E30: 293 | F30: INTERNET | G30: INTERNET | I30: 487783 | J30: =+J29+H30-I30 -> 17742935
B31: 46107 | C31: 29 | D31: 2321-154-TD26 | E31: 1100 | F31: PLATAFORMA | G31: PLATAFORMA 7.680.000 / 1 CUOTAS | I31: 4388572 | J31: =+J30+H31-I31 -> 13354363
J32: =+J31+H32-I32 -> 13354363
J33: =+J32+H33-I33 -> 13354363
B34: ABRIL
F35: SUBVENCION | G35: SUBVENCION | H35: =SUBVENCION!I7+SUBVENCION!J7 -> 35182209 | J35: =+J33+H35-I35 -> 48536572 | K35: ABRIL | L35: INGRESOS | M35: 10% ADM | N35: RR.HH. | O35: BNS Y SERV | P35: SALDO
F36: REMUNERACIONES | G36: REMUNERACIONES | I36: 27147268 | J36: =+J35+H36-I36 -> 21389304 | L36: =H35 -> 35182209 | M36: =L36*10% -> 3518220.9 | N36: =I36 -> 27147268 | O36: =SUM(I37:I43) -> 2445587 | P36: =L36-M36-N36-O36 -> 2071133.1
E37: 455 | F37: INTERNET | G37: INTERNET | I37: 488340 | J37: =+J36+H37-I37 -> 20900964
B38: 46113 | C38: 32 | D38: 274 | E38: 598 | F38: MATERIAL DE ENSEÑANZA | G38: LIBRERÍA | I38: 209545 | J38: =+J37+H38-I38 -> 20691419
B39: 46113 | C39: 31 | D39: 273 | E39: 576 | F39: MATERIAL DE ENSEÑANZA | G39: LIBRERÍA | I39: 208050 | J39: =+J38+H39-I39 -> 20483369
B40: 46126 | C40: 34 | D40: 300 | E40: 707 | F40: COLACIONES | G40: COLACIONES | I40: 115020 | J40: =+J39+H40-I40 -> 20368349
B41: 46121 | C41: 33 | D41: 2321-112-AG26 | E41: 622 | F41: COLACIONES | G41: COLACIONES | I41: 599546 | J41: =+J40+H41-I41 -> 19768803
B42: 46129 | C42: 35 | D42: 310 | E42: 647 | F42: COLACIONES | G42: COLACIONES | I42: 204120 | J42: =+J41+H42-I42 -> 19564683
B43: 46142 | C43: 37 | D43: 2321-134-AG26 | E43: 781 | F43: COLACIONES | G43: COLACIONES | I43: 620966 | J43: =+J42+H43-I43 -> 18943717
J44: =+J43+H44-I44 -> 18943717
J45: =+J44+H45-I45 -> 18943717
B47: MAYO
F48: SUBVENCION | G48: SUBVENCION | H48: =SUBVENCION!K7+SUBVENCION!L7 -> 35131530 | J48: =+J45+H48-I48 -> 54075247 | K48: MAYO | L48: INGRESOS | M48: 10% ADM | N48: RR.HH. | O48: BNS Y SERV | P48: SALDO
F49: REMUNERACIONES | G49: REMUNERACIONES | I49: 27001114 | J49: =+J48+H49-I49 -> 27074133 | L49: =H48 -> 35131530 | M49: =L49*10% -> 3513153 | N49: =I49 -> 27001114 | O49: =SUM(I50:I60) -> 5322153 | P49: =L49-M49-N49-O49 -> -704890
E50: 564 | F50: INTERNET | G50: INTERNET | I50: 491916 | J50: =+J49+H50-I50 -> 26582217
B51: 46146 | C51: 38 | D51: 2321-136-AG26 | E51: 773 | F51: INSUMO COMPUTACIONALES | G51: INSUMO COMPUTACIONALES | I51: 2017050 | J51: =+J50+H51-I51 -> 24565167
B52: 46146 | C52: 39 | D52: 378 | E52: 757 | F52: PREMIOS | G52: PREMIOS | I52: 140000 | J52: =+J51+H52-I52 -> 24425167
B53: 46147 | C53: 43 | D53: 2321-176-AG26 | E53: 1036 | F53: EQUIPO DE AMPLIFICADOR | G53: EQUIPO DE AMPLIFICADOR | I53: 712000 | J53: =+J52+H53-I53 -> 23713167
B54: 46147 | C54: 41 | D54: 401 | E54: 772 | F54: OTROS SERVICIOS | G54: SERVICIO DE AMPLIFICADOR | I54: 94395 | J54: =+J53+H54-I54 -> 23618772
B55: 46148 | C55: 45 | D55: 416 | E55: 745 | F55: MATERIALES DE ENSEÑANZA | G55: LIBRERÍA | I55: 208400 | J55: =+J54+H55-I55 -> 23410372
B56: 46153 | C56: 47 | D56: 441 | E56: 758 | F56: MATERIALES DE ENSEÑANZA | G56: IMPLEMENTOS DE DEPORTE | I56: 204504 | J56: =+J55+H56-I56 -> 23205868
B57: 46153 | C57: 46 | D57: 435 | E57: 805 | F57: MATERIALES DE ENSEÑANZA | G57: MATERIALES DE ENSEÑANZA | I57: 211338 | J57: =+J56+H57-I57 -> 22994530
B58: 46155 | C58: 48 | D58: 2321-164-ag26 | E58: 1068 | F58: INSUMO COMPUTACIONALES | G58: INSUMO COMPUTACIONALES | I58: 310000 | J58: =+J57+H58-I58 -> 22684530
B59: 46160 | C59: 53 | D59: 462 | E59: 825 | F59: MATERIALES DE ENSEÑANZA | G59: IMPLEMENTOS DE DEPORTE | I59: 204600 | J59: =+J58+H59-I59 -> 22479930
B60: 46164 | C60: 49-50-51 | D60: 2321-167-AG26 | E60: 960 | F60: MATERIALES DE ENSEÑANZA | G60: LIBRERÍA | I60: 727950 | J60: =+J59+H60-I60 -> 21751980
J61: =+J60+H61-I61 -> 21751980
B62: JUNIO
F63: SUBVENCION | G63: SUBVENCION | H63: =SUBVENCION!M7+SUBVENCION!N7 -> 32756444 | J63: =+J61+H63-I63 -> 54508424 | K63: JUNIO | L63: INGRESOS | M63: 10% ADM | N63: RR.HH. | O63: BNS Y SERV | P63: SALDO
F64: REMUNERACIONES | G64: REMUNERACIONES | I64: 27705203 | J64: =+J63+H64-I64 -> 26803221 | L64: =H63 -> 32756444 | M64: =L64*10% -> 3275644.4 | N64: =I64 -> 27705203 | O64: =I65+I66+I67+I68+I69+I70+I71 -> 2260134 | P64: =L64-M64-N64-O64 -> -484537.4
E65: 791 | F65: INTERNET | G65: INTERNET | I65: 497972 | J65: =+J64+H65-I65 -> 26305249
B66: 46177 | C66: 62 | D66: 2321-193-AG26 | F66: IMPLEMENTOS DEPORTIVOS | G66: IMPLEMENTOS DEPORTIVOS | I66: 271177 | J66: =+J65+H66-I66 -> 26034072
B67: 46176 | C67: 60 | D67: 536-537 | E67: 1030 | F67: PREMIOS | G67: PREMIOS | I67: 211726 | J67: =+J66+H67-I67 -> 25822346
B68: 46175 | C68: 59 | D68: 535 | E68: 1070 | F68: TRANSPORTE | G68: TRASLADO | I68: 200000 | J68: =+J67+H68-I68 -> 25622346
B69: 46178 | C69: 64 | D69: 2321-199-AG26 | E69: 1250 | F69: MATERIALES DE ENSEÑANZA | G69: MATERIALES DIDACTICOS | I69: 473608 | J69: =+J68+H69-I69 -> 25148738
B70: 46183 | C70: 67 | D70: 2321-192-AG26 | E70: 1073 | F70: RESMAS | G70: RESMAS | I70: 605651 | J70: =+J69+H70-I70 -> 24543087
J71: =+J70+H71-I71 -> 24543087
B72: JULIO
F73: SUBVENCION | G73: SUBVENCION | H73: =+SUBVENCION!O7+SUBVENCION!P7 -> 34681189 | J73: =+J71+H73-I73 -> 59224276 | K73: JULIO | L73: INGRESOS | M73: 10% ADM | N73: RR.HH. | O73: BNS Y SERV | P73: SALDO
F74: REMUNERACIONES | G74: REMUNERACIONES | I74: 27084372 | J74: =J73+H74-I74 -> 32139904 | L74: =H73 -> 34681189 | M74: =L74*10% -> 3468118.9 | N74: =I74 -> 27084372 | O74: =I75+I76+I79+I77+I78 -> 1219408 | P74: =L74-M74-N74-O74 -> 2909290.1
E75: 995 | F75: INTERNET | G75: INTERNET | I75: 500368 | J75: =J74+H75-I75 -> 31639536
B76: 46216 | C76: 70 | D76: 645 | E76: 1163 | F76: COLACIONES | G76: 14 COLACIONES ALUMNOS VOLEIBOL | I76: 84000 | J76: =J75+H76-I76 -> 31555536
B77: 46226 | C77: 72 | D77: 707 | F77: MATERIALES DE ENSEÑANZA | G77: ARTES | I77: 213980 | J77: =J76+H77-I77 -> 31341556
B78: 46228 | C78: 74 | D78: 708 | E78: 1284 | F78: INSUMOS COMPUTACIONALES | G78: TONER | I78: 207060 | J78: =J77+H78-I78 -> 31134496
B79: 46234 | C79: 76 | D79: 743 | E79: 1283 | F79: COLACIONES | G79: COLACIONES | I79: 214000 | J79: =J78+H79-I79 -> 30920496
B80: AGOSTO
F81: SUBVENCION | G81: SUBVENCION | H81: =+SUBVENCION!Q7+SUBVENCION!R7 -> 34138573 | J81: =+J79+H81-I81 -> 65059069 | K81: AGOSTO | L81: INGRESOS | M81: 10% ADM | N81: RR.HH. | O81: BNS Y SERV | P81: SALDO
F82: REMUNERACIONES | G82: REMUNERACIONES | I82: 27015183 | J82: =+J81+H82-I82 -> 38043886 | L82: =H81 -> 34138573 | M82: =H81*10% -> 3413857.3 | N82: =I82 -> 27015183 | O82: =I83+I84+I85+I86+I91+I87+I88+I89+I90 -> 1829358 | P82: =L82-M82-N82-O82 -> 1880174.7
E83: 1405 | F83: INTERNET | G83: INTERNET | I83: 500634 | J83: =+J82+H83-I83 -> 37543252
B84: 46238 | C84: 81 | D84: 761 | E84: 1285 | F84: TRANSPORTE | G84: TRASLADO | I84: 200000 | J84: =+J83+H84-I84 -> 37343252
B85: 46247 | C85: 83 | D85: 796 | E85: 1392 | F85: TRANSPORTE | G85: TRASLADO | I85: 200000 | J85: =+J84+H85-I85 -> 37143252
B86: 46247 | C86: 82 | D86: 795 | E86: 1340 | F86: MATERIALES DE ENSEÑANZA | G86: LIBROS BIBLIOTECA | I86: 214914 | J86: =+J85+H86-I86 -> 36928338
B87: 46253 | C87: 85 | D87: 833 | E87: 1391 | F87: COLACIONES | G87: COLACIONES | I87: 73950 | J87: =+J86+H87-I87 -> 36854388
B88: 46253 | C88: 87 | D88: 834 | F88: COLACIONES | G88: COLACIONES | I88: 212930 | J88: =+J87+H88-I88 -> 36641458
B89: 46254 | C89: 88 | D89: 849 | F89: COLACIONES | G89: EMPANADAS | I89: 212930 | J89: =+J88+H89-I89 -> 36428528
B90: 46261 | C90: 91 | D90: 891 | F90: MATERIALES DE ENSEÑANZA | G90: MATERIAL LIBERIA | I90: 214000 | J90: =+J89+H90-I90 -> 36214528
J91: =+J90+H91-I91 -> 36214528
B92: SEPTEIMBRE
F93: SUBVENCION | G93: SUBVENCION | H93: =+SUBVENCION!S7+SUBVENCION!T7 -> 33867444 | J93: =+J91+H93-I93 -> 70081972 | K93: SEPTIEMBRE | L93: INGRESOS | M93: 10% ADM | N93: RR.HH. | O93: BNS Y SERV | P93: SALDO
F94: REMUNERACIONES | G94: REMUNERACIONES | I94: 27131966 | J94: =+J93+H94-I94 -> 42950006 | L94: =H93 -> 33867444 | M94: =L94*10% -> 3386744.4 | N94: =I94 -> 27131966 | O94: =SUM(I95:I111) -> 3002010 | P94: =L94-M94-N94-O94 -> 346723.6
F95: INTERNET | G95: INTERNET | J95: =+J94+H95-I95 -> 42950006
B96: 46268 | C96: 93 | D96: 928 | F96: MOBILIARIO | G96: PARLANTE | I96: 179980 | J96: =+J95+H96-I96 -> 42770026
B97: 46269 | C97: 94 | D97: 940 | F97: COLACIONES | G97: EMPANADAS | I97: 93530 | J97: =+J96+H97-I97 -> 42676496
B98: 46272 | C98: 95 | D98: 2321-277-AG26 | E98: PP | F98: DIARIO MURAL | G98: DIARIO MURAL | I98: 414120 | J98: =+J97+H98-I98 -> 42262376
B99: 46274 | C99: 96 | D99: 959 | F99: MATERIALES DE ENSEÑANZA | G99: BATERIA EVALUA | I99: 214200 | J99: =+J98+H99-I99 -> 42048176
B100: 46286 | C100: 97 | D100: 987 | F100: MATERIALES DE ENSEÑANZA | G100: GENERO | I100: 77350 | J100: =+J99+H100-I100 -> 41970826
B101: 46287 | C101: 98 | D101: 995 | F101: COLACIONES | G101: COLACIONES | I101: 214000 | J101: =+J100+H101-I101 -> 41756826
B102: 46289 | C102: 102 | D102: 1013 | F102: PREMIOS | G102: GALVANOS | I102: 120000 | J102: =+J101+H102-I102 -> 41636826
...

Sheet F-425
B2: UNIDAD DE FINANZAS DAEM
B3: LEY SEP
B4: ESCUELA: F-425 MANUEL RODRIGUEZ
B5: DIRECTOR: PAULA MEZA
B6: RBD: 3494
B7: SECTOR:
B8: FECHA | C8: SOL | D8: OC | F8: CATEGORIA | G8: DETALLE | H8: INGRESOS | I8: GASTOS | J8: SALDO
G9: SALDO 2025 | H9: 5317986 | J9: =+H9-I9 -> 5317986
B10: ENERO
F11: SUBVENCION | G11: SUBVENCION | H11: =SUBVENCION!C12+SUBVENCION!D12 -> 6888074 | J11: =+J9+H11-I11 -> 12206060 | L11: INGRESOS | M11: 10% ADM | N11: RR.HH. | O11: BNS Y SERV | P11: SALDO
F12: REMUNERACIONES | G12: REMUNERACIONES | I12: 4855682 | J12: =+J11+H12-I12 -> 7350378 | L12: =H11 -> 6888074 | M12: =L12*10% -> 688807.4 | N12: =I12 -> 4855682 | O12: =I13+I14 -> 1197880 | P12: =L12-M12-N12-O12 -> 145704.6
B13: 45968 | C13: 64 | D13: 2321-108-TD26 | E13: 1168 | F13: MATERIALES ENSEÑANZA | G13: MATERIALES ENSEÑANZA | I13: 1197880 | J13: =+J12+H13-I13 -> 6152498
J14: =+J13+H14-I14 -> 6152498
B15: FEBRERO
F16: SUBVENCION | G16: SUBVENCION | H16: =SUBVENCION!E12+SUBVENCION!F12 -> 7301558 | J16: =+J14+H16-I16 -> 13454056 | L16: INGRESOS | M16: 10% ADM | N16: RR.HH. | O16: BNS Y SERV | P16: SALDO
F17: REMUNERACIONES | G17: REMUNERACIONES | I17: 5135028 | J17: =+J16+H17-I17 -> 8319028 | L17: =H16 -> 7301558 | M17: =L17*10% -> 730155.8 | N17: =I17 -> 5135028 | O17: 0 | P17: =L17-M17-N17-O17 -> 1436374.2
B18: MARZO
F19: SUBVENCION | G19: SUBVENCION | H19: =SUBVENCION!G12+SUBVENCION!H12 -> 7025835 | J19: =+J17+H19-I19 -> 15344863 | L19: INGRESOS | M19: 10% ADM | N19: RR.HH. | O19: BNS Y SERV | P19: SALDO
F20: REMUNERACIONES | G20: REMUNERACIONES | I20: 6245988 | J20: =+J19+H20-I20 -> 9098875 | L20: =H19 -> 7025835 | M20: =L20*10% -> 702583.5 | N20: =I20 -> 6245988 | O20: =I21+I22+I23+I24 -> 728102 | P20: =L20-M20-N20-O20 -> -650838.5
B21: 46104 | C21: 2 | D21: 160 | E21: 370 | F21: MATERIALES DE ENSEÑANZA | G21: LIBRERÍA | I21: 200320 | J21: =+J20+H21-I21 -> 8898555
B22: 46108 | C22: 5 | D22: 2321-107-AG26 | E22: 880 | F22: INSUMO COMPUTACIONALES | G22: TINTAS | I22: 319741 | J22: =+J21+H22-I22 -> 8578814
B23: 45742 | C23: 4 | D23: 174 | E23: 600 | F23: COLACIONES | G23: COLACIONES | I23: 208041 | J23: =+J22+H23-I23 -> 8370773
J24: =+J23+H24-I24 -> 8370773
B25: ABRIL
F26: SUBVENCION | G26: SUBVENCION | H26: =SUBVENCION!I12+SUBVENCION!J12 -> 6528303 | J26: =+J24+H26-I26 -> 14899076 | L26: INGRESOS | M26: 10% ADM | N26: RR.HH. | O26: BNS Y SERV | P26: SALDO
F27: REMUNERACIONES | G27: REMUNERACIONES | I27: 6252447 | J27: =+J26+H27-I27 -> 8646629 | L27: =H26 -> 6528303 | M27: =L27*10% -> 652830.3 | N27: =I27 -> 6252447 | O27: =I28+I29+I30+I31+I32+I33 -> 1157784 | P27: =L27-M27-N27-O27 -> -1534758.3
B28: 46114 | C28: 6 | D28: 219 | E28: 871 | F28: MANTENCION EQUIPO | G28: MANTENCION EQUIPO | I28: 170000 | J28: =+J27+H28-I28 -> 8476629
B29: 46122 | C29: 7 | D29: 2321-140-AG26 | E29: 1034 | F29: MARERIAL DE ENSEÑAZA | G29: BATERIAS | I29: 571200 | J29: =+J28+H29-I29 -> 7905429
B30: 46142 | C30: 13 | D30: ABASTECIMIENTO | E30: NULA | F30: MARERIAL DE ENSEÑAZA | G30: LIBROS | I30: 0 | J30: =+J29+H30-I30 -> 7905429
B31: 45777 | C31: 11 | D31: 372 | E31: 807 | F31: TRASLADO | G31: TRASLADO | I31: 209000 | J31: =+J30+H31-I31 -> 7696429
B32: 46142 | C32: 12 | D32: 373 | E32: 713 | F32: COLACIONES | G32: COLACIONES | I32: 207584 | J32: =+J31+H32-I32 -> 7488845
J33: =+J32+H33-I33 -> 7488845
B34: MAYO
F35: SUBVENCION | G35: SUBVENCION | H35: =SUBVENCION!K12+SUBVENCION!L12 -> 6478062 | J35: =+J33+H35-I35 -> 13966907 | L35: INGRESOS | M35: 10% ADM | N35: RR.HH. | O35: BNS Y SERV | P35: SALDO
F36: REMUNERACIONES | G36: REMUNERACIONES | I36: 6247581 | J36: =+J35+H36-I36 -> 7719326 | L36: =H35 -> 6478062 | M36: =L36*10% -> 647806.2 | N36: =I36 -> 6247581 | O36: =SUM(I37:I40) -> 830034 | P36: =L36-M36-N36-O36 -> -1247359.2
B37: 46146 | C37: 14 | D37: 382 | E37: 708 | F37: MATERIALES DE ENSEÑANZA | G37: MATERIALES DE ENSEÑANZA | I37: 204920 | J37: =+J36+H37-I37 -> 7514406
B38: 46159 | C38: 17 | D38: 454 | F38: MATERIALES DE ENSEÑANZA | G38: MATERIALES DE ENSEÑANZA | I38: 207090 | J38: =+J37+H38-I38 -> 7307316
B39: 46160 | C39: 18 | D39: 458 | E39: 807 | F39: TRANSPORTE | G39: TRASLADO | I39: 209000 | J39: =+J38+H39-I39 -> 7098316
B40: 46160 | C40: 19 | D40: 460 | E40: 951 | F40: MATERIALES DE ENSEÑANZA | G40: IMPLEMENTO DEPORTIVO | I40: 209024 | J40: =+J39+H40-I40 -> 6889292
B41: JUNIO
F42: SUBVENCION | G42: SUBVENCION | H42: =SUBVENCION!M12+SUBVENCION!N12 -> 5929186 | J42: =J40+H42-I42 -> 12818478 | L42: INGRESOS | M42: 10% ADM | N42: RR.HH. | O42: BNS Y SERV | P42: SALDO
F43: REMUNERACIONES | G43: REMUNERACIONES | I43: 6376758 | J43: =+J42+H43-I43 -> 6441720 | L43: =H42 -> 5929186 | M43: =L43*10% -> 592918.6 | N43: =I43 -> 6376758 | O43: =I44+I45+I46+I47 -> 830688 | P43: =L43-M43-N43-O43 -> -1871178.6
B44: 46181 | C44: 20 | D44: 565 | E44: 1029 | F44: TRASLADO | G44: TRANSPORTE | I44: 209000 | J44: =+J43+H44-I44 -> 6232720
B45: 46183 | C45: 24 | D45: 566 | E45: 1022 | F45: COLACIONES | G45: COLACIONES | I45: 209288 | J45: =+J44+H45-I45 -> 6023432
B46: 46184 | C46: 29 | D46: 575 | E46: 953 | F46: MATERIALES DE ENSEÑANZA | G46: LIBRERÍA | I46: 211500 | J46: =+J45+H46-I46 -> 5811932
B47: 46184 | C47: 30 | D47: 576 | E47: 1023 | F47: MATERIALES DE ENSEÑANZA | G47: JUEGO DIDACTICOS | I47: 200900 | J47: =+J46+H47-I47 -> 5611032
B48: JULIO
F49: SUBVENCION | G49: SUBVENCION | H49: =+SUBVENCION!O12+SUBVENCION!P12 -> 6501775 | J49: =+J47+H49-I49 -> 12112807 | L49: INGRESOS | M49: 10% ADM | N49: RR.HH. | O49: BNS Y SERV | P49: SALDO
F50: REMUNERACIONES | G50: REMUNERACIONES | I50: 6262894 | J50: =+J49+H50-I50 -> 5849913 | L50: =H49 -> 6501775 | M50: =L50*10% -> 650177.5 | N50: =I50 -> 6262894 | O50: =SUM(I51:I53) -> 1070711 | P50: =L50-M50-N50-O50 -> -1482007.5
B51: 46213 | C51: 40 | D51: 2321-213-AG26 | E51: 1166 | F51: MATERIAL ENSEÑANZA | G51: TEST WISC | I51: 654500 | J51: =+J50+H51-I51 -> 5195413
B52: 46217 | C52: 42 | D52: 690 | F52: INSUMO COMPUTACIONALES | G52: CONECTORES ROUTER Y OTROS | I52: 207331 | J52: =+J51+H52-I52 -> 4988082
B53: 46232 | C53: 44 | D53: 764 | E53: 1299 | F53: MATERIAL ENSEÑANZA | G53: LIBRERÍA | I53: 208880 | J53: =+J52+H53-I53 -> 4779202
J54: =+J53+H54-I54 -> 4779202
J55: =+J54+H55-I55 -> 4779202
B56: AGOSTO
F57: SUBVENCION | G57: SUBVENCION | H57: =+SUBVENCION!Q12+SUBVENCION!R12 -> 6414454 | J57: =+J55+H57-I57 -> 11193656 | L57: INGRESOS | M57: 10% ADM | N57: RR.HH. | O57: BNS Y SERV | P57: SALDO
F58: REMUNERACIONES | G58: REMUNERACIONES | I58: 6285891 | J58: =+J57+H58-I58 -> 4907765 | L58: =H57 -> 6414454 | M58: =L58*10% -> 641445.4 | N58: =I58 -> 6285891 | O58: =SUM(I59:I64) -> 1075928 | P58: =L58-M58-N58-O58 -> -1588810.4
B59: 46233 | C59: 45 | D59: 746 | E59: 1282 | F59: MATERIAL ENSEÑANZA | G59: LIBRERÍA | I59: 207270 | J59: =+J58+H59-I59 -> 4700495
B60: 46237 | C60: 49 | D60: 747 | E60: 1245 | F60: COLACIONES | G60: COLACIONES | I60: 214885 | J60: =+J59+H60-I60 -> 4485610
B61: 46240 | C61: 51 | D61: 765 | E61: 1289 | F61: TRANSPORTE | G61: TRANSPORTE | I61: 209000 | J61: =+J60+H61-I61 -> 4276610
B62: 46240 | C62: 53 | D62: 2321-255-AG26 | F62: INSUMO COMPUTACIONALES | G62: TINTAS | I62: 404313 | J62: =+J61+H62-I62 -> 3872297
B63: 46261 | C63: 56 | D63: 892 | F63: MATERIAL ENSEÑANZA | G63: TROVICEL | I63: 40460 | J63: =+J62+H63-I63 -> 3831837
J64: =+J63+H64-I64 -> 3831837
B65: SEPTIEMBRE
F66: SUBVENCION | G66: SUBVENCION | H66: =+SUBVENCION!S12+SUBVENCION!T12 -> 6428618 | J66: =+J64+H66-I66 -> 10260455 | L66: INGRESOS | M66: 10% ADM | N66: RR.HH. | O66: BNS Y SERV | P66: SALDO
F67: REMUNERACIONES | G67: REMUNERACIONES | I67: 6286575 | J67: =+J66+H67-I67 -> 3973880 | L67: =H66 -> 6428618 | M67: =L67*10% -> 642861.8 | N67: =I67 -> 6286575 | O67: =I68+I69+I70+I71 -> 843868 | P67: =L67-M67-N67-O67 -> -1344686.8
B68: 46266 | C68: 57 | D68: 907 | F68: COLACIONES | G68: COLACIONES | I68: 214438 | J68: =+J67+H68-I68 -> 3759442
B69: 46268 | C69: 58 | D69: 925 | F69: TRASLADO | G69: TRASLADO | I69: 209000 | J69: =+J68+H69-I69 -> 3550442
B70: 46269 | C70: 60 | D70: 938 | F70: MATERIAL ENSEÑANZA | G70: MATERIAL LIBRERÍA | I70: 208560 | J70: =+J69+H70-I70 -> 3341882
B71: 46279 | C71: 61 | D71: 977 | F71: MATERIAL ENSEÑANZA | G71: MATERIAL ENSEÑANZA | I71: 211870 | J71: =+J70+H71-I71 -> 3130012
B72: 46293 | C72: 65 | D72: 1031 | F72: COLACIONES | G72: COLACIONES | I72: 214200 | J72: =+J71+H72-I72 -> 2915812
B73: 46294 | C73: 66 | D73: 1042 | F73: LIENZO | G73: LIENZO | I73: 42245 | J73: =+J72+H73-I73 -> 2873567
J74: =+J73+H74-I74 -> 2873567
J75: =+J74+H75-I75 -> 2873567
J76: =+J75+H76-I76 -> 2873567
B77: OCTUBRE
F78: SUBVENCION | G78: SUBVENCION | H78: =+SUBVENCION!U12+SUBVENCION!V12 -> 0 | J78: =+J76+H78-I78 -> 2873567 | L78: INGRESOS | M78: 10% ADM | N78: RR.HH. | O78: BNS Y SERV | P78: SALDO
F79: REMUNERACIONES | G79: REMUNERACIONES | J79: =+J78+H79-I79 -> 2873567 | L79: =H78 -> 0 | M79: =L79*10% -> 0 | N79: =I79 -> 0 | O79: =SUM(I80:I86) -> 0 | P79: =L79-M79-N79-O79 -> 0
J80: =+J79+H80-I80 -> 2873567
J81: =+J80+H81-I81 -> 2873567
J82: =+J81+H82-I82 -> 2873567
J83: =+J82+H83-I83 -> 2873567
J84: =+J83+H84-I84 -> 2873567
J85: =+J84+H85-I85 -> 2873567
J86: =+J85+H86-I86 -> 2873567
J87: =+J86+H87-I87 -> 2873567
B89: NOVIEMBRE
F90: SUBVENCION | G90: SUBVENCION | H90: =+SUBVENCION!W12+SUBVENCION!X12 -> 0 | J90: =+J87+H90-I90 -> 2873567 | L90: INGRESOS | M90: 10% ADM | N90: RR.HH. | O90: BNS Y SERV | P90: SALDO
F91: REMUNERACIONES | G91: REMUNERACIONES | J91: =+J90+H91-I91 -> 2873567 | L91: =H90 -> 0 | M91: =L91*10% -> 0 | N91: =I91 -> 0 | O91: 0 | P91: =L91-M91-N91-O91 -> 0
J92: =+J91+H92-I92 -> 2873567
J93: =+J92+H93-I93 -> 2873567
J94: =+J93+H94-I94 -> 2873567
J95: =+J94+H95-I95 -> 2873567
J96: =+J95+H96-I96 -> 2873567
J97: =+J96+H97-I97 -> 2873567
J98: =+J97+H98-I98 -> 2873567
J99: =+J98+H99-I99 -> 2873567
J100: =+J99+H100-I100 -> 2873567
J101: =+J100+H101-I101 -> 2873567
J102: =+J101+H102-I102 -> 2873567
...

Sheet F-426
B2: UNIDAD DE FINANZAS DAEM
B3: LEY SEP
B4: ESCUELA: F-426 PEDRO LAGOS
B5: DIRECTOR: SUSANA MOYA
B6: RBD: 3495
B7: SECTOR:
B8: FECHA | C8: SOL | D8: OC | E8: DP | F8: CATEGORIA | G8: DETALLE | H8: INGRESOS | I8: GASTOS | J8: SALDO
G9: SALDO 2025 | H9: -830673 | J9: =+H9-I9 -> -830673
B10: ENERO
F11: SUBVENCION | G11: SUBVENCION | H11: =SUBVENCION!C13+SUBVENCION!D13 -> 11036677 | J11: =H11-I11 -> 11036677 | L11: INGRESOS | M11: 10% ADM | N11: RR.HH. | O11: BNS Y SERV | P11: SALDO
F12: REMUNERACIONES | G12: REMUNERACIONES | I12: 9911711 | J12: =+J11+H12-I12 -> 1124966 | L12: =H11 -> 11036677 | M12: =L12*10% -> 1103667.7 | N12: =I12 -> 9911711 | O12: =I13 -> 26523 | P12: =L12-M12-N12-O12 -> -5224.7
E13: 12 | F13: INTERNET | G13: INTERNET | I13: 26523 | J13: =+J12+H13-I13 -> 1098443
J14: =+J13+H14-I14 -> 1098443
B15: FEBRERO
F16: SUBVENCION | G16: SUBVENCION | H16: =SUBVENCION!E13+SUBVENCION!F13 -> 11699154 | J16: =+J14+H16-I16 -> 12797597 | L16: INGRESOS | M16: 10% ADM | N16: RR.HH. | O16: BNS Y SERV | P16: SALDO
F17: REMUNERACIONES | G17: REMUNERACIONES | I17: 10817066 | J17: =+J16+H17-I17 -> 1980531 | L17: =H16 -> 11699154 | M17: =L17*10% -> 1169915.4 | N17: =I17 -> 10817066 | O17: =I18 -> 26522 | P17: =L17-M17-N17-O17 -> -314349.4
E18: 130 | F18: INTERNET | G18: INTERNET | I18: 26522 | J18: =+J17+H18-I18 -> 1954009
J19: =+J18+H19-I19 -> 1954009
B20: MARZO
F21: SUBVENCION | G21: SUBVENCION | H21: =SUBVENCION!G13+SUBVENCION!H13 -> 11257415 | J21: =+J19+H21-I21 -> 13211424 | L21: INGRESOS | M21: 10% ADM | N21: RR.HH. | O21: BNS Y SERV | P21: SALDO
F22: REMUNERACIONES | G22: REMUNERACIONES | I22: 10646072 | J22: =+J21+H22-I22 -> 2565352 | L22: =H21 -> 11257415 | M22: =L22*10% -> 1125741.5 | N22: =I22 -> 10646072 | O22: =SUM(I23:I25) -> 233073 | P22: =L22-M22-N22-O22 -> -747471.5
E23: 222 | F23: INTERNET | G23: INTERNET | I23: 26522 | J23: =+J22+H23-I23 -> 2538830
B24: 46086 | C24: 5 | D24: 148 | E24: 570 | F24: MATERIALES ENSEÑANZA | G24: MATERIALES ENSEÑANZA | I24: 206551 | J24: =+J23+H24-I24 -> 2332279
J25: =+J24+H25-I25 -> 2332279
B26: ABRIL
F27: SUBVENCION | G27: SUBVENCION | H27: =SUBVENCION!I13+SUBVENCION!J13 -> 10925031 | J27: =+J25+H27-I27 -> 13257310 | L27: INGRESOS | M27: 10% ADM | N27: RR.HH. | O27: BNS Y SERV | P27: SALDO
F28: REMUNERACIONES | G28: REMUNERACIONES | I28: 10875941 | J28: =+J27+H28-I28 -> 2381369 | L28: =H27 -> 10925031 | M28: =L28*10% -> 1092503.1 | N28: =I28 -> 10875941 | O28: =SUM(I29:I30) -> 26535 | P28: =L28-M28-N28-O28 -> -1069948.1
E29: 350 | F29: INTERNET | G29: INTERNET | I29: 26535 | J29: =+J28+H29-I29 -> 2354834
J30: =+J29+H30-I30 -> 2354834
B31: MAYO
F32: SUBVENCION | G32: SUBVENCION | H32: =SUBVENCION!K13+SUBVENCION!L13 -> 10953973 | J32: =+J30+H32-I32 -> 13308807 | L32: INGRESOS | M32: 10% ADM | N32: RR.HH. | O32: BNS Y SERV | P32: SALDO
F33: REMUNERACIONES | G33: REMUNERACIONES | I33: 10666031 | J33: =+J32+H33-I33 -> 2642776 | L33: =H32 -> 10953973 | M33: =L33*10% -> 1095397.3 | N33: =I33 -> 10666031 | O33: =I34+I35++#REF!+#REF! -> #REF! | P33: =L33-M33-N33-O33 -> #REF!
E34: 563 | F34: INTERNET | G34: INTERNET | I34: 26522 | J34: =+J33+H34-I34 -> 2616254
J35: =+J34+H35-I35 -> 2616254
B36: JUNIO
F37: SUBVENCION | G37: SUBVENCION | H37: =SUBVENCION!M13+SUBVENCION!N13 -> 10929008 | J37: =+J35+H37-I37 -> 13545262 | L37: INGRESOS | M37: 10% ADM | N37: RR.HH. | O37: BNS Y SERV | P37: SALDO
F38: REMUNERACIONES | G38: REMUNERACIONES | I38: 10192458 | J38: =+J37+H38-I38 -> 3352804 | L38: =H37 -> 10929008 | M38: =L38*10% -> 1092900.8 | N38: =I38 -> 10192458 | O38: =I39+#REF!+#REF!+#REF!+I40 -> #REF! | P38: =L38-M38-N38-O38 -> #REF!
E39: 734 | F39: INTERNET | G39: INTERNET | I39: 26522 | J39: =+J38+H39-I39 -> 3326282
J40: =+J39+H40-I40 -> 3326282
B41: JULIO
F42: SUBVENCION | G42: SUBVENCION | H42: =+SUBVENCION!O13+SUBVENCION!P13 -> 11213106 | J42: =+J40+H42-I42 -> 14539388 | L42: INGRESOS | M42: 10% ADM | N42: RR.HH. | O42: BNS Y SERV | P42: SALDO
F43: REMUNERACIONES | G43: REMUNERACIONES | I43: 10130978 | J43: =+J42+H43-I43 -> 4408410 | L43: =H42 -> 11213106 | M43: =L43*10% -> 1121310.6 | N43: =I43 -> 10130978 | O43: =I44+#REF!+#REF!+I45 -> #REF! | P43: =L43-M43-N43-O43 -> #REF!
E44: 944 | F44: INTERNET | G44: INTERNET | I44: 26522 | J44: =+J43+H44-I44 -> 4381888
J45: =+J44+H45-I45 -> 4381888
B46: AGOSTO
F47: SUBVENCION | G47: SUBVENCION | H47: =+SUBVENCION!Q13+SUBVENCION!R13 -> 11066449 | J47: =+J45+H47-I47 -> 15448337 | L47: INGRESOS | M47: 10% ADM | N47: RR.HH. | O47: BNS Y SERV | P47: SALDO
F48: REMUNERACIONES | G48: REMUNERACIONES | I48: 9632153 | J48: =+J47+H48-I48 -> 5816184 | L48: =H47 -> 11066449 | M48: =L48*10% -> 1106644.9 | N48: =I48 -> 9632153 | O48: =SUM(I49:I52) -> 446152 | P48: =L48-M48-N48-O48 -> -118500.9
E49: 1178 | F49: INTERNET | G49: INTERNET | I49: 26522 | J49: =+J48+H49-I49 -> 5789662
B50: 46262 | C50: 31 | D50: 897 | F50: MATERIALES ENSEÑANZA | G50: MATERIALES ENSEÑANZA | I50: 208810 | J50: =+J49+H50-I50 -> 5580852
B51: 46262 | C51: 32 | D51: 898 | F51: COLACIONES | G51: COLACIONES | I51: 210820 | J51: =+J50+H51-I51 -> 5370032
J52: =+J51+H52-I52 -> 5370032
B53: SEPTIEMBRE
F54: SUBVENCION | G54: SUBVENCION | H54: =+SUBVENCION!S13+SUBVENCION!T13 -> 10992219 | J54: =+J52+H54-I54 -> 16362251 | L54: INGRESOS | M54: 10% ADM | N54: RR.HH. | O54: BNS Y SERV | P54: SALDO
F55: REMUNERACIONES | G55: REMUNERACIONES | I55: 9086880 | J55: =J54+H55-I55 -> 7275371 | L55: =H54 -> 10992219 | M55: =L55*10% -> 1099221.9 | N55: =I55 -> 9086880 | O55: =SUM(I56:I64) -> 1850121 | P55: =L55-M55-N55-O55 -> -1044003.9
B56: 46267 | C56: 33 | D56: 919 | E56: PP | F56: COLACIONES | G56: EMPANADAS | I56: 215064 | J56: =J55+H56-I56 -> 7060307
B57: 46269 | C57: 35 | D57: 934 | F57: COLACIONES | G57: COLACIONES | I57: 214650 | J57: =J56+H57-I57 -> 6845657
B58: 46269 | C58: 34 | D58: 935 | F58: MATERIALES ENSEÑANZA | G58: RESMAS | I58: 214610 | J58: =J57+H58-I58 -> 6631047
B59: 46279 | C59: 38 | D59: 980 | F59: MATERIALES ENSEÑANZA | G59: INSUMOS TALLER DE CIENCIAS | I59: 214100 | J59: =J58+H59-I59 -> 6416947
B60: 46279 | C60: 39 | D60: 982 | F60: MATERIALES ENSEÑANZA | G60: TALLER DE FOLCLOR | I60: 208900 | J60: =J59+H60-I60 -> 6208047
B61: 46281 | C61: 40 | D61: 984 | F61: MATERIALES ENSEÑANZA | G61: TALLER MANUALIDADES | I61: 215150 | J61: =J60+H61-I61 -> 5992897
B62: 46290 | C62: 41 | D62: ABASTECIMIENTO | F62: WISC-V | G62: WISC-V | I62: 567647 | J62: =J61+H62-I62 -> 5425250
J63: =J62+H63-I63 -> 5425250
J64: =J63+H64-I64 -> 5425250
B65: OCTUBRE
F66: SUBVENCION | G66: SUBVENCION | H66: =+SUBVENCION!U13+SUBVENCION!V13 -> 0 | J66: =J64+H66-I66 -> 5425250 | L66: INGRESOS | M66: 10% ADM | N66: RR.HH. | O66: BNS Y SERV | P66: SALDO
F67: REMUNERACIONES | G67: REMUNERACIONES | J67: =+J66+H67-I67 -> 5425250 | L67: =H66 -> 0 | M67: =L67*10% -> 0 | N67: =I67 -> 0 | O67: =I68 -> 0 | P67: =L67-M67-N67-O67 -> 0
J68: =+J67+H68-I68 -> 5425250
J69: =+J68+H69-I69 -> 5425250
J70: =+J69+H70-I70 -> 5425250
J71: =+J70+H71-I71 -> 5425250
J72: =+J71+H72-I72 -> 5425250
J73: =+J72+H73-I73 -> 5425250
B74: NOVIEMBRE
F75: SUBVENCION | G75: SUBVENCION | H75: =+SUBVENCION!W13+SUBVENCION!X13 -> 0 | J75: =+J73+H75-I75 -> 5425250 | L75: INGRESOS | M75: 10% ADM | N75: RR.HH. | O75: BNS Y SERV | P75: SALDO
F76: REMUNERACIONES | G76: REMUNERACIONES | J76: =+J75+H76-I76 -> 5425250 | L76: =H75 -> 0 | M76: =L76*10% -> 0 | N76: =I76 -> 0 | O76: 0 | P76: =L76-M76-N76-O76 -> 0
J77: =+J76+H77-I77 -> 5425250
J78: =+J77+H78-I78 -> 5425250
J79: =+J78+H79-I79 -> 5425250
J80: =+J79+H80-I80 -> 5425250
B81: DICIEMBRE
F82: SUBVENCION | G82: SUBVENCION | H82: =+SUBVENCION!Y13+SUBVENCION!Z13 -> 0 | J82: =J80+H82-I82 -> 5425250 | L82: INGRESOS | M82: 10% ADM | N82: RR.HH. | O82: BNS Y SERV | P82: SALDO
F83: REMUNERACIONES | G83: REMUNERACIONES | J83: =J82+H83-I83 -> 5425250 | L83: =H82 -> 0 | M83: =I83*10% -> 0 | N83: =I83 -> 0 | P83: =L83-M83-N83-O83 -> 0
J84: =J83+H84-I84 -> 5425250
J85: =J84+H85-I85 -> 5425250
J86: =J85+H86-I86 -> 5425250
J87: =J86+H87-I87 -> 5425250
J88: =J87+H88-I88 -> 5425250
J89: =J88+H89-I89 -> 5425250
J90: =J89+H90-I90 -> 5425250
J91: =J90+H91-I91 -> 5425250
F92: AC | G92: AC | H92: =(H11+H16+H21+H27+H32+H37+H42+H47+H54+H66+H75+H82)*-10% -> -10007303 | J92: =J91+H92-I92 -> -4582053.2
B93: x | C93: x | G93: TOTAL | H93: =SUM(H11:H92) -> 90065729 | I93: =SUM(I11:I92) -> 94647782 | J93: =+H93-I93 -> -4582053.2
G97: EJECUCION | H97: INGRESOS | I97: GASTOS | J97: %
H98: =+H93 -> 90065729 | I98: =+I93 -> 94647782 | J98: =+I98*100/H98 -> 105.08745

Sheet F-428
B2: UNIDAD DE FINANZAS DAEM
B3: LEY SEP
B4: ESCUELA: F-428 JOSE MIGUEL CARRERA
B5: DIRECTOR: MARCELO ALFARO
B6: RBD:
B7: SECTOR:
B8: FECHA | C8: SOL | D8: OC | E8: DP | F8: CATEGORIA | G8: DETALLE | H8: INGRESOS | I8: GASTOS | J8: SALDO
G9: SALDO 2025 | H9: ='[1]F-428'!$J$143 -> -7438804.9 | J9: =+H9-I9 -> -7438804.9
F11: SUBVENCION | G11: SUBVENCION | H11: =SUBVENCION!C14+SUBVENCION!D14 -> 10207725 | J11: =+H11-I11 -> 10207725 | L11: INGRESOS | M11: 10% ADM | N11: RR.HH. | O11: BNS Y SERV | P11: SALDO
F12: REMUNERACION | G12: REMUNERACION | I12: 8493905 | J12: =+J11+H12-I12 -> 1713820 | L12: =H11 -> 10207725 | M12: =L12*10% -> 1020772.5 | N12: =I12 -> 8493905 | O12: =I13 -> 0 | P12: =L12-M12-N12-O12 -> 693047.5
J13: =+J12+H13-I13 -> 1713820
J14: =+J13+H14-I14 -> 1713820
B15: FEBRERO
F16: SUBVENCION | G16: SUBVENCION | H16: =SUBVENCION!E14+SUBVENCION!F14 -> 10816645 | J16: =+J14+H16-I16 -> 12530465 | L16: INGRESOS | M16: 10% ADM | N16: RR.HH. | O16: BNS Y SERV | P16: SALDO
F17: REMUNERACION | G17: REMUNERACION | I17: 9283979 | J17: =+J16+H17-I17 -> 3246486 | L17: =H16 -> 10816645 | M17: =L17*10% -> 1081664.5 | N17: =I17 -> 9283979 | O17: =I18 -> 206000 | P17: =L17-M17-N17-O17 -> 245001.5
B18: 46065 | C18: 2 | D18: 8 | E18: 257 | F18: LIBROS PARA ALUMNOS | G18: MATERIALES ENSEÑANZA | I18: 206000 | J18: =+J17+H18-I18 -> 3040486
B19: MARZO
F20: SUBVENCION | G20: SUBVENCION | H20: =SUBVENCION!G14+SUBVENCION!H14 -> 10411879 | J20: =+J18+H20-I20 -> 13452365 | L20: INGRESOS | M20: 10% ADM | N20: RR.HH. | O20: BNS Y SERV | P20: SALDO
F21: REMUNERACION | G21: REMUNERACION | I21: 8599698 | J21: =+J20+H21-I21 -> 4852667 | L21: =H20 -> 10411879 | M21: =H20*10% -> 1041187.9 | N21: =I21 -> 8599698 | O21: =I22+I23+I24+I25+I26+I27+I28+I29+I30+I31+I32+I33 -> 2341684 | P21: =L21-M21-N21-O21 -> -1570690.9
B22: 46084 | C22: 8 | D22: 28 | E22: 214 | F22: MATERIALES OFICINA | G22: LIBRERÍA | I22: 205330 | J22: =+J21+H22-I22 -> 4647337
B23: 46084 | C23: 7 | D23: 27 | E23: 215 | F23: INSUMOS COMPUTACIONALES | G23: TINTAS | I23: 207870 | J23: =+J22+H23-I23 -> 4439467
B24: 46085 | C24: 9 | D24: 36 | E24: 216 | F24: INSUMO COMPUTACIONES | G24: TINTAS | I24: 204680 | J24: =+J23+H24-I24 -> 4234787
B25: 46085 | C25: 10 | D25: 38 | E25: 265 | F25: MATERIALES ENSEÑANZA | G25: LIBRERÍA | I25: 203639 | J25: =+J24+H25-I25 -> 4031148
B26: 46087 | C26: 12 | D26: 61 | E26: 262 | F26: MATERIALES ENSEÑANZA | G26: LIBRERÍA | I26: 206582 | J26: =+J25+H26-I26 -> 3824566
B27: 46090 | C27: 14 | D27: 80 | E27: 384 | F27: INSUMO COMPUTACIONES | G27: INSUMO COMPUTACIONES | I27: 203024 | J27: =+J26+H27-I27 -> 3621542
B28: 46091 | C28: 15 | D28: 81 | E28: 269 | F28: MATERIALES ENSEÑANZA | G28: LIBRERÍA | I28: 206917 | J28: =+J27+H28-I28 -> 3414625
B29: 46092 | C29: 17 | D29: ABASTECIMIENTO | E29: NULA | F29: APP COMUNICACIÓN ES COLAR | G29: PLATAFORMA | I29: 0 | J29: =+J28+H29-I29 -> 3414625
B30: 46092 | C30: 16 | D30: 105 | E30: 382 | F30: MATERIALES ENSEÑANZA | G30: LIBRERÍA | I30: 207700 | J30: =+J29+H30-I30 -> 3206925
B31: 46086 | C31: 11 | D31: 2321-74 AG26 | E31: 397 | F31: MATERIALES ENSEÑANZA | G31: RESMAS | I31: 282625 | J31: =+J30+H31-I31 -> 2924300
B32: 46104 | C32: 18 | D32: 275 | E32: 566 | F32: COLACIONES | G32: COLACIONES | I32: 205400 | J32: =+J31+H32-I32 -> 2718900
B33: 46104 | C33: 20 | D33: 276 | E33: 577 | F33: PREMIOS | G33: PREMIOS | I33: 207917 | J33: =+J32+H33-I33 -> 2510983
B34: ABRIL
F35: SUBVENCION | G35: SUBVENCION | H35: =SUBVENCION!I14+SUBVENCION!J14 -> 11593863 | J35: =+J33+H35-I35 -> 14104846 | L35: INGRESOS | M35: 10% ADM | N35: RR.HH. | O35: BNS Y SERV | P35: SALDO
F36: REMUNERACION | G36: REMUNERACION | I36: 8342843 | J36: =+J35+H36-I36 -> 5762003 | L36: =H35 -> 11593863 | M36: =H35*10% -> 1159386.3 | N36: =I36 -> 8342843 | O36: =I37+I38 -> 417074 | P36: =L36-M36-N36-O36 -> 1674559.7
B37: 46120 | C37: 24 | D37: 277 | E37: 605 | F37: PREMIOS | G37: PREMIOS | I37: 208300 | J37: =+J36+H37-I37 -> 5553703
B38: 46120 | C38: 25 | D38: 278 | E38: 572 | F38: PREMIOS | G38: PREMIOS | I38: 208774 | J38: =+J37+H38-I38 -> 5344929
B39: MAYO
F40: SUBVENCION | G40: SUBVENCION | H40: =SUBVENCION!K14+SUBVENCION!L14 -> 11578829 | J40: =+J38+H40-I40 -> 16923758 | L40: INGRESOS | M40: 10% ADM | N40: RR.HH. | O40: BNS Y SERV | P40: SALDO
F41: REMUNERACION | G41: REMUNERACION | I41: 8399093 | J41: =+J40+H41-I41 -> 8524665 | L41: =H40 -> 11578829 | M41: =L41*10% -> 1157882.9 | N41: =I41 -> 8399093 | O41: =I42+I43 -> 411466 | P41: =L41-M41-N41-O41 -> 1610387.1
B42: 46153 | C42: 28 | D42: 431 | E42: 991 | F42: PREMIOS | G42: PREMIOS | I42: 201450 | J42: =+J41+H42-I42 -> 8323215
B43: 46153 | C43: 29 | D43: 432 | E43: 826 | F43: GASTOS MENORES | G43: ESTAMPADOS | I43: 210016 | J43: =+J42+H43-I43 -> 8113199
J44: =+J43+H44-I44 -> 8113199
B45: JUNIO
F46: SUBVENCION | G46: SUBVENCION | H46: =SUBVENCION!M14+SUBVENCION!N14 -> 12514611 | J46: =+J44+H46-I46 -> 20627810 | L46: INGRESOS | M46: 10% ADM | N46: RR.HH. | O46: BNS Y SERV | P46: SALDO
F47: REMUNERACION | G47: REMUNERACION | I47: 8546566 | J47: =+J46+H47-I47 -> 12081244 | L47: =H46 -> 12514611 | M47: =L47*10% -> 1251461.1 | N47: =I47 -> 8546566 | O47: =I48+I49 -> 407898 | P47: =L47-M47-N47-O47 -> 2308685.9
B48: 46175 | C48: 33 | D48: 521 | E48: 957 | F48: TRASPORTE | G48: TRASLADO | I48: 199998 | J48: =+J47+H48-I48 -> 11881246
B49: 46175 | C49: 34 | D49: 522 | E49: 1075 | F49: MATERIALES ENSEÑANZA | G49: LIBRERÍA | I49: 207900 | J49: =+J48+H49-I49 -> 11673346
J50: =+J49+H50-I50 -> 11673346
B51: JULIO
F52: SUBVENCION | G52: SUBVENCION | H52: =+SUBVENCION!O14+SUBVENCION!P14 -> 11318239 | J52: =+J50+H52-I52 -> 22991585 | L52: INGRESOS | M52: 10% ADM | N52: RR.HH. | O52: BNS Y SERV | P52: SALDO
F53: REMUNERACION | G53: REMUNERACION | I53: 8826673 | J53: =+J52+H53-I53 -> 14164912 | L53: =H52 -> 11318239 | M53: =L53*10% -> 1131823.9 | N53: =I53 -> 8826673 | O53: =+I54+I55+I56+I57+I58+I59 -> 972741 | P53: =L53-M53-N53-O53 -> 387001.1
B54: 46213 | C54: 38 | D54: 642 | F54: PREMIOS | G54: GALVANOS | I54: 51765 | J54: =+J53+H54-I54 -> 14113147
B55: 46218 | C55: 39 | D55: 659 | E55: 1151 | F55: MATERIALES ENSEÑANZA | G55: INSMOS TALLER COCINA | I55: 208486 | J55: =+J54+H55-I55 -> 13904661
B56: 46218 | C56: 40 | D56: 660 | E56: 1158 | F56: MATERIAL OFICINA | G56: RESMAS | I56: 204680 | J56: =+J55+H56-I56 -> 13699981
B57: 46218 | C57: 71 | D57: 662 | E57: 1147 | F57: INSUMOS COMPUTACIONALES | G57: TAMBOR | I57: 214000 | J57: =+J56+H57-I57 -> 13485981
B58: 46224 | C58: 43 | D58: 684 | E58: 1244 | F58: MATERIAL ENSEÑANZA | G58: BLOCK GOMA EVA ETC | I58: 208130 | J58: =+J57+H58-I58 -> 13277851
B59: 46230 | C59: 44 | D59: 724 | E59: 1239 | F59: INSUMOS COMPUTACIONALES | G59: CABLES HDMI | I59: 85680 | J59: =+J58+H59-I59 -> 13192171
J60: =+J59+H60-I60 -> 13192171
B61: AGOSTO
F62: SUBVENCION | G62: SUBVENCION | H62: =+SUBVENCION!Q14+SUBVENCION!R14 -> 11025594 | J62: =+J60+H62-I62 -> 24217765 | L62: INGRESOS | M62: 10% ADM | N62: RR.HH. | O62: BNS Y SERV | P62: SALDO
F63: REMUNERACION | G63: REMUNERACION | I63: 8627187 | J63: =+J62+H63-I63 -> 15590578 | L63: =H62 -> 11025594 | M63: =L63*10% -> 1102559.4 | N63: =I63 -> 8627187 | O63: =I64+I65+I66+I67+I68 -> 1045255 | P63: =L63-M63-N63-O63 -> 250592.6
B64: 46238 | C64: 45 | D64: 763 | F64: TORTA | G64: TORTA | I64: 208488 | J64: =+J63+H64-I64 -> 15382090
B65: 46259 | C65: 49 | D65: 860 | E65: 1416 | F65: TRASPORTE | G65: TRASLADO | I65: 200000 | J65: =+J64+H65-I65 -> 15182090
B66: 46261 | C66: 51 | D66: 883 | F66: MATERIAL ENSEÑANZA | G66: MATERIALES ENSEÑANZA | I66: 212040 | J66: =+J65+H66-I66 -> 14970050
B67: 46261 | C67: 52 | D67: 884 | F67: MATERIAL ENSEÑANZA | G67: INSUMOS TALLER COCINA | I67: 210729 | J67: =+J66+H67-I67 -> 14759321
B68: 46261 | C68: 53 | D68: 885 | F68: MATERIAL ENSEÑANZA | G68: BALONES FUTBOL | I68: 213998 | J68: =+J67+H68-I68 -> 14545323
J69: =+H69+J68-I69 -> 14545323
B70: SEPTIEMBRE
F71: SUBVENCION | G71: SUBVENCION | H71: =+SUBVENCION!S14+SUBVENCION!T14 -> 11005594 | J71: =+J69+H71-I71 -> 25550917 | L71: INGRESOS | M71: 10% ADM | N71: RR.HH. | O71: BNS Y SERV | P71: SALDO
F72: REMUNERACION | G72: REMUNERACION | I72: 8652751 | J72: =+J71+H72-I72 -> 16898166 | L72: =H71 -> 11005594 | M72: =L72*10% -> 1100559.4 | N72: =I72 -> 8652751 | O72: =SUM(I73:I76) -> 421939 | P72: =L72-M72-N72-O72 -> 830344.6
B73: 46279 | C73: 54 | D73: 979 | F73: COLACIONES | G73: EMPANADAS | I73: 210000 | J73: =+J72+H73-I73 -> 16688166
B74: 46287 | C74: 56 | D74: 994 | F74: MATERIAL ENSEÑANZA | G74: MATERIALES ENSEÑANZA | I74: 211939 | J74: =+J73+H74-I74 -> 16476227
J75: =+J74+H75-I75 -> 16476227
J76: =+J75+H76-I76 -> 16476227
B77: OCTUBRE
F78: SUBVENCION | G78: SUBVENCION | H78: =+SUBVENCION!U14+SUBVENCION!V14 -> 0 | J78: =J76+H78-I78 -> 16476227 | L78: INGRESOS | M78: 10% ADM | N78: RR.HH. | O78: BNS Y SERV | P78: SALDO
F79: REMUNERACION | G79: REMUNERACION | J79: =+J78+H79-I79 -> 16476227 | L79: =H78 -> 0 | M79: =L79*10% -> 0 | N79: =I79 -> 0 | O79: =SUM(I80:I84) -> 216134 | P79: =L79-M79-N79-O79 -> -216134
B80: 46296 | C80: 58 | D80: 1054 | F80: PREMIOS | G80: PREMIOS | I80: 216134 | J80: =+J79+H80-I80 -> 16260093
J81: =+J80+H81-I81 -> 16260093
J82: =+J81+H82-I82 -> 16260093
J83: =+J82+H83-I83 -> 16260093
J84: =+J83+H84-I84 -> 16260093
B85: NOVIEMBRE
F86: SUBVENCION | G86: SUBVENCION | H86: =+SUBVENCION!W14+SUBVENCION!X14 -> 0 | J86: =+J84+H86-I86 -> 16260093 | L86: INGRESOS | M86: 10% ADM | N86: RR.HH. | O86: BNS Y SERV | P86: SALDO
F87: REMUNERACION | G87: REMUNERACION | J87: =+J86+H87-I87 -> 16260093
J88: =+J87+H88-I88 -> 16260093
J89: =+J88+H89-I89 -> 16260093
J90: =+J89+H90-I90 -> 16260093
J91: =+J90+H91-I91 -> 16260093
B92: DICIEMBRE
F93: SUBVENCION | G93: SUBVENCION | H93: =+SUBVENCION!Y14+SUBVENCION!Z14 -> 0 | J93: =+J91+H93-I93 -> 16260093 | L93: INGRESOS | M93: 10% ADM | N93: RR.HH. | O93: BNS Y SERV | P93: SALDO
F94: REMUNERACION | G94: REMUNERACION | J94: =+J93+H94-I94 -> 16260093
J95: =+J94+H95-I95 -> 16260093
J96: =+J95+H96-I96 -> 16260093
J97: =+J96+H97-I97 -> 16260093
J98: =+J97+H98-I98 -> 16260093
F99: AC | G99: AC | H99: =(H11+H16+H20+H35+H40+H46+H52+H62+H71+H78+H86+H93)*-10% -> -10047298 | J99: =+J98+H99-I99 -> 6212795.1
B100: x | C100: x | G100: TOTAL | H100: =SUM(H11:H99) -> 90425681 | I100: =SUM(I11:I99) -> 84212886 | J100: =+H100-I100 -> 6212795.1
G105: EJECUCION | H105: INGRESOS | I105: GASTOS | J105: %
H106: =+H100 -> 90425681 | I106: =+I100 -> 84212886 | J106: =+I106*100/H106 -> 93.129391

Sheet G-429
B2: UNIDAD DE FINANZAS DAEM
B3: LEY SEP
B4: ESCUELA: G-429 CARLOS CONDELL RBD 3523
B5: DIRECTOR: DULCINEA GONZALEZ BECERRA
B6: RBD:
B7: SECTOR:
B8: FECHA | C8: SOL | D8: OC | E8: DP | F8: CATEGORIA | G8: DETALLE | H8: INGRESOS | I8: GASTOS | J8: SALDO
G9: SALDO 2025 | H9: -1069156 | J9: =+H9-I9 -> -1069156
B10: ENERO
F11: SUBVENCION | G11: SUBVENCION | H11: =SUBVENCION!C21 -> 516671 | J11: =+H11-I11 -> 516671 | L11: INGRESOS | M11: 10% ADM | N11: RR.HH. | O11: BNS Y SERV | P11: SALDO
G12: REMUNERACIONES | I12: 325193 | J12: =J11+H12-I12 -> 191478
B13: FEBRERO | L13: =H11 -> 516671 | M13: =L13*10% -> 51667.1 | N13: 0 | O13: 0 | P13: =L13-M13-O13 -> 465003.9
F14: SUBVENCION | G14: SUBVENCION | H14: =SUBVENCION!E21 -> 547165 | J14: =+J12+H14-I14 -> 738643 | L14: INGRESOS | M14: 10% ADM | N14: RR.HH. | O14: BNS Y SERV | P14: SALDO
G15: REMUNERACIONES | I15: 363465 | J15: =+J14+H15-I15 -> 375178
B16: MARZO | L16: =H14 -> 547165 | M16: =L16*10% -> 54716.5 | N16: 0 | O16: 0 | P16: =L16-M16-N16-O16 -> 492448.5
F17: SUBVENCION | G17: SUBVENCION | H17: =SUBVENCION!G21 -> 527003 | J17: =+J15+H17-I17 -> 902181 | L17: INGRESOS | M17: 10% ADM | N17: RR.HH. | O17: BNS Y SERV | P17: SALDO
G18: REMUNERACIONES | J18: =+J17+H18-I18 -> 902181 | L18: =H17 -> 527003 | M18: =L18*10% -> 52700.3 | N18: =I18 -> 0 | O18: 0 | P18: =L18-M18-N18-O18 -> 474302.7
J19: =+J18+H19-I19 -> 902181
J20: =+J19+H20-I20 -> 902181
B21: ABRIL
F22: SUBVENCION | G22: SUBVENCION | H22: =SUBVENCION!I21 -> 501486 | J22: =+J20+H22-I22 -> 1403667 | L22: INGRESOS | M22: 10% ADM | N22: RR.HH. | O22: BNS Y SERV | P22: SALDO
F23: REMUNERACIONES | G23: REMUNERACIONES | J23: =+J22+H23-I23 -> 1403667 | L23: =H22 -> 501486 | M23: =L23*10% -> 50148.6 | N23: 324433 | O23: 0 | P23: =L23-M23-N23-O23 -> 126904.4
B24: MAYO
F25: SUBVENCION | G25: SUBVENCION | H25: =SUBVENCION!K21 -> 501486 | J25: =+J23+H25-I25 -> 1905153 | L25: INGRESOS | M25: 10% ADM | N25: RR.HH. | O25: BNS Y SERV | P25: SALDO
J26: =+J25+H26-I26 -> 1905153
B27: JUNIO
F28: SUBVENCION | G28: SUBVENCION | H28: =SUBVENCION!M21 -> 482994 | J28: =+J26+H28-I28 -> 2388147 | L28: INGRESOS | M28: 10% ADM | N28: RR.HH. | O28: BNS Y SERV | P28: SALDO
F29: REMUNERACIONES | G29: REMUNERACIONES | J29: =+J28+H29-I29 -> 2388147 | L29: =H28 -> 482994 | M29: =L29*10% -> 48299.4 | N29: =I29 -> 0 | O29: =I30+I31 -> 0 | P29: =L29-M29-O29 -> 434694.6
J30: =+J29+H30-I30 -> 2388147
J31: =+J30+H31-I31 -> 2388147
B32: JULIO
F33: SUBVENCION | G33: SUBVENCION | H33: =+SUBVENCION!O21+SUBVENCION!P21 -> 508511 | J33: =+J31+H33-I33 -> 2896658 | L33: INGRESOS | M33: 10% ADM | N33: RR.HH. | O33: BNS Y SERV | P33: SALDO
F34: REMUNERACIONES | G34: REMUNERACIONES | J34: =+J33+H34-I34 -> 2896658 | L34: =H33 -> 508511 | M34: =L34*10% -> 50851.1 | N34: =I34 -> 0 | O34: =I35+I36+I37+I38 -> 801220 | P34: =L34-M34-N34-O34 -> -343560.1
B35: 46224 | C35: 2 | D35: 728 | E35: 1347 | F35: MOBILIARIO | G35: ESTUFA | I35: 189900 | J35: =+J34+H35-I35 -> 2706758
B36: 46225 | C36: 3 | D36: 729 | E36: 1237 | F36: MATERIAL DE OFICINA | G36: RESMAS | I36: 214600 | J36: =+J35+H36-I36 -> 2492158
B37: 46225 | C37: 4 | D37: 730 | E37: 1248 | F37: MATERIAL ENSEÑANZA | G37: MICAS TERMOLAMINAS | I37: 198900 | J37: =+J36+H37-I37 -> 2293258
B38: 46225 | C38: 5 | D38: 731 | E38: 1247 | F38: INSUMOS COMPUTACIONALES | G38: TINTAS | I38: 197820 | J38: =+J37+H38-I38 -> 2095438
J39: =+J38+H39-I39 -> 2095438
B40: AGOSTO
F41: SUBVENCION | G41: SUBVENCION | H41: =+SUBVENCION!Q21+SUBVENCION!R21 -> 508511 | J41: =+J39+H41-I41 -> 2603949 | L41: INGRESOS | M41: 10% ADM | N41: RR.HH. | O41: BNS Y SERV | P41: SALDO
F42: REMUNERACIONES | G42: REMUNERACIONES | J42: =+J41+H42-I42 -> 2603949 | L42: =H41 -> 508511 | M42: =L42*10% -> 50851.1 | N42: =I42 -> 0 | O42: =I43+I42 -> 0 | P42: =L42-M42-N42-O42 -> 457659.9
J43: =+J42-H43+I43 -> 2603949
B44: SEPTIEMBRE
F45: SUBVENCION | G45: SUBVENCION | H45: =+SUBVENCION!S21+SUBVENCION!T21 -> 508511 | J45: =+J43+H45-I45 -> 3112460 | L45: INGRESOS | M45: 10% ADM | N45: RR.HH. | O45: BNS Y SERV | P45: SALDO
F46: REMUNERACIONES | G46: REMUNERACIONES | J46: =J45+H46-I46 -> 3112460 | L46: =H45 -> 508511 | M46: =L46*10% -> 50851.1 | N46: =I46 -> 0 | O46: =SUM(I47:I49) -> 317870 | P46: =L46-M46-N46-O46 -> 139789.9
B47: 46273 | C47: 7 | D47: 955 | F47: MATERIAL ENSEÑANZA | G47: MATERIAL ENSEÑANZA | I47: 214940 | J47: =J46+H47-I47 -> 2897520
B48: 46273 | C48: 8 | D48: 966 | F48: INSUMOS ACTIVIDADES | G48: MATERIAL DECORATIVO | I48: 102930 | J48: =J47+H48-I48 -> 2794590
J49: =J48+H49-I49 -> 2794590
J50: =J49+H50-I50 -> 2794590
B51: OCTUBRE
F52: SUBVENCION | G52: SUBVENCION | H52: =+SUBVENCION!U21+SUBVENCION!V21 -> 0 | J52: =+J50+H52-I52 -> 2794590 | L52: INGRESOS | M52: 10% ADM | N52: RR.HH. | O52: BNS Y SERV | P52: SALDO
F53: REMUNERACIONES | G53: REMUNERACIONES | J53: =+J52+H53-I53 -> 2794590 | L53: =H52 -> 0 | M53: =L53*10% -> 0 | N53: =I53 -> 0 | O53: =I54+I55 -> 0 | P53: =L53-M53-N53-O53 -> 0
J54: =+J53+H54-I54 -> 2794590
J55: =+J54+H55-I55 -> 2794590
J56: =+J55+H56-I56 -> 2794590
J57: =+J56+H57-I57 -> 2794590
B58: NOVIEMBRE
F59: SUBVENCION | G59: SUBVENCION | H59: =+SUBVENCION!W21+SUBVENCION!X21 -> 0 | J59: =+J57+H59-I59 -> 2794590 | L59: INGRESOS | M59: 10% ADM | N59: RR.HH. | O59: BNS Y SERV | P59: SALDO
F60: REMUNERACIONES | G60: REMUNERACIONES | J60: =+J59+H60-I60 -> 2794590 | L60: =H59 -> 0 | M60: =L60*10% -> 0 | N60: =I60 -> 0 | P60: =L60-M60-N60-O60 -> 0
J61: =+J60+H61-I61 -> 2794590
J62: =+J61+H62-I62 -> 2794590
J63: =+J62+H63-I63 -> 2794590
J64: =+J63+H64-I64 -> 2794590
J65: =+J64+H65-I65 -> 2794590
J66: =+J65+H66-I66 -> 2794590
J67: =+J66+H67-I67 -> 2794590
J68: =+J67+H68-I68 -> 2794590
J69: =+J68+H69-I69 -> 2794590
B70: DICIEMBRE
F71: SUBVENCION | G71: SUBVENCION | H71: =+SUBVENCION!Y21+SUBVENCION!Z21 -> 0 | J71: =+J69+H71-I71 -> 2794590 | L71: INGRESOS | M71: 10% ADM | N71: RR.HH. | O71: BNS Y SERV | P71: SALDO
F72: REMUNERACIONES | G72: REMUNERACIONES | J72: =+J71+H72-I72 -> 2794590 | L72: =H71 -> 0 | M72: =L72*10% -> 0 | N72: =I72 -> 0 | P72: =L72-M72-N72-O72 -> 0
J73: =+J72+H73-I73 -> 2794590
J74: =+J73+H74-I74 -> 2794590
J75: =+J74+H75-I75 -> 2794590
F76: AC | G76: AC | H76: =(H11+H14+H17+H22+H25+H28+H33+H45+H52+H59+H41+H71)*-10% -> -460233.8 | J76: =+J75+H76-I76 -> 2334356.2
B77: x | C77: x | G77: TOTAL | H77: =SUM(H11:H76) -> 4142104.2 | I77: =SUM(I11:I76) -> 1807748 | J77: =+H77-I77 -> 2334356.2
G82: EJECUCION | H82: INGRESOS | I82: GASTOS | J82: %
H83: =+H77 -> 4142104.2 | I83: =+I77 -> 1807748 | J83: =+I83*100/H83 -> 43.643228

Sheet G-433
B2: UNIDAD DE FINANZAS DAEM
B3: LEY SEP
B4: ESCUELA: G-433 AURELIO MEZA RIVERA
B5: DIRECTOR: LUISA GONZALEZ BECERRA
B6: RBD: 3526
B7: SECTOR:
B8: FECHA | C8: SOL | D8: OC | E8: DP | F8: CATEGORIA | G8: DETALLE | H8: INGRESOS | I8: GASTOS | J8: SALDO
G9: SALDO 2025 | H9: 1629481 | J9: =+H9-I9 -> 1629481
B10: ENERO
F11: SUBVENCION | G11: SUBVENCION | H11: =SUBVENCION!C22 -> 1144429 | J11: =+J9+H11-I11 -> 2773910 | L11: INGRESOS | M11: 10% ADM | N11: RR.HH. | O11: BNS Y SERV | P11: SALDO
G12: REMUNERACIONES | I12: 166769 | J12: =+J11+H12-I12 -> 2607141 | L12: =H11 -> 1144429 | M12: =L12*10% -> 114442.9 | N12: =I12 -> 166769 | O12: 0 | P12: =L12-M12-N12 -> 863217.1
F14: SUBVENCION | G14: SUBVENCION | H14: =SUBVENCION!E22+SUBVENCION!F22 -> 1247139 | J14: =+J12+H14-I14 -> 3854280 | L14: INGRESOS | M14: 10% ADM | N14: RR.HH. | O14: BNS Y SERV | P14: SALDO
G15: REMUNERACIONES | I15: 170117 | J15: =+J14+H15-I15 -> 3684163 | L15: =H14 -> 1247139 | M15: =L15*10% -> 124713.9 | N15: =I15 -> 170117 | O15: 0 | P15: =L15-M15-N15-O15 -> 952308.1
B17: MARZO
F18: SUBVENCION | G18: SUBVENCION | H18: =SUBVENCION!G22+SUBVENCION!H22 -> 1201882 | J18: =+J15+H18-I18 -> 4886045 | L18: INGRESOS | M18: 10% ADM | N18: RR.HH. | O18: BNS Y SERV | P18: SALDO
G19: REMUNERACIONES | L19: =H18 -> 1201882 | M19: =I19*10% -> 0 | N19: =I19 -> 0 | P19: =L19-M19-N19-O19 -> 1201882
B20: ABRIL
F21: SUBVENCION | G21: SUBVENCION | H21: =SUBVENCION!I22+SUBVENCION!J22 -> 1060980 | J21: =+J18+H21-I21 -> 5947025 | L21: INGRESOS | M21: 10% ADM | N21: RR.HH. | O21: BNS Y SERV | P21: SALDO
F22: REMUNERACIONES | G22: REMUNERACIONES | J22: =+J21+H22-I22 -> 5947025 | L22: =H21 -> 1060980 | M22: =L22*10% -> 106098 | N22: 0 | O22: 0 | P22: =L22-M22-N22-O22 -> 954882
J23: =+J22+H23-I23 -> 5947025
B24: MAYO
F25: SUBVENCION | G25: SUBVENCION | H25: =SUBVENCION!K22+SUBVENCION!L22 -> 1060980 | J25: =+J23+H25-I25 -> 7008005 | L25: INGRESOS | M25: 10% ADM | N25: RR.HH. | O25: BNS Y SERV | P25: SALDO
F26: REMUNERACIONES | G26: REMUNERACIONES | J26: =+J25+H26-I26 -> 7008005 | L26: =H25 -> 1060980 | M26: =L26*10% -> 106098 | N26: 0 | O26: =I27+I28+I29+I30+I31+I32 -> 1238153 | P26: =L26-M26-N26-O26 -> -283271
B27: 46154 | C27: 3 | D27: 443 | E27: 746 | F27: MATERIALES ENSEÑANZA | G27: MATERIALES ENSEÑANZA | I27: 203659 | J27: =+J26+H27-I27 -> 6804346
B28: 46154 | C28: 4 | D28: 444 | E28: 753 | F28: INSUMO COMPUTACIONES | G28: INSUMO COMPUTACIONES | I28: 207840 | J28: =+J27+H28-I28 -> 6596506
B29: 46154 | C29: 5 | D29: 445 | E29: 747 | F29: COLACIONES | G29: COLACIONES | I29: 202430 | J29: =+J28+H29-I29 -> 6394076
B30: 46154 | C30: 6 | D30: 446 | E30: 752 | F30: MATERIALES ENSEÑANZA | G30: MATERIALES ENSEÑANZA | I30: 208993 | J30: =+J29+H30-I30 -> 6185083
B31: 46169 | C31: 8 | D31: 493 | E31: 844 | F31: MATERIALES ENSEÑANZA | G31: LIBRERÍA | I31: 209200 | J31: =+J30+H31-I31 -> 5975883
B32: 46169 | C32: 7 | D32: 492 | E32: 832 | F32: MATERIALES ENSEÑANZA | G32: LIBRERÍA | I32: 206031 | J32: =+J31+H32-I32 -> 5769852
J33: =+J32+H33-I33 -> 5769852
J34: =+J33+H34-I34 -> 5769852
B35: JUNIO
F36: SUBVENCION | G36: SUBVENCION | H36: =SUBVENCION!M22+SUBVENCION!N22 -> 934937 | J36: =+J34+H36-I36 -> 6704789 | L36: INGRESOS | M36: 10% ADM | N36: RR.HH. | O36: BNS Y SERV | P36: SALDO
F37: REMUNERACIONES | G37: REMUNERACIONES | J37: =+J36+H37-I37 -> 6704789 | L37: =H36 -> 934937 | M37: =L37*10% -> 93493.7 | N37: =I37 -> 0 | O37: =I38 -> 174720 | P37: =L37-M37-N37-O37 -> 666723.3
B38: 46178 | C38: 9 | D38: 547 | E38: 970 | F38: PREMIOS | G38: PREMIOS | I38: 174720 | J38: =+J37+H38-I38 -> 6530069
J39: =+J38+H39-I39 -> 6530069
J40: =+J39+H40-I40 -> 6530069
B41: JULIO
F42: SUBVENCION | G42: SUBVENCION | H42: =+SUBVENCION!O22+SUBVENCION!P22 -> 1075839 | J42: =+J40+H42-I42 -> 7605908 | L42: INGRESOS | M42: 10% ADM | N42: RR.HH. | O42: BNS Y SERV | P42: SALDO
F43: REMUNERACIONES | G43: REMUNERACIONES | J43: =+J42+H43-I43 -> 7605908 | L43: =H42 -> 1075839 | M43: =L43*10% -> 107583.9 | O43: =I44 -> 189900 | P43: =L43-M43-O43 -> 778355.1
B44: 46226 | C44: 11 | D44: 700 | E44: 1243 | F44: MOBILIARIO | G44: ESTUFA | I44: 189900 | J44: =+J43+H44-I44 -> 7416008
J45: =+J44+H45-I45 -> 7416008
B46: AGOSTO
F47: SUBVENCION | G47: SUBVENCION | H47: =+SUBVENCION!Q22+SUBVENCION!R22 -> 1075839 | J47: =+J45+H47-I47 -> 8491847 | L47: INGRESOS | M47: 10% ADM | N47: RR.HH. | O47: BNS Y SERV | P47: SALDO
F48: REMUNERACIONES | G48: REMUNERACIONES | J48: =+J47+H48-I48 -> 8491847 | L48: =H47 -> 1075839 | M48: =L48*10% -> 107583.9 | O48: =I49+I50+I51+I52+I53 -> 1036929 | P48: =L48-M48-O48 -> -68673.9
B49: 46252 | C49: 13 | D49: 821 | E49: 1363 | F49: INSUMOS OFICINA | G49: RESMAS | I49: 209649 | J49: =+J48+H49-I49 -> 8282198
B50: 46251 | C50: 12 | D50: 867 | E50: 1438 | F50: INSUMOS OFICINA | G50: INSUMOS OFICINA | I50: 213430 | J50: =+J49+H50-I50 -> 8068768
B51: 46254 | C51: 15 | D51: 840 | E51: 1394 | F51: INSUMOS COMPUTACIONALES | G51: TONER | I51: 209800 | J51: =+J50+H51-I51 -> 7858968
B52: 46253 | C52: 14 | D52: 848 | E52: 1439 | F52: MATERIAL ENSEÑANZA | G52: ADORNOS Y VETIMENTAS | I52: 217270 | J52: =+J51+H52-I52 -> 7641698
B53: 46262 | C53: 16 | D53: 903 | F53: VESTUARIO | G53: VESTUARIO | I53: 186780 | J53: =+J52+H53-I53 -> 7454918
J54: =+J53+H54-I54 -> 7454918
B55: SEPTIEMBRE
F56: SUBVENCION | G56: SUBVENCION | H56: =+SUBVENCION!S22+SUBVENCION!T22 -> 1075839 | J56: =+J54+H56-I56 -> 8530757 | L56: INGRESOS | M56: 10% ADM | N56: RR.HH. | O56: BNS Y SERV | P56: SALDO
F57: REMUNERACIONES | G57: REMUNERACIONES | J57: =+J56+H57-I57 -> 8530757 | L57: =H56 -> 1075839 | M57: =L57*10% -> 107583.9 | O57: =SUM(I58:I65) -> 1277070 | P57: =L57-M57-O57 -> -308814.9
B58: 46269 | C58: 17 | D58: 943 | F58: INSUMOS COMPUTACIONALES | G58: TONER | I58: 213960 | J58: =+J57+H58-I58 -> 8316797
B59: 46269 | C59: 18 | D59: 944 | F59: MOBILIARIO | G59: SILLAS | I59: 210000 | J59: =+J58+H59-I59 -> 8106797
B60: 46269 | C60: 19 | D60: 945 | F60: COLACIONES | G60: COLACIONES | I60: 212310 | J60: =+J59+H60-I60 -> 7894487
B61: 46275 | C61: 20 | D61: 953 | F61: MATERIAL ENSEÑANZA | G61: BALONES | I61: 213840 | J61: =+J60+H61-I61 -> 7680647
B62: 46275 | C62: 21 | D62: 974 | F62: MATERIAL ENSEÑANZA | G62: MATERIALES ENSEÑANZA | I62: 212940 | J62: =+J61+H62-I62 -> 7467707
B63: 46289 | C63: 22 | D63: 1008 | E63: PP | F63: MATERIAL ENSEÑANZA | G63: BALON MEDICINAL | I63: 214020 | J63: =+J62+H63-I63 -> 7253687
J64: =+J63+H64-I64 -> 7253687
J65: =+J64+H65-I65 -> 7253687
B66: OCTUBRE
F67: SUBVENCION | G67: SUBVENCION | H67: =+SUBVENCION!U22+SUBVENCION!V22 -> 0 | J67: =+J65+H67-I67 -> 7253687 | L67: INGRESOS | M67: 10% ADM | N67: RR.HH. | O67: BNS Y SERV | P67: SALDO
F68: REMUNERACIONES | G68: REMUNERACIONES | J68: =J67+H68-I68 -> 7253687 | L68: =H67 -> 0 | M68: =L68*10% -> 0 | O68: =SUM(I69:I74) -> 179820 | P68: =L68-M68-O68 -> -179820
B69: 46296 | C69: 23 | D69: 1055 | F69: MATERIAL ENSEÑANZA | G69: PIZARRA ACRILICA | I69: 179820 | J69: =J68+H69-I69 -> 7073867
J70: =J69+H70-I70 -> 7073867
J71: =J70+H71-I71 -> 7073867
J72: =J71+H72-I72 -> 7073867
J73: =J72+H73-I73 -> 7073867
J74: =J73+H74-I74 -> 7073867
J75: =J74+H75-I75 -> 7073867
B76: NOVIEMBRE
F77: SUBVENCION | G77: SUBVENCION | H77: =+SUBVENCION!W22+SUBVENCION!X22 -> 0 | J77: =+J75+H77-I77 -> 7073867 | L77: INGRESOS | M77: 10% ADM | N77: RR.HH. | O77: BNS Y SERV | P77: SALDO
F78: REMUNERACIONES | G78: REMUNERACIONES | J78: =+J77+H78-I78 -> 7073867
J79: =+J78+H79-I79 -> 7073867
J80: =+J79+H80-I80 -> 7073867
J81: =+J80+H81-I81 -> 7073867
J82: =+J81+H82-I82 -> 7073867
J83: =+J82+H83-I83 -> 7073867
J84: =+J83+H84-I84 -> 7073867
J85: =+J84+H85-I85 -> 7073867
J86: =+J85+H86-I86 -> 7073867
J87: =+J86+H87-I87 -> 7073867
J88: =+J87+H88-I88 -> 7073867
J89: =+J88+H89-I89 -> 7073867
J90: =+J89+H90-I90 -> 7073867
... J100: =+J99+H100-I100 -> 7073867
B101: DICIEMBRE
F102: SUBVENCION | G102: SUBVENCION | H102: =+SUBVENCION!Y22+SUBVENCION!Z22 -> 0 | J102: =+J100+H102-I102 -> 7073867 | L102: INGRESOS | M102: 10% ADM | N102: RR.HH. | O102: BNS Y SERV | P102: SALDO
F103: REMUNERACIONES | G103: REMUNERACIONES | J103: =+J102+H103-I103 -> 7073867
J104: =+J103+H104-I104 -> 7073867
J105: =+J104+H105-I105 -> 7073867
J106: =+J105+H106-I106 -> 7073867
J107: =+J106+H107-I107 -> 7073867
J108: =+J107+H108-I108 -> 7073867
J109: =+J108+H109-I109 -> 7073867
F110: AC | G110: AC | H110: =(H11+H14+H18+H21+H25+H36+H42+H47+H56+H67+H77+H102)*-10% -> -987786.4 | J110: =+J109+H110-I110 -> 6086080.6
B111: x | C111: x | G111: TOTAL | H111: =SUM(H9:H110) -> 10519559 | I111: =SUM(I11:I110) -> 4433478 | J111: =+H111-I111 -> 6086080.6
G116: EJECUCION | H116: INGRESOS | I116: GASTOS | J116: %
...

Sheet G-446
B2: UNIDAD DE FINANZAS DAEM
B3: LEY SEP
B4: ESCUELA: G-446 IRENE MORALES
B5: DIRECTOR: LILIANA BRAVO GONZALEZ
B6: RBD: 3488
B7: SECTOR:
B8: FECHA | C8: SOL | D8: OC | E8: DP | F8: CATEGORIA | G8: DETALLE | H8: INGRESOS | I8: GASTOS | J8: SALDO
G9: SALDO 2025 | H9: ='[1]G-446'!$J$93 -> 4176808.5 | J9: =+H9-I9 -> 4176808.5
B10: ENERO
F11: SUBVENCION | G11: SUBVENCION | H11: =SUBVENCION!C23+SUBVENCION!D23 -> 6183446 | J11: =+J9+H11-I11 -> 10360254 | M11: INGRESOS | N11: 10% ADM | O11: RR.HH. | P11: BNS Y SERV | Q11: SALDO
F12: REMUNERACIONES | G12: REMUNERACIONES | I12: 4413897 | J12: =+J11+H12-I12 -> 5946357.5 | M12: =H11 -> 6183446 | N12: =M12*10% -> 618344.6 | O12: =I12 -> 4413897 | Q12: =M12-N12-O12-P12 -> 1151204.4
F14: SUBVENCION | G14: SUBVENCION | H14: =SUBVENCION!E23+SUBVENCION!F23 -> 5460217 | J14: =+J12+H14-I14 -> 11406574 | M14: INGRESOS | N14: 10% ADM | O14: RR.HH. | P14: BNS Y SERV | Q14: SALDO
F15: REMUNERACIONES | G15: REMUNERACIONES | I15: 4748544 | J15: =+J14+H15-I15 -> 6658030.5 | M15: =H14 -> 5460217 | N15: =M15*10% -> 546021.7 | O15: =I15 -> 4748544 | Q15: =M15-N15-O15 -> 165651.3
J16: =+J15+H16-I16 -> 6658030.5
J17: =+J16+H17-I17 -> 6658030.5
B18: MARZO
F19: SUBVENCION | G19: SUBVENCION | H19: =SUBVENCION!G23+SUBVENCION!H23 -> 5254380 | J19: =+J17+H19-I19 -> 11912410 | M19: INGRESOS | N19: 10% ADM | O19: RR.HH. | P19: BNS Y SERV | Q19: SALDO
F20: REMUNERACIONES | G20: REMUNERACIONES | I20: 4177421 | J20: =+J19+H20-I20 -> 7734989.5 | M20: =H19 -> 5254380 | N20: =M20*10% -> 525438 | O20: =I20 -> 4177421 | P20: =I21 -> 207919 | Q20: =M20-N20-O20-P20 -> 343602
B21: 46092 | C21: 3 | D21: 89 | E21: 383 | F21: MATERIALES ENSEÑANZA | G21: LIBRERÍA | I21: 207919 | J21: =+J20+H21-I21 -> 7527070.5
J22: =+J21+H22-I22 -> 7527070.5
J23: =+J22+H23-I23 -> 7527070.5
J24: =+J23+H24-I24 -> 7527070.5
J25: =+J24+H25-I25 -> 7527070.5
B26: ABRIL
F27: SUBVENCION | G27: SUBVENCION | H27: =SUBVENCION!I23+SUBVENCION!J23 -> 5419443 | J27: =+J25+H27-I27 -> 12946514
G28: REMUNERACIONES | I28: 3961486 | J28: =+J27+H28-I28 -> 8985027.5 | M28: INGRESOS | N28: 10% ADM | O28: RR.HH. | P28: BNS Y SERV | Q28: SALDO
B29: 46120 | C29: 5 | D29: 258 | E29: 611 | F29: MATERIALES ENSEÑANZA | G29: LIBRERÍA | I29: 206822 | J29: =+J28+H29-I29 -> 8778205.5 | M29: =H27 -> 5419443 | N29: =H27*10% -> 541944.3 | O29: =I28 -> 3961486 | P29: =I29 -> 206822 | Q29: =M29-N29-O29-P29 -> 709190.7
B30: 46139 | C30: 7 | D30: 363 | E30: 754 | F30: COLACIONES | G30: COLACIONES | I30: 208845 | J30: =+J29+H30-I30 -> 8569360.5
B31: MAYO
F32: SUBVENCION | G32: SUBVENCION | H32: =SUBVENCION!K23+SUBVENCION!L23 -> 5719278 | J32: =+J30+H32-I32 -> 14288638 | M32: INGRESOS | N32: 10% ADM | O32: RR.HH. | P32: BNS Y SERV | Q32: SALDO
G33: REMUNERACIONES | I33: 3947635 | J33: =+J32+H33-I33 -> 10341004 | M33: =H32 -> 5719278 | N33: =M33*10% -> 571927.8 | O33: =I33 -> 3947635 | P33: =#REF! -> #REF! | Q33: =M33-N33-O33-P33 -> #REF!
J34: =+J33+H34-I34 -> 10341004
B35: JUNIO
F36: SUBVENCION | G36: SUBVENCION | H36: =SUBVENCION!M23+SUBVENCION!N23 -> 6810722 | J36: =+J34+H36-I36 -> 17151726 | M36: INGRESOS | N36: 10% ADM | O36: RR.HH. | P36: BNS Y SERV | Q36: SALDO
F37: REMUNERACIONES | G37: REMUNERACIONES | I37: 4319935 | J37: =+J36+H37-I37 -> 12831790 | M37: =H36 -> 6810722 | N37: =M37*10% -> 681072.2 | O37: =I37 -> 4319935 | P37: =I38+I39+I40 -> 1804228 | Q37: =M37-N37-O37-P37 -> 5486.8
B38: 46176 | C38: 8 | D38: 541 | E38: 972 | F38: MATERIALES ENSEÑANZA | G38: LIBRERÍA | I38: 116818 | J38: =+J37+H38-I38 -> 12714972
B39: 46176 | C39: 9 | D39: 542 | E39: 972 | F39: MATERIALES ENSEÑANZA | G39: MATERIALES ENSEÑANZA | I39: 87411 | J39: =+J38+H39-I39 -> 12627562
B40: 46182 | C40: 10 | D40: 2321-182-AG26 | E40: 1071 | F40: NOTEBOOK E IMPRESORA | G40: NOTEBOOK E IMPRESORA | I40: 1599999 | J40: =+J39+H40-I40 -> 11027562
B41: JULIO
F42: SUBVENCION | G42: SUBVENCION | H42: =+SUBVENCION!O23+SUBVENCION!P23 -> 5774050 | J42: =+J40+H42-I42 -> 16801612 | M42: INGRESOS | N42: 10% ADM | O42: RR.HH. | P42: BNS Y SERV | Q42: SALDO
F43: REMUNERACIONES | G43: REMUNERACIONES | I43: 4018879 | J43: =+J42+H43-I43 -> 12782734 | M43: =H42 -> 5774050 | N43: =M43*10% -> 577405 | O43: =I43 -> 4018879 | P43: =I44+I45 -> 297958 | Q43: =M43-N43-O43-P43 -> 879808
B44: 46211 | C44: 12 | D44: 630 | E44: 1157 | F44: INSUMOS COMPUTACIONALES | G44: TINTAS | I44: 147998 | J44: =+J43+H44-I44 -> 12634736
B45: 46226 | C45: 15 | D45: 703 | E45: 1217 | F45: MATERIALES ENSEÑANZA | G45: LIBRERÍA | I45: 149960 | J45: =+J44+H45-I45 -> 12484776
J46: =+J45+H46-I46 -> 12484776
B47: AGOSTO
F48: SUBVENCION | G48: SUBVENCION | H48: =+SUBVENCION!Q23+SUBVENCION!R23 -> 5509175 | J48: =+J46+H48-I48 -> 17993950 | M48: INGRESOS | N48: 10% ADM | O48: RR.HH. | P48: BNS Y SERV | Q48: SALDO
F49: REMUNERACIONES | G49: REMUNERACIONES | I49: 4368958 | J49: =+J48+H49-I49 -> 13624992 | M49: =H48 -> 5509175 | N49: =M49*10% -> 550917.5 | O49: =I49 -> 4368958 | P49: =I50+I51 -> 366525 | Q49: =M49-N49-O49-P49 -> 222774.5
B50: 46238 | C50: 17 | D50: 742 | E50: 1255 | F50: MATERIALES ENSEÑANZA | G50: MANUALIDADES | I50: 152325 | J50: =+J49+H50-I50 -> 13472668
B51: 46260 | C51: 20 | D51: 905 | F51: COLACIONES | G51: COLACIONES | I51: 214200 | J51: =+J50+H51-I51 -> 13258468
J52: =+J51+H52-I52 -> 13258468
B53: SEPTIEMBRE
F54: SUBVENCION | G54: SUBVENCION | H54: =+SUBVENCION!S23+SUBVENCION!T23 -> 5500202 | J54: =+J52+H54-I54 -> 18758670 | M54: INGRESOS | N54: 10% ADM | O54: RR.HH. | P54: BNS Y SERV | Q54: SALDO
F55: REMUNERACIONES | G55: REMUNERACIONES | I55: 4708006 | J55: =+J54+H55-I55 -> 14050664 | M55: =H54 -> 5500202 | N55: =M55*10% -> 550020.2 | O55: =I55 -> 4708006 | P55: =SUM(I56:I61) -> 830220 | Q55: =M55-N55-O55-P55 -> -588044.2
B56: 46267 | C56: 21 | D56: 818 | F56: TRASLADO | G56: TRASLADO | I56: 100000 | J56: =+J55+H56-I56 -> 13950664
B57: 46268 | C57: 22 | D57: 926 | F57: TRASLADO | G57: TRASLADO | I57: 200000 | J57: =+J56+H57-I57 -> 13750664
B58: 46056 | C58: 24 | D58: 927 | F58: MATERIALES ENSEÑANZA | G58: TELAS | I58: 120000 | J58: =+J57+H58-I58 -> 13630664
B59: 46287 | C59: 25 | D59: 990 | E59: PP | F59: MATERIALES ENSEÑANZA | G59: LIBRERÍA | I59: 199980 | J59: =+J58+H59-I59 -> 13430684
B60: 46293 | C60: 26 | D60: 1022 | F60: COLACIONES | G60: COLACIONES | I60: 210240 | J60: =+J59+H60-I60 -> 13220444
J61: =+J60+H61-I61 -> 13220444
B62: OCTUBRE
F63: SUBVENCION | G63: SUBVENCION | H63: =+SUBVENCION!U23+SUBVENCION!V23 -> 0 | J63: =+J61+H63-I63 -> 13220444 | M63: INGRESOS | N63: 10% ADM | O63: RR.HH. | P63: BNS Y SERV | Q63: SALDO
F64: REMUNERACIONES | G64: REMUNERACIONES | J64: =+J63+H64-I64 -> 13220444 | M64: =H63 -> 0 | N64: =M64*10% -> 0 | O64: =I64 -> 0 | P64: =SUM(I65:I72) -> 0 | Q64: =M64-N64-O64-P64 -> 0
J65: =+J64+H65-I65 -> 13220444
J66: =+J65+H66-I66 -> 13220444
J67: =+J66+H67-I67 -> 13220444
J68: =+J67+H68-I68 -> 13220444
J69: =+J68+H69-I69 -> 13220444
J70: =+J69+H70-I70 -> 13220444
J71: =+J70+H71-I71 -> 13220444
J72: =+J71+H72-I72 -> 13220444
B73: NOVIEMBRE
F74: SUBVENCION | G74: SUBVENCION | H74: =+SUBVENCION!W23+SUBVENCION!X23 -> 0 | J74: =+J72+H74-I74 -> 13220444 | M74: INGRESOS | N74: 10% ADM | O74: RR.HH. | P74: BNS Y SERV | Q74: SALDO
F75: REMUNERACIONES | G75: REMUNERACIONES | J75: =+J74+H75-I75 -> 13220444
J76: =+J75+H76-I76 -> 13220444
J77: =+J76+H77-I77 -> 13220444
J78: =+J77+H78-I78 -> 13220444
J79: =+J78+H79-I79 -> 13220444
J80: =+J79+H80-I80 -> 13220444
J81: =+J80+H81-I81 -> 13220444
J82: =+J81+H82-I82 -> 13220444
J83: =+J82+H83-I83 -> 13220444
J84: =+J83+H84-I84 -> 13220444
J85: =+J84+H85-I85 -> 13220444
J86: =+J85+H86-I86 -> 13220444
B87: DICIEMBRE
F88: SUBVENCION | G88: SUBVENCION | H88: =+SUBVENCION!Y23+SUBVENCION!Z23 -> 0 | J88: =+J86+H88-I88 -> 13220444
F89: REMUNERACIONES | G89: REMUNERACIONES | J89: =+J88+H89-I89 -> 13220444 | M89: INGRESOS | N89: 10% ADM | O89: RR.HH. | P89: BNS Y SERV | Q89: SALDO
J90: =+J89+H90-I90 -> 13220444
J91: =+J90+H91-I91 -> 13220444
J92: =+J91+H92-I92 -> 13220444
J93: =+J92+H93-I93 -> 13220444
F94: AC | G94: AC | H94: =(H11+H14+H19+H27+H32+H36+H42+H48+H54+H63+H74+H88)*-10% -> -5163091.3 | J94: =+J93+H94-I94 -> 8057352.2
B95: x | C95: x | G95: TOTAL | H95: =SUM(H9:H94) -> 50644630 | I95: =SUM(I11:I94) -> 42587278 | J95: =+H95-I95 -> 8057352.2
G100: EJECUCION | H100: INGRESOS | I100: GASTOS | J100: %
H101: =+H95 -> 50644630 | I101: =+I95 -> 42587278 | J101: =+I101*100/H101 -> 84.090412

Sheet G-469
B2: UNIDAD DE FINANZAS DAEM
B3: LEY SEP
B4: ESCUELA: G-469 CAMILA MATTA VIAL
B5: DIRECTOR: FLORIN URIBE
B6: RBD: 3527
B7: SECTOR:
B8: FECHA | C8: SOL | D8: OC | E8: DP | F8: CATEGORIA | G8: DETALLE | H8: INGRESOS | I8: GASTOS | J8: SALDO
G9: SALDO 2025 | H9: ='[1]G-469'!$J$69 -> -71783.1 | J9: =+H9-I9 -> -71783.1
B10: ENERO
F11: SUBVENCION | G11: SUBVENCION | H11: =SUBVENCION!C24 -> 491656 | J11: =+H11-I11 -> 491656 | L11: INGRESOS | M11: 10% ADM | N11: RR.HH. | O11: BNS Y SERV | P11: SALDO
L12: =H11 -> 491656 | M12: =L12*10% -> 49165.6 | N12: 0 | P12: =L12-M12-N12-O12 -> 442490.4
B13: FEBRERO
F14: SUBVENCION | G14: SUBVENCION | H14: =SUBVENCION!E24 -> 521146 | J14: =+J11+H14-I14 -> 1012802 | L14: INGRESOS | M14: 10% ADM | N14: RR.HH. | O14: BNS Y SERV | P14: SALDO
L15: =H14 -> 521146 | M15: =L15*10% -> 52114.6 | N15: 0 | P15: =L15-M15-N15-O15 -> 469031.4
B16: MARZO
F17: SUBVENCION | G17: SUBVENCION | H17: =SUBVENCION!G24 -> 501486 | J17: =+J14+H17-I17 -> 1514288 | L17: INGRESOS | M17: 10% ADM | N17: RR.HH. | O17: BNS Y SERV | P17: SALDO
B18: 46112 | C18: 3 | D18: 202 | E18: 418 | F18: INSUMO COMPUTACIONALES | G18: TONER | I18: 195160 | J18: =+J17+H18-I18 -> 1319128 | L18: =H17 -> 501486 | M18: =H17*10% -> 50148.6 | N18: 0 | P18: =L18-M18-N18-O18 -> 451337.4
J19: =+J18+H19-I19 -> 1319128
J20: =+J19+H20-I20 -> 1319128
B21: ABRIL
F22: SUBVENCION | G22: SUBVENCION | H22: =SUBVENCION!I24 -> 417905 | J22: =+J20+H22-I22 -> 1737033 | L22: INGRESOS | M22: 10% ADM | N22: RR.HH. | O22: BNS Y SERV | P22: SALDO
J23: =+J22+H23-I23 -> 1737033 | L23: =H22 -> 417905 | M23: =L23*10% -> 41790.5 | N23: 0 | O23: =I24 -> 207300 | P23: =L23-M23-N23-O23 -> 168814.5
B24: 46118 | C24: 4 | D24: 227 | E24: 402 | F24: MATERIALES ENSEÑANZA | G24: LIBRERÍA | I24: 207300 | J24: =+J23+H24-I24 -> 1529733
J25: =+J24+H25-I25 -> 1529733
B26: MAYO
